Workbook

Sheet ANALISE PRODUTO
E1: =TEXT(COUNT(D3:D10000), "#.###") & " SKU" | R1: =TEXT(COUNTIFS(D3:D10000,">0",S3:S10000,"S"), "#.###") & " SKU FL" | U1: =SUBTOTAL(9,U3:U10000) | V1: =SUBTOTAL(9,V3:V10000) | AA1: =SUBTOTAL(9,AA3:AA10000) | AB1: =SUBTOTAL(9,AB3:AB10000) | AC1: =SUBTOTAL(9,AC3:AC10000) | AJ1: =SUBTOTAL(9,AJ3:AJ10000) | AN1: =SUBTOTAL(9,AN3:AN10000) | AO1: =SUBTOTAL(9,AO3:AO10000) | AP1: =SUBTOTAL(9,AP3:AP10000) | AQ1: =SUBTOTAL(9,AQ3:AQ10000) | AR1: =SUBTOTAL(9,AR3:AR10000) | AS1: =SUBTOTAL(9,AS3:AS10000) | AT1: =SUBTOTAL(9,AT3:AT10000) | AU1: =IFERROR((SUBTOTAL(9,AN3:AN10000)/SUBTOTAL(9,AJ3:AJ10000)), 0) | AV1: =IFERROR(((SUBTOTAL(9,AO3:AO10000)) / SUBTOTAL(9,AJ3:AJ10000)), 0) | AX1: =SUBTOTAL(9,AX3:AX10000) | AZ1: {=SUMPRODUCT(SUBTOTAL(9,OFFSET(AZ3,ROW(AZ3:AZ10000)-ROW(AZ3),0,1)),--(AZ3:AZ10000>0))} | BA1: =SUBTOTAL(9,BA3:BA10000) | BB1: =SUBTOTAL(9,BB3:BB10000) | BC1: =SUBTOTAL(9,BC3:BC10000) | BD1: =SUBTOTAL(9,BD3:BD10000) | BE1: =SUBTOTAL(101,BE3:BE10000) | BF1: =SUBTOTAL(101,BF3:BF10000) | BH1: =SUBTOTAL(9,BH3:BH10000) | BI1: =SUBTOTAL(9,BI3:BI10000) | BJ1: =SUBTOTAL(9,BJ3:BJ10000) | BK1: =SUBTOTAL(9,BK3:BK10000) | BL1: =SUBTOTAL(9,BL3:BL10000) | BM1: =SUBTOTAL(101,BM3:BM10000) | BN1: =SUBTOTAL(9,BN3:BN10000) | BO1: =SUBTOTAL(9,BO3:BO10000) | BP1: =SUBTOTAL(9,BP3:BP10000) | BQ1: =SUBTOTAL(9,BQ3:BQ10000) | BR1: =SUBTOTAL(9,BR3:BR5706) | BS1: =SUBTOTAL(9,BS3:BS10000) | BT1: =SUBTOTAL(9,BT3:BT10000) | BU1: =SUBTOTAL(9,BU3:BU10000) | BV1: =SUBTOTAL(9,BV3:BV10000) | BW1: =SUBTOTAL(9,BW3:BW10000) | CB1: =SUBTOTAL(9,CB3:CB10000) | CC1: =SUBTOTAL(9,CC3:CC10000)
A2: Filial | B2: BARRAS | C2: CODIGO PRINCIPAL | D2: Código Produto | E2: DESCRIÇÃO | F2: COD. FORNEC | G2: FORNECEDOR | H2: COMPRADOR | I2: COD COMPRADOR | J2: COD. MARCA | K2: MARCA | L2: COD. DEP. | M2: DEPARTAMENTO | N2: COD. SESSÃO | O2: SESSÃO | P2: COD. LINHA | Q2: LINHA | R2: CURVA ABC | S2: FORA DE LINHA | T2: CLASSE | U2: ESTOQUE DISPONÍVEL | V2: QUANTIDADE PEDIDA PENDENTE | X2: AVARIADO | Y2: BLOQUEADO | Z2: RESERVADO | AA2: QUANTIDADE VENDIDA TRI | AB2: GIRO MÉDIO MENSAL | AC2: GIRO DIA | AD2: DATA ULTIMA ENTRADA | AE2: POSITIVAÇÃO | AF2: PREÇO PEDIDO COMPRA | AG2: CUSTO REAL | AH2: CUSTO REAL SEM ST | AI2: PREÇO MÉDIO VENDA | AJ2: VALOR MEDIA VENDA MÊS | AK2: MÊS P/ RUPTURA | AL2: MÉDIA IDEAL ESTOQUE | AM2: MÊS P/ EXCESSO | AN2: VALOR ESTOQUE PREÇO VENDA | AO2: VALOR ESTOQUE PREÇO VENDA + PENDÊNCIA | AP2: VALOR ESTOQUE PREÇO CUSTO | AQ2: VALOR ESTOQUE PREÇO CUSTO + PENDÊNCIA | AR2: ESTOQUE VALOR A | AS2: ESTOQUE VALOR B | AT2: ESTOQUE VALOR C | AU2: MÊS S/ PENDÊNCIA | AV2: MÊS + PENDÊNCIA | AW2: ESTOQUE IDEAL UND | AX2: ESTOQUE IDEAL CUSTO VALOR | AY2: ESTOQUE LIMITE RUPTURA UND | AZ2: RUPTURA UND | BA2: RUPTURA VALOR | BB2: Ruptura Valor A | BC2: Ruptura Valor B | BD2: Ruptura Valor C | BE2: NIVEL SERVIÇO RUPTURA S/ PENDÊNCIA | BF2: NIVEL SERVIÇO RUPTURA C/ PENDÊNCIA | BG2: ESTOQUE LIMITE P/ EXCESSO | BH2: EXCESSO UND | BI2: EXCESSO VALOR | BJ2: EXCESSO VALOR A | BK2: EXCESSO VALOR B | BL2: EXCESSO VALOR C | BM2: NÍVEL DE EXCESSO | BN2: VENDA MÉDIA MÊS (CUSTO) | BO2: ESTOQUE ATUAL + DEMANDA (CUSTO) | BP2: ESTOQUE IDEAL (CUSTO) | BQ2: COMPRA MÊS ATUAL (CUSTO) | BR2: COMPRA PRÓXIMO MÊS (CUSTO) | BS2: VENDA MÉDIA MÊS (VENDA) | BT2: ESTOQUE ATUAL + DEMANDA (VENDA) | BU2: ESTOQUE IDEAL (VENDA) | BV2: COMPRA MÊS ATUAL (VENDA) | BW2: COMPRA PRÓXIMO MÊS (VENDA) | BX2: DATA ÚLTIMO PEDIDO | BY2: DATA CADASTRO PRODUTO | BZ2: COMISSÃO INTERNA | CA2: COMISSÃO EXTERNA | CB2: PEDIDO PENDENTE A PREÇO COMPRA | CC2: PEDIDO PENDENTE A PREÇO VENDA | CD2: PREÇO TABELA
A3: =IF(D3="","",VLOOKUP(D3,'produto-estoque-total-7'!A:AB,3,0)) | B3: =IF(D3="","",VLOOKUP(D3,'produto-estoque-total-7'!A:AB,12,0)) | C3: =IF(D3="","",VLOOKUP(D3,'produto-estoque-total-7'!A:AB,2,0)) | D3: =IFERROR(IF('produto-estoque-total-7'!A2="","",'produto-estoque-total-7'!A2),"") | E3: =IF(D3="","",VLOOKUP(D3,'produto-estoque-total-7'!A:AB,4,0)) | F3: =IF(D3="","",VLOOKUP(D3,'produto-estoque-total-7'!A:AB,13,0)) | G3: =IF(F3="","",VLOOKUP(F3,'FORNECEDORES X COMPRADOR'!A:D,4,0)) | H3: =IF(F3="","",VLOOKUP(F3,'FORNECEDORES X COMPRADOR'!A:E,5,0)) | I3: =IF(D3="","",VLOOKUP(D3,'produto-estoque-total-7'!A:AB,15,0)) | J3: =IF(D3="","",VLOOKUP(D3,'produto-estoque-total-7'!A:AB,19,0)) | K3: =IF(D3="","",VLOOKUP(D3,'produto-estoque-total-7'!A:AB,20,0)) | L3: =IF(D3="","",VLOOKUP(D3,'produto-estoque-total-7'!A:AB,17,0)) | M3: =IF(D3="","",VLOOKUP(D3,'produto-estoque-total-7'!A:AB,18,0)) | N3: =IF(D3="","",VLOOKUP(D3,'produto-estoque-total-7'!A:AB,21,0)) | O3: =IF(D3="","",VLOOKUP(D3,'produto-estoque-total-7'!A:AB,22,0)) | P3: =IF(D3="","",VLOOKUP(D3,'produto-estoque-total-7'!A:AB,23,0)) | Q3: =IF(D3="","",VLOOKUP(D3,'produto-estoque-total-7'!A:AB,24,0)) | R3: =IFERROR(IF(D3="","",VLOOKUP(D3,'produto-venda-7'!B:N,13,0)),"C") | S3: =IF(D3="","",VLOOKUP(D3,'produto-estoque-total-7'!A:AB,6,0)) | T3: =IF(D3="","",VLOOKUP(D3,'produto-estoque-total-7'!A:AB,5,0)) | U3: =IF(D3="","",VLOOKUP(D3,'produto-estoque-total-7'!A:AB,11,0)) | V3: =IF(D3="","",IFERROR(VLOOKUP(D3,'produto-entrada-7'!A:M,10,0),0)) | X3: =IF(D3="","",VLOOKUP(D3,'produto-estoque-total-7'!A:AB,8,0)) | Y3: =IF(D3="","",VLOOKUP(D3,'produto-estoque-total-7'!A:AB,9,0)) | Z3: =IF(D3="","",VLOOKUP(D3,'produto-estoque-total-7'!A:AB,10,0)) | AA3: =IFERROR(IF(D3="","",VLOOKUP(D3,'produto-venda-7'!B:N,4,0)),0) | AB3: =IFERROR(IF(D3="","",VLOOKUP(D3,'produto-venda-7'!B:N,5,0)),0) | AC3: =IF(D3="","",IFERROR(AA3/90,0)) | AD3: =IF(D3="","",IFERROR(VLOOKUP(D3,'produto-entrada-7'!A:M,4,0),0)) | AE3: =IFERROR(IF(D3="","",VLOOKUP(D3,'produto-venda-7'!B:N,10,0)),0) | AF3: =IF(D3="","",IFERROR(VLOOKUP(D3,'produto-entrada-7'!A:M,11,0),0)) | AG3: =IF(D3="","",IFERROR(VLOOKUP(D3,'produto-entrada-7'!A:M,12,0),0)) | AH3: =IF(D3="","",IFERROR(VLOOKUP(D3,'produto-entrada-7'!A:M,13,0),0)) | AI3: =IFERROR(IF(D3="","",VLOOKUP(D3,'produto-venda-7'!B:N,11,0)),0) | AJ3: =IF(D3="","",IFERROR(AI3*AB3,0)) | AK3: =IFERROR(IF(D3="","",VLOOKUP(F3,'ANALISE FORNECEDOR'!$A:$I,8,0)),"") | AL3: =IF(D3="","",AVERAGE(AM3,AK3)) | AM3: =IFERROR(IF(D3="","",VLOOKUP(F3,'ANALISE FORNECEDOR'!$A:$I,9,0)),"") | AN3: =IF(D3="","",IF(Y3>12,AI3*(U3+Y3),AI3*U3)) | AO3: =IF(D3="","",IF(Y3>12,AI3*(U3+V3+Y3),AI3*(U3+V3))) | AP3: =IF(D3="","",IF(Y3>12,AG3*(U3+Y3),AG3*U3)) | AQ3: =IF(D3="","",IF(Y3>12,AG3*(U3+V3+Y3),AG3*(U3+V3))) | AR3: =IF(D3="","",IF(OR(R3="A",R3="AA",R3="AAA"),AP3,0)) | AS3: =IF(D3="","",IF(R3="B",AP3,0)) | AT3: =IF(D3="","",IF(R3="C",AP3,0)) | AU3: =IF(D3="","",IFERROR(AN3/AJ3,0)) | AV3: =IF(D3="","",IFERROR(((AO3)/AJ3),0)) | AW3: =IF(D3="","",IF(OR(S3="S",NOT(AND(ISNUMBER(AC3),ISNUMBER(AL3),AC3*AL3>=0))),0,AC3*AL3)) | AX3: =IFERROR(IF(D3="","",AW3*AG3),0) | AY3: =IF(D3="","",IF(OR(S3="S",NOT(AND(ISNUMBER(AC3),ISNUMBER(AK3),AC3*AK3>=0))),0,AC3*AK3)) | AZ3: =IFERROR(IF(D3="","",IF(AY3=0,0,IF(((AY3)-(U3+Y3))<0,0,(AY3)-U3))),0) | BA3: =IF(D3="","",AZ3*AG3) | BB3: =IF(D3="","",IF(OR(R3="A",R3="AA",R3="AAA"),BA3,0)) | BC3: =IF(D3="","",IF(R3="B",BA3,0)) | BD3: =IF(D3="","",IF(R3="B",BA3,0)) | BE3: =IF(D3="","",IF(S3="S", 1, IF(AC3=0, 1, IF( IFERROR(((U3+Y3)*AG3)/((AC3*AK3)*AG3),0)<0, 0, IF( IFERROR(((U3+Y3)*AG3)/((AC3*AK3)*AG3),0)>1, 1, IFERROR(((U3+Y3)*AG3)/((AC3*AK3)*AG3),0) ) ) ) )) | BF3: =IF(D3="","",IF(S3="S", 1, IF(AC3=0, 1, IF( IFERROR(((U3+V3+Y3)*AG3)/((AC3*AK3)*AG3),0)<0, 0, IF( IFERROR(((U3+V3+Y3)*AG3)/((AC3*AK3)*AG3),0)>1, 1, IFERROR(((U3+V3+Y3)*AG3)/((AC3*AK3)*AG3),0) ) ) ) )) | BG3: =IF(D3="","",IF(S3="S",0,IF(AND(ISNUMBER(AC3),ISNUMBER(AM3)),IF(OR(AC3*AM3<0,ISERR(AC3*AM3)),0,AC3*AM3),0))) | BH3: =IF(D3="","",IF(BY3>TODAY()-60,0,IF(Y3>12,MAX(0,(U3+Y3)-BG3),MAX(0,U3-BG3)))) | BI3: =IF(D3="","",BH3*AG3) | BJ3: =IF(D3="","",IF(OR(R3="A",R3="AA",R3="AAA"),BI3,0)) | BK3: =IF(D3="","",IF(R3="B",BI3,0)) | BL3: =IF(D3="","",IF(R3="C",BI3,0)) | BM3: =IF(D3="","",IFERROR(MAX(0,MIN(BI3/AP3,1)),0)) | BN3: =IF(D3="","",AB3*AG3) | BO3: =IF(D3="","",(U3+V3+X3)*AG3) | BP3: =IF(D3="","",(AB3*3)*AG3) | BQ3: =IF(D3="","",IF(BO3-BP3>0,0,BO3-BP3)) | BR3: =IF(D3="","",IF(BO3-BP3-BN3>0,0,BO3-BP3-BN3)) | BS3: =IF(D3="","",IFERROR(AB3*AI3,0)) | BT3: =IF(D3="","",IFERROR(IF(X3>12, AI3*(U3+V3+X3), AI3*(U3+V3)),0)) | BU3: =IF(D3="","",IFERROR(((AB3*3)*AI3),0)) | BV3: =IF(D3="","",IF(BT3-BU3>0,0,BT3-BU3)) | BW3: =IF(D3="","",IF(BT3-BU3-BS3>0,0,BT3-BU3-BS3)) | BX3: =IF(D3="","",IFERROR(VLOOKUP(D3,'produto-entrada-7'!A:M,3,0),"SEM PEDIDO")) | BY3: =IF(D3="","",VLOOKUP(D3,'produto-estoque-total-7'!A:AB,25,0)) | BZ3: =IF(D3="","",IFERROR(VLOOKUP(D3,'produto-estoque-total-7'!A:AB,26,0)/100,0)) | CA3: =IF(D3="","",IFERROR(VLOOKUP(D3,'produto-estoque-total-7'!A:AB,27,0)/100,0)) | CB3: =IF(D3="","",V3*AF3) | CC3: =IF(D3="","",V3*AI3) | CD3: =IF(D3="","",VLOOKUP(D3,'produto-estoque-total-7'!A:AB,28,0))
A4: =IF(D4="","",VLOOKUP(D4,'produto-estoque-total-7'!A:AB,3,0)) | B4: =IF(D4="","",VLOOKUP(D4,'produto-estoque-total-7'!A:AB,12,0)) | C4: =IF(D4="","",VLOOKUP(D4,'produto-estoque-total-7'!A:AB,2,0)) | D4: =IFERROR(IF('produto-estoque-total-7'!A3="","",'produto-estoque-total-7'!A3),"") | E4: =IF(D4="","",VLOOKUP(D4,'produto-estoque-total-7'!A:AB,4,0)) | F4: =IF(D4="","",VLOOKUP(D4,'produto-estoque-total-7'!A:AB,13,0)) | G4: =IF(F4="","",VLOOKUP(F4,'FORNECEDORES X COMPRADOR'!A:D,4,0)) | H4: =IF(F4="","",VLOOKUP(F4,'FORNECEDORES X COMPRADOR'!A:E,5,0)) | I4: =IF(D4="","",VLOOKUP(D4,'produto-estoque-total-7'!A:AB,15,0)) | J4: =IF(D4="","",VLOOKUP(D4,'produto-estoque-total-7'!A:AB,19,0)) | K4: =IF(D4="","",VLOOKUP(D4,'produto-estoque-total-7'!A:AB,20,0)) | L4: =IF(D4="","",VLOOKUP(D4,'produto-estoque-total-7'!A:AB,17,0)) | M4: =IF(D4="","",VLOOKUP(D4,'produto-estoque-total-7'!A:AB,18,0)) | N4: =IF(D4="","",VLOOKUP(D4,'produto-estoque-total-7'!A:AB,21,0)) | O4: =IF(D4="","",VLOOKUP(D4,'produto-estoque-total-7'!A:AB,22,0)) | P4: =IF(D4="","",VLOOKUP(D4,'produto-estoque-total-7'!A:AB,23,0)) | Q4: =IF(D4="","",VLOOKUP(D4,'produto-estoque-total-7'!A:AB,24,0)) | R4: =IFERROR(IF(D4="","",VLOOKUP(D4,'produto-venda-7'!B:N,13,0)),"C") | S4: =IF(D4="","",VLOOKUP(D4,'produto-estoque-total-7'!A:AB,6,0)) | T4: =IF(D4="","",VLOOKUP(D4,'produto-estoque-total-7'!A:AB,5,0)) | U4: =IF(D4="","",VLOOKUP(D4,'produto-estoque-total-7'!A:AB,11,0)) | V4: =IF(D4="","",IFERROR(VLOOKUP(D4,'produto-entrada-7'!A:M,10,0),0)) | X4: =IF(D4="","",VLOOKUP(D4,'produto-estoque-total-7'!A:AB,8,0)) | Y4: =IF(D4="","",VLOOKUP(D4,'produto-estoque-total-7'!A:AB,9,0)) | Z4: =IF(D4="","",VLOOKUP(D4,'produto-estoque-total-7'!A:AB,10,0)) | AA4: =IFERROR(IF(D4="","",VLOOKUP(D4,'produto-venda-7'!B:N,4,0)),0) | AB4: =IFERROR(IF(D4="","",VLOOKUP(D4,'produto-venda-7'!B:N,5,0)),0) | AC4: =IF(D4="","",IFERROR(AA4/90,0)) | AD4: =IF(D4="","",IFERROR(VLOOKUP(D4,'produto-entrada-7'!A:M,4,0),0)) | AE4: =IFERROR(IF(D4="","",VLOOKUP(D4,'produto-venda-7'!B:N,10,0)),0) | AF4: =IF(D4="","",IFERROR(VLOOKUP(D4,'produto-entrada-7'!A:M,11,0),0)) | AG4: =IF(D4="","",IFERROR(VLOOKUP(D4,'produto-entrada-7'!A:M,12,0),0)) | AH4: =IF(D4="","",IFERROR(VLOOKUP(D4,'produto-entrada-7'!A:M,13,0),0)) | AI4: =IFERROR(IF(D4="","",VLOOKUP(D4,'produto-venda-7'!B:N,11,0)),0) | AJ4: =IF(D4="","",IFERROR(AI4*AB4,0)) | AK4: =IFERROR(IF(D4="","",VLOOKUP(F4,'ANALISE FORNECEDOR'!$A:$I,8,0)),"") | AL4: =IF(D4="","",AVERAGE(AM4,AK4)) | AM4: =IFERROR(IF(D4="","",VLOOKUP(F4,'ANALISE FORNECEDOR'!$A:$I,9,0)),"") | AN4: =IF(D4="","",IF(Y4>12,AI4*(U4+Y4),AI4*U4)) | AO4: =IF(D4="","",IF(Y4>12,AI4*(U4+V4+Y4),AI4*(U4+V4))) | AP4: =IF(D4="","",IF(Y4>12,AG4*(U4+Y4),AG4*U4)) | AQ4: =IF(D4="","",IF(Y4>12,AG4*(U4+V4+Y4),AG4*(U4+V4))) | AR4: =IF(D4="","",IF(OR(R4="A",R4="AA",R4="AAA"),AP4,0)) | AS4: =IF(D4="","",IF(R4="B",AP4,0)) | AT4: =IF(D4="","",IF(R4="C",AP4,0)) | AU4: =IF(D4="","",IFERROR(AN4/AJ4,0)) | AV4: =IF(D4="","",IFERROR(((AO4)/AJ4),0)) | AW4: =IF(D4="","",IF(OR(S4="S",NOT(AND(ISNUMBER(AC4),ISNUMBER(AL4),AC4*AL4>=0))),0,AC4*AL4)) | AX4: =IFERROR(IF(D4="","",AW4*AG4),0) | AY4: =IF(D4="","",IF(OR(S4="S",NOT(AND(ISNUMBER(AC4),ISNUMBER(AK4),AC4*AK4>=0))),0,AC4*AK4)) | AZ4: =IFERROR(IF(D4="","",IF(AY4=0,0,IF(((AY4)-(U4+Y4))<0,0,(AY4)-U4))),0) | BA4: =IF(D4="","",AZ4*AG4) | BB4: =IF(D4="","",IF(OR(R4="A",R4="AA",R4="AAA"),BA4,0)) | BC4: =IF(D4="","",IF(R4="B",BA4,0)) | BD4: =IF(D4="","",IF(R4="B",BA4,0)) | BE4: =IF(D4="","",IF(S4="S", 1, IF(AC4=0, 1, IF( IFERROR(((U4+Y4)*AG4)/((AC4*AK4)*AG4),0)<0, 0, IF( IFERROR(((U4+Y4)*AG4)/((AC4*AK4)*AG4),0)>1, 1, IFERROR(((U4+Y4)*AG4)/((AC4*AK4)*AG4),0) ) ) ) )) | BF4: =IF(D4="","",IF(S4="S", 1, IF(AC4=0, 1, IF( IFERROR(((U4+V4+Y4)*AG4)/((AC4*AK4)*AG4),0)<0, 0, IF( IFERROR(((U4+V4+Y4)*AG4)/((AC4*AK4)*AG4),0)>1, 1, IFERROR(((U4+V4+Y4)*AG4)/((AC4*AK4)*AG4),0) ) ) ) )) | BG4: =IF(D4="","",IF(S4="S",0,IF(AND(ISNUMBER(AC4),ISNUMBER(AM4)),IF(OR(AC4*AM4<0,ISERR(AC4*AM4)),0,AC4*AM4),0))) | BH4: =IF(D4="","",IF(BY4>TODAY()-60,0,IF(Y4>12,MAX(0,(U4+Y4)-BG4),MAX(0,U4-BG4)))) | BI4: =IF(D4="","",BH4*AG4) | BJ4: =IF(D4="","",IF(OR(R4="A",R4="AA",R4="AAA"),BI4,0)) | BK4: =IF(D4="","",IF(R4="B",BI4,0)) | BL4: =IF(D4="","",IF(R4="C",BI4,0)) | BM4: =IF(D4="","",IFERROR(MAX(0,MIN(BI4/AP4,1)),0)) | BN4: =IF(D4="","",AB4*AG4) | BO4: =IF(D4="","",(U4+V4+X4)*AG4) | BP4: =IF(D4="","",(AB4*3)*AG4) | BQ4: =IF(D4="","",IF(BO4-BP4>0,0,BO4-BP4)) | BR4: =IF(D4="","",IF(BO4-BP4-BN4>0,0,BO4-BP4-BN4)) | BS4: =IF(D4="","",IFERROR(AB4*AI4,0)) | BT4: =IF(D4="","",IFERROR(IF(X4>12, AI4*(U4+V4+X4), AI4*(U4+V4)),0)) | BU4: =IF(D4="","",IFERROR(((AB4*3)*AI4),0)) | BV4: =IF(D4="","",IF(BT4-BU4>0,0,BT4-BU4)) | BW4: =IF(D4="","",IF(BT4-BU4-BS4>0,0,BT4-BU4-BS4)) | BX4: =IF(D4="","",IFERROR(VLOOKUP(D4,'produto-entrada-7'!A:M,3,0),"SEM PEDIDO")) | BY4: =IF(D4="","",VLOOKUP(D4,'produto-estoque-total-7'!A:AB,25,0)) | BZ4: =IF(D4="","",IFERROR(VLOOKUP(D4,'produto-estoque-total-7'!A:AB,26,0)/100,0)) | CA4: =IF(D4="","",IFERROR(VLOOKUP(D4,'produto-estoque-total-7'!A:AB,27,0)/100,0)) | CB4: =IF(D4="","",V4*AF4) | CC4: =IF(D4="","",V4*AI4) | CD4: =IF(D4="","",VLOOKUP(D4,'produto-estoque-total-7'!A:AB,28,0))
A5: =IF(D5="","",VLOOKUP(D5,'produto-estoque-total-7'!A:AB,3,0)) | B5: =IF(D5="","",VLOOKUP(D5,'produto-estoque-total-7'!A:AB,12,0)) | C5: =IF(D5="","",VLOOKUP(D5,'produto-estoque-total-7'!A:AB,2,0)) | D5: =IFERROR(IF('produto-estoque-total-7'!A4="","",'produto-estoque-total-7'!A4),"") | E5: =IF(D5="","",VLOOKUP(D5,'produto-estoque-total-7'!A:AB,4,0)) | F5: =IF(D5="","",VLOOKUP(D5,'produto-estoque-total-7'!A:AB,13,0)) | G5: =IF(F5="","",VLOOKUP(F5,'FORNECEDORES X COMPRADOR'!A:D,4,0)) | H5: =IF(F5="","",VLOOKUP(F5,'FORNECEDORES X COMPRADOR'!A:E,5,0)) | I5: =IF(D5="","",VLOOKUP(D5,'produto-estoque-total-7'!A:AB,15,0)) | J5: =IF(D5="","",VLOOKUP(D5,'produto-estoque-total-7'!A:AB,19,0)) | K5: =IF(D5="","",VLOOKUP(D5,'produto-estoque-total-7'!A:AB,20,0)) | L5: =IF(D5="","",VLOOKUP(D5,'produto-estoque-total-7'!A:AB,17,0)) | M5: =IF(D5="","",VLOOKUP(D5,'produto-estoque-total-7'!A:AB,18,0)) | N5: =IF(D5="","",VLOOKUP(D5,'produto-estoque-total-7'!A:AB,21,0)) | O5: =IF(D5="","",VLOOKUP(D5,'produto-estoque-total-7'!A:AB,22,0)) | P5: =IF(D5="","",VLOOKUP(D5,'produto-estoque-total-7'!A:AB,23,0)) | Q5: =IF(D5="","",VLOOKUP(D5,'produto-estoque-total-7'!A:AB,24,0)) | R5: =IFERROR(IF(D5="","",VLOOKUP(D5,'produto-venda-7'!B:N,13,0)),"C") | S5: =IF(D5="","",VLOOKUP(D5,'produto-estoque-total-7'!A:AB,6,0)) | T5: =IF(D5="","",VLOOKUP(D5,'produto-estoque-total-7'!A:AB,5,0)) | U5: =IF(D5="","",VLOOKUP(D5,'produto-estoque-total-7'!A:AB,11,0)) | V5: =IF(D5="","",IFERROR(VLOOKUP(D5,'produto-entrada-7'!A:M,10,0),0)) | X5: =IF(D5="","",VLOOKUP(D5,'produto-estoque-total-7'!A:AB,8,0)) | Y5: =IF(D5="","",VLOOKUP(D5,'produto-estoque-total-7'!A:AB,9,0)) | Z5: =IF(D5="","",VLOOKUP(D5,'produto-estoque-total-7'!A:AB,10,0)) | AA5: =IFERROR(IF(D5="","",VLOOKUP(D5,'produto-venda-7'!B:N,4,0)),0) | AB5: =IFERROR(IF(D5="","",VLOOKUP(D5,'produto-venda-7'!B:N,5,0)),0) | AC5: =IF(D5="","",IFERROR(AA5/90,0)) | AD5: =IF(D5="","",IFERROR(VLOOKUP(D5,'produto-entrada-7'!A:M,4,0),0)) | AE5: =IFERROR(IF(D5="","",VLOOKUP(D5,'produto-venda-7'!B:N,10,0)),0) | AF5: =IF(D5="","",IFERROR(VLOOKUP(D5,'produto-entrada-7'!A:M,11,0),0)) | AG5: =IF(D5="","",IFERROR(VLOOKUP(D5,'produto-entrada-7'!A:M,12,0),0)) | AH5: =IF(D5="","",IFERROR(VLOOKUP(D5,'produto-entrada-7'!A:M,13,0),0)) | AI5: =IFERROR(IF(D5="","",VLOOKUP(D5,'produto-venda-7'!B:N,11,0)),0) | AJ5: =IF(D5="","",IFERROR(AI5*AB5,0)) | AK5: =IFERROR(IF(D5="","",VLOOKUP(F5,'ANALISE FORNECEDOR'!$A:$I,8,0)),"") | AL5: =IF(D5="","",AVERAGE(AM5,AK5)) | AM5: =IFERROR(IF(D5="","",VLOOKUP(F5,'ANALISE FORNECEDOR'!$A:$I,9,0)),"") | AN5: =IF(D5="","",IF(Y5>12,AI5*(U5+Y5),AI5*U5)) | AO5: =IF(D5="","",IF(Y5>12,AI5*(U5+V5+Y5),AI5*(U5+V5))) | AP5: =IF(D5="","",IF(Y5>12,AG5*(U5+Y5),AG5*U5)) | AQ5: =IF(D5="","",IF(Y5>12,AG5*(U5+V5+Y5),AG5*(U5+V5))) | AR5: =IF(D5="","",IF(OR(R5="A",R5="AA",R5="AAA"),AP5,0)) | AS5: =IF(D5="","",IF(R5="B",AP5,0)) | AT5: =IF(D5="","",IF(R5="C",AP5,0)) | AU5: =IF(D5="","",IFERROR(AN5/AJ5,0)) | AV5: =IF(D5="","",IFERROR(((AO5)/AJ5),0)) | AW5: =IF(D5="","",IF(OR(S5="S",NOT(AND(ISNUMBER(AC5),ISNUMBER(AL5),AC5*AL5>=0))),0,AC5*AL5)) | AX5: =IFERROR(IF(D5="","",AW5*AG5),0) | AY5: =IF(D5="","",IF(OR(S5="S",NOT(AND(ISNUMBER(AC5),ISNUMBER(AK5),AC5*AK5>=0))),0,AC5*AK5)) | AZ5: =IFERROR(IF(D5="","",IF(AY5=0,0,IF(((AY5)-(U5+Y5))<0,0,(AY5)-U5))),0) | BA5: =IF(D5="","",AZ5*AG5) | BB5: =IF(D5="","",IF(OR(R5="A",R5="AA",R5="AAA"),BA5,0)) | BC5: =IF(D5="","",IF(R5="B",BA5,0)) | BD5: =IF(D5="","",IF(R5="B",BA5,0)) | BE5: =IF(D5="","",IF(S5="S", 1, IF(AC5=0, 1, IF( IFERROR(((U5+Y5)*AG5)/((AC5*AK5)*AG5),0)<0, 0, IF( IFERROR(((U5+Y5)*AG5)/((AC5*AK5)*AG5),0)>1, 1, IFERROR(((U5+Y5)*AG5)/((AC5*AK5)*AG5),0) ) ) ) )) | BF5: =IF(D5="","",IF(S5="S", 1, IF(AC5=0, 1, IF( IFERROR(((U5+V5+Y5)*AG5)/((AC5*AK5)*AG5),0)<0, 0, IF( IFERROR(((U5+V5+Y5)*AG5)/((AC5*AK5)*AG5),0)>1, 1, IFERROR(((U5+V5+Y5)*AG5)/((AC5*AK5)*AG5),0) ) ) ) )) | BG5: =IF(D5="","",IF(S5="S",0,IF(AND(ISNUMBER(AC5),ISNUMBER(AM5)),IF(OR(AC5*AM5<0,ISERR(AC5*AM5)),0,AC5*AM5),0))) | BH5: =IF(D5="","",IF(BY5>TODAY()-60,0,IF(Y5>12,MAX(0,(U5+Y5)-BG5),MAX(0,U5-BG5)))) | BI5: =IF(D5="","",BH5*AG5) | BJ5: =IF(D5="","",IF(OR(R5="A",R5="AA",R5="AAA"),BI5,0)) | BK5: =IF(D5="","",IF(R5="B",BI5,0)) | BL5: =IF(D5="","",IF(R5="C",BI5,0)) | BM5: =IF(D5="","",IFERROR(MAX(0,MIN(BI5/AP5,1)),0)) | BN5: =IF(D5="","",AB5*AG5) | BO5: =IF(D5="","",(U5+V5+X5)*AG5) | BP5: =IF(D5="","",(AB5*3)*AG5) | BQ5: =IF(D5="","",IF(BO5-BP5>0,0,BO5-BP5)) | BR5: =IF(D5="","",IF(BO5-BP5-BN5>0,0,BO5-BP5-BN5)) | BS5: =IF(D5="","",IFERROR(AB5*AI5,0)) | BT5: =IF(D5="","",IFERROR(IF(X5>12, AI5*(U5+V5+X5), AI5*(U5+V5)),0)) | BU5: =IF(D5="","",IFERROR(((AB5*3)*AI5),0)) | BV5: =IF(D5="","",IF(BT5-BU5>0,0,BT5-BU5)) | BW5: =IF(D5="","",IF(BT5-BU5-BS5>0,0,BT5-BU5-BS5)) | BX5: =IF(D5="","",IFERROR(VLOOKUP(D5,'produto-entrada-7'!A:M,3,0),"SEM PEDIDO")) | BY5: =IF(D5="","",VLOOKUP(D5,'produto-estoque-total-7'!A:AB,25,0)) | BZ5: =IF(D5="","",IFERROR(VLOOKUP(D5,'produto-estoque-total-7'!A:AB,26,0)/100,0)) | CA5: =IF(D5="","",IFERROR(VLOOKUP(D5,'produto-estoque-total-7'!A:AB,27,0)/100,0)) | CB5: =IF(D5="","",V5*AF5) | CC5: =IF(D5="","",V5*AI5) | CD5: =IF(D5="","",VLOOKUP(D5,'produto-estoque-total-7'!A:AB,28,0))
A6: =IF(D6="","",VLOOKUP(D6,'produto-estoque-total-7'!A:AB,3,0)) | B6: =IF(D6="","",VLOOKUP(D6,'produto-estoque-total-7'!A:AB,12,0)) | C6: =IF(D6="","",VLOOKUP(D6,'produto-estoque-total-7'!A:AB,2,0)) | D6: =IFERROR(IF('produto-estoque-total-7'!A5="","",'produto-estoque-total-7'!A5),"") | E6: =IF(D6="","",VLOOKUP(D6,'produto-estoque-total-7'!A:AB,4,0)) | F6: =IF(D6="","",VLOOKUP(D6,'produto-estoque-total-7'!A:AB,13,0)) | G6: =IF(F6="","",VLOOKUP(F6,'FORNECEDORES X COMPRADOR'!A:D,4,0)) | H6: =IF(F6="","",VLOOKUP(F6,'FORNECEDORES X COMPRADOR'!A:E,5,0)) | I6: =IF(D6="","",VLOOKUP(D6,'produto-estoque-total-7'!A:AB,15,0)) | J6: =IF(D6="","",VLOOKUP(D6,'produto-estoque-total-7'!A:AB,19,0)) | K6: =IF(D6="","",VLOOKUP(D6,'produto-estoque-total-7'!A:AB,20,0)) | L6: =IF(D6="","",VLOOKUP(D6,'produto-estoque-total-7'!A:AB,17,0)) | M6: =IF(D6="","",VLOOKUP(D6,'produto-estoque-total-7'!A:AB,18,0)) | N6: =IF(D6="","",VLOOKUP(D6,'produto-estoque-total-7'!A:AB,21,0)) | O6: =IF(D6="","",VLOOKUP(D6,'produto-estoque-total-7'!A:AB,22,0)) | P6: =IF(D6="","",VLOOKUP(D6,'produto-estoque-total-7'!A:AB,23,0)) | Q6: =IF(D6="","",VLOOKUP(D6,'produto-estoque-total-7'!A:AB,24,0)) | R6: =IFERROR(IF(D6="","",VLOOKUP(D6,'produto-venda-7'!B:N,13,0)),"C") | S6: =IF(D6="","",VLOOKUP(D6,'produto-estoque-total-7'!A:AB,6,0)) | T6: =IF(D6="","",VLOOKUP(D6,'produto-estoque-total-7'!A:AB,5,0)) | U6: =IF(D6="","",VLOOKUP(D6,'produto-estoque-total-7'!A:AB,11,0)) | V6: =IF(D6="","",IFERROR(VLOOKUP(D6,'produto-entrada-7'!A:M,10,0),0)) | X6: =IF(D6="","",VLOOKUP(D6,'produto-estoque-total-7'!A:AB,8,0)) | Y6: =IF(D6="","",VLOOKUP(D6,'produto-estoque-total-7'!A:AB,9,0)) | Z6: =IF(D6="","",VLOOKUP(D6,'produto-estoque-total-7'!A:AB,10,0)) | AA6: =IFERROR(IF(D6="","",VLOOKUP(D6,'produto-venda-7'!B:N,4,0)),0) | AB6: =IFERROR(IF(D6="","",VLOOKUP(D6,'produto-venda-7'!B:N,5,0)),0) | AC6: =IF(D6="","",IFERROR(AA6/90,0)) | AD6: =IF(D6="","",IFERROR(VLOOKUP(D6,'produto-entrada-7'!A:M,4,0),0)) | AE6: =IFERROR(IF(D6="","",VLOOKUP(D6,'produto-venda-7'!B:N,10,0)),0) | AF6: =IF(D6="","",IFERROR(VLOOKUP(D6,'produto-entrada-7'!A:M,11,0),0)) | AG6: =IF(D6="","",IFERROR(VLOOKUP(D6,'produto-entrada-7'!A:M,12,0),0)) | AH6: =IF(D6="","",IFERROR(VLOOKUP(D6,'produto-entrada-7'!A:M,13,0),0)) | AI6: =IFERROR(IF(D6="","",VLOOKUP(D6,'produto-venda-7'!B:N,11,0)),0) | AJ6: =IF(D6="","",IFERROR(AI6*AB6,0)) | AK6: =IFERROR(IF(D6="","",VLOOKUP(F6,'ANALISE FORNECEDOR'!$A:$I,8,0)),"") | AL6: =IF(D6="","",AVERAGE(AM6,AK6)) | AM6: =IFERROR(IF(D6="","",VLOOKUP(F6,'ANALISE FORNECEDOR'!$A:$I,9,0)),"") | AN6: =IF(D6="","",IF(Y6>12,AI6*(U6+Y6),AI6*U6)) | AO6: =IF(D6="","",IF(Y6>12,AI6*(U6+V6+Y6),AI6*(U6+V6))) | AP6: =IF(D6="","",IF(Y6>12,AG6*(U6+Y6),AG6*U6)) | AQ6: =IF(D6="","",IF(Y6>12,AG6*(U6+V6+Y6),AG6*(U6+V6))) | AR6: =IF(D6="","",IF(OR(R6="A",R6="AA",R6="AAA"),AP6,0)) | AS6: =IF(D6="","",IF(R6="B",AP6,0)) | AT6: =IF(D6="","",IF(R6="C",AP6,0)) | AU6: =IF(D6="","",IFERROR(AN6/AJ6,0)) | AV6: =IF(D6="","",IFERROR(((AO6)/AJ6),0)) | AW6: =IF(D6="","",IF(OR(S6="S",NOT(AND(ISNUMBER(AC6),ISNUMBER(AL6),AC6*AL6>=0))),0,AC6*AL6)) | AX6: =IFERROR(IF(D6="","",AW6*AG6),0) | AY6: =IF(D6="","",IF(OR(S6="S",NOT(AND(ISNUMBER(AC6),ISNUMBER(AK6),AC6*AK6>=0))),0,AC6*AK6)) | AZ6: =IFERROR(IF(D6="","",IF(AY6=0,0,IF(((AY6)-(U6+Y6))<0,0,(AY6)-U6))),0) | BA6: =IF(D6="","",AZ6*AG6) | BB6: =IF(D6="","",IF(OR(R6="A",R6="AA",R6="AAA"),BA6,0)) | BC6: =IF(D6="","",IF(R6="B",BA6,0)) | BD6: =IF(D6="","",IF(R6="B",BA6,0)) | BE6: =IF(D6="","",IF(S6="S", 1, IF(AC6=0, 1, IF( IFERROR(((U6+Y6)*AG6)/((AC6*AK6)*AG6),0)<0, 0, IF( IFERROR(((U6+Y6)*AG6)/((AC6*AK6)*AG6),0)>1, 1, IFERROR(((U6+Y6)*AG6)/((AC6*AK6)*AG6),0) ) ) ) )) | BF6: =IF(D6="","",IF(S6="S", 1, IF(AC6=0, 1, IF( IFERROR(((U6+V6+Y6)*AG6)/((AC6*AK6)*AG6),0)<0, 0, IF( IFERROR(((U6+V6+Y6)*AG6)/((AC6*AK6)*AG6),0)>1, 1, IFERROR(((U6+V6+Y6)*AG6)/((AC6*AK6)*AG6),0) ) ) ) )) | BG6: =IF(D6="","",IF(S6="S",0,IF(AND(ISNUMBER(AC6),ISNUMBER(AM6)),IF(OR(AC6*AM6<0,ISERR(AC6*AM6)),0,AC6*AM6),0))) | BH6: =IF(D6="","",IF(BY6>TODAY()-60,0,IF(Y6>12,MAX(0,(U6+Y6)-BG6),MAX(0,U6-BG6)))) | BI6: =IF(D6="","",BH6*AG6) | BJ6: =IF(D6="","",IF(OR(R6="A",R6="AA",R6="AAA"),BI6,0)) | BK6: =IF(D6="","",IF(R6="B",BI6,0)) | BL6: =IF(D6="","",IF(R6="C",BI6,0)) | BM6: =IF(D6="","",IFERROR(MAX(0,MIN(BI6/AP6,1)),0)) | BN6: =IF(D6="","",AB6*AG6) | BO6: =IF(D6="","",(U6+V6+X6)*AG6) | BP6: =IF(D6="","",(AB6*3)*AG6) | BQ6: =IF(D6="","",IF(BO6-BP6>0,0,BO6-BP6)) | BR6: =IF(D6="","",IF(BO6-BP6-BN6>0,0,BO6-BP6-BN6)) | BS6: =IF(D6="","",IFERROR(AB6*AI6,0)) | BT6: =IF(D6="","",IFERROR(IF(X6>12, AI6*(U6+V6+X6), AI6*(U6+V6)),0)) | BU6: =IF(D6="","",IFERROR(((AB6*3)*AI6),0)) | BV6: =IF(D6="","",IF(BT6-BU6>0,0,BT6-BU6)) | BW6: =IF(D6="","",IF(BT6-BU6-BS6>0,0,BT6-BU6-BS6)) | BX6: =IF(D6="","",IFERROR(VLOOKUP(D6,'produto-entrada-7'!A:M,3,0),"SEM PEDIDO")) | BY6: =IF(D6="","",VLOOKUP(D6,'produto-estoque-total-7'!A:AB,25,0)) | BZ6: =IF(D6="","",IFERROR(VLOOKUP(D6,'produto-estoque-total-7'!A:AB,26,0)/100,0)) | CA6: =IF(D6="","",IFERROR(VLOOKUP(D6,'produto-estoque-total-7'!A:AB,27,0)/100,0)) | CB6: =IF(D6="","",V6*AF6) | CC6: =IF(D6="","",V6*AI6) | CD6: =IF(D6="","",VLOOKUP(D6,'produto-estoque-total-7'!A:AB,28,0))
A7: =IF(D7="","",VLOOKUP(D7,'produto-estoque-total-7'!A:AB,3,0)) | B7: =IF(D7="","",VLOOKUP(D7,'produto-estoque-total-7'!A:AB,12,0)) | C7: =IF(D7="","",VLOOKUP(D7,'produto-estoque-total-7'!A:AB,2,0)) | D7: =IFERROR(IF('produto-estoque-total-7'!A6="","",'produto-estoque-total-7'!A6),"") | E7: =IF(D7="","",VLOOKUP(D7,'produto-estoque-total-7'!A:AB,4,0)) | F7: =IF(D7="","",VLOOKUP(D7,'produto-estoque-total-7'!A:AB,13,0)) | G7: =IF(F7="","",VLOOKUP(F7,'FORNECEDORES X COMPRADOR'!A:D,4,0)) | H7: =IF(F7="","",VLOOKUP(F7,'FORNECEDORES X COMPRADOR'!A:E,5,0)) | I7: =IF(D7="","",VLOOKUP(D7,'produto-estoque-total-7'!A:AB,15,0)) | J7: =IF(D7="","",VLOOKUP(D7,'produto-estoque-total-7'!A:AB,19,0)) | K7: =IF(D7="","",VLOOKUP(D7,'produto-estoque-total-7'!A:AB,20,0)) | L7: =IF(D7="","",VLOOKUP(D7,'produto-estoque-total-7'!A:AB,17,0)) | M7: =IF(D7="","",VLOOKUP(D7,'produto-estoque-total-7'!A:AB,18,0)) | N7: =IF(D7="","",VLOOKUP(D7,'produto-estoque-total-7'!A:AB,21,0)) | O7: =IF(D7="","",VLOOKUP(D7,'produto-estoque-total-7'!A:AB,22,0)) | P7: =IF(D7="","",VLOOKUP(D7,'produto-estoque-total-7'!A:AB,23,0)) | Q7: =IF(D7="","",VLOOKUP(D7,'produto-estoque-total-7'!A:AB,24,0)) | R7: =IFERROR(IF(D7="","",VLOOKUP(D7,'produto-venda-7'!B:N,13,0)),"C") | S7: =IF(D7="","",VLOOKUP(D7,'produto-estoque-total-7'!A:AB,6,0)) | T7: =IF(D7="","",VLOOKUP(D7,'produto-estoque-total-7'!A:AB,5,0)) | U7: =IF(D7="","",VLOOKUP(D7,'produto-estoque-total-7'!A:AB,11,0)) | V7: =IF(D7="","",IFERROR(VLOOKUP(D7,'produto-entrada-7'!A:M,10,0),0)) | X7: =IF(D7="","",VLOOKUP(D7,'produto-estoque-total-7'!A:AB,8,0)) | Y7: =IF(D7="","",VLOOKUP(D7,'produto-estoque-total-7'!A:AB,9,0)) | Z7: =IF(D7="","",VLOOKUP(D7,'produto-estoque-total-7'!A:AB,10,0)) | AA7: =IFERROR(IF(D7="","",VLOOKUP(D7,'produto-venda-7'!B:N,4,0)),0) | AB7: =IFERROR(IF(D7="","",VLOOKUP(D7,'produto-venda-7'!B:N,5,0)),0) | AC7: =IF(D7="","",IFERROR(AA7/90,0)) | AD7: =IF(D7="","",IFERROR(VLOOKUP(D7,'produto-entrada-7'!A:M,4,0),0)) | AE7: =IFERROR(IF(D7="","",VLOOKUP(D7,'produto-venda-7'!B:N,10,0)),0) | AF7: =IF(D7="","",IFERROR(VLOOKUP(D7,'produto-entrada-7'!A:M,11,0),0)) | AG7: =IF(D7="","",IFERROR(VLOOKUP(D7,'produto-entrada-7'!A:M,12,0),0)) | AH7: =IF(D7="","",IFERROR(VLOOKUP(D7,'produto-entrada-7'!A:M,13,0),0)) | AI7: =IFERROR(IF(D7="","",VLOOKUP(D7,'produto-venda-7'!B:N,11,0)),0) | AJ7: =IF(D7="","",IFERROR(AI7*AB7,0)) | AK7: =IFERROR(IF(D7="","",VLOOKUP(F7,'ANALISE FORNECEDOR'!$A:$I,8,0)),"") | AL7: =IF(D7="","",AVERAGE(AM7,AK7)) | AM7: =IFERROR(IF(D7="","",VLOOKUP(F7,'ANALISE FORNECEDOR'!$A:$I,9,0)),"") | AN7: =IF(D7="","",IF(Y7>12,AI7*(U7+Y7),AI7*U7)) | AO7: =IF(D7="","",IF(Y7>12,AI7*(U7+V7+Y7),AI7*(U7+V7))) | AP7: =IF(D7="","",IF(Y7>12,AG7*(U7+Y7),AG7*U7)) | AQ7: =IF(D7="","",IF(Y7>12,AG7*(U7+V7+Y7),AG7*(U7+V7))) | AR7: =IF(D7="","",IF(OR(R7="A",R7="AA",R7="AAA"),AP7,0)) | AS7: =IF(D7="","",IF(R7="B",AP7,0)) | AT7: =IF(D7="","",IF(R7="C",AP7,0)) | AU7: =IF(D7="","",IFERROR(AN7/AJ7,0)) | AV7: =IF(D7="","",IFERROR(((AO7)/AJ7),0)) | AW7: =IF(D7="","",IF(OR(S7="S",NOT(AND(ISNUMBER(AC7),ISNUMBER(AL7),AC7*AL7>=0))),0,AC7*AL7)) | AX7: =IFERROR(IF(D7="","",AW7*AG7),0) | AY7: =IF(D7="","",IF(OR(S7="S",NOT(AND(ISNUMBER(AC7),ISNUMBER(AK7),AC7*AK7>=0))),0,AC7*AK7)) | AZ7: =IFERROR(IF(D7="","",IF(AY7=0,0,IF(((AY7)-(U7+Y7))<0,0,(AY7)-U7))),0) | BA7: =IF(D7="","",AZ7*AG7) | BB7: =IF(D7="","",IF(OR(R7="A",R7="AA",R7="AAA"),BA7,0)) | BC7: =IF(D7="","",IF(R7="B",BA7,0)) | BD7: =IF(D7="","",IF(R7="B",BA7,0)) | BE7: =IF(D7="","",IF(S7="S", 1, IF(AC7=0, 1, IF( IFERROR(((U7+Y7)*AG7)/((AC7*AK7)*AG7),0)<0, 0, IF( IFERROR(((U7+Y7)*AG7)/((AC7*AK7)*AG7),0)>1, 1, IFERROR(((U7+Y7)*AG7)/((AC7*AK7)*AG7),0) ) ) ) )) | BF7: =IF(D7="","",IF(S7="S", 1, IF(AC7=0, 1, IF( IFERROR(((U7+V7+Y7)*AG7)/((AC7*AK7)*AG7),0)<0, 0, IF( IFERROR(((U7+V7+Y7)*AG7)/((AC7*AK7)*AG7),0)>1, 1, IFERROR(((U7+V7+Y7)*AG7)/((AC7*AK7)*AG7),0) ) ) ) )) | BG7: =IF(D7="","",IF(S7="S",0,IF(AND(ISNUMBER(AC7),ISNUMBER(AM7)),IF(OR(AC7*AM7<0,ISERR(AC7*AM7)),0,AC7*AM7),0))) | BH7: =IF(D7="","",IF(BY7>TODAY()-60,0,IF(Y7>12,MAX(0,(U7+Y7)-BG7),MAX(0,U7-BG7)))) | BI7: =IF(D7="","",BH7*AG7) | BJ7: =IF(D7="","",IF(OR(R7="A",R7="AA",R7="AAA"),BI7,0)) | BK7: =IF(D7="","",IF(R7="B",BI7,0)) | BL7: =IF(D7="","",IF(R7="C",BI7,0)) | BM7: =IF(D7="","",IFERROR(MAX(0,MIN(BI7/AP7,1)),0)) | BN7: =IF(D7="","",AB7*AG7) | BO7: =IF(D7="","",(U7+V7+X7)*AG7) | BP7: =IF(D7="","",(AB7*3)*AG7) | BQ7: =IF(D7="","",IF(BO7-BP7>0,0,BO7-BP7)) | BR7: =IF(D7="","",IF(BO7-BP7-BN7>0,0,BO7-BP7-BN7)) | BS7: =IF(D7="","",IFERROR(AB7*AI7,0)) | BT7: =IF(D7="","",IFERROR(IF(X7>12, AI7*(U7+V7+X7), AI7*(U7+V7)),0)) | BU7: =IF(D7="","",IFERROR(((AB7*3)*AI7),0)) | BV7: =IF(D7="","",IF(BT7-BU7>0,0,BT7-BU7)) | BW7: =IF(D7="","",IF(BT7-BU7-BS7>0,0,BT7-BU7-BS7)) | BX7: =IF(D7="","",IFERROR(VLOOKUP(D7,'produto-entrada-7'!A:M,3,0),"SEM PEDIDO")) | BY7: =IF(D7="","",VLOOKUP(D7,'produto-estoque-total-7'!A:AB,25,0)) | BZ7: =IF(D7="","",IFERROR(VLOOKUP(D7,'produto-estoque-total-7'!A:AB,26,0)/100,0)) | CA7: =IF(D7="","",IFERROR(VLOOKUP(D7,'produto-estoque-total-7'!A:AB,27,0)/100,0)) | CB7: =IF(D7="","",V7*AF7) | CC7: =IF(D7="","",V7*AI7) | CD7: =IF(D7="","",VLOOKUP(D7,'produto-estoque-total-7'!A:AB,28,0))
A8: =IF(D8="","",VLOOKUP(D8,'produto-estoque-total-7'!A:AB,3,0)) | B8: =IF(D8="","",VLOOKUP(D8,'produto-estoque-total-7'!A:AB,12,0)) | C8: =IF(D8="","",VLOOKUP(D8,'produto-estoque-total-7'!A:AB,2,0)) | D8: =IFERROR(IF('produto-estoque-total-7'!A7="","",'produto-estoque-total-7'!A7),"") | E8: =IF(D8="","",VLOOKUP(D8,'produto-estoque-total-7'!A:AB,4,0)) | F8: =IF(D8="","",VLOOKUP(D8,'produto-estoque-total-7'!A:AB,13,0)) | G8: =IF(F8="","",VLOOKUP(F8,'FORNECEDORES X COMPRADOR'!A:D,4,0)) | H8: =IF(F8="","",VLOOKUP(F8,'FORNECEDORES X COMPRADOR'!A:E,5,0)) | I8: =IF(D8="","",VLOOKUP(D8,'produto-estoque-total-7'!A:AB,15,0)) | J8: =IF(D8="","",VLOOKUP(D8,'produto-estoque-total-7'!A:AB,19,0)) | K8: =IF(D8="","",VLOOKUP(D8,'produto-estoque-total-7'!A:AB,20,0)) | L8: =IF(D8="","",VLOOKUP(D8,'produto-estoque-total-7'!A:AB,17,0)) | M8: =IF(D8="","",VLOOKUP(D8,'produto-estoque-total-7'!A:AB,18,0)) | N8: =IF(D8="","",VLOOKUP(D8,'produto-estoque-total-7'!A:AB,21,0)) | O8: =IF(D8="","",VLOOKUP(D8,'produto-estoque-total-7'!A:AB,22,0)) | P8: =IF(D8="","",VLOOKUP(D8,'produto-estoque-total-7'!A:AB,23,0)) | Q8: =IF(D8="","",VLOOKUP(D8,'produto-estoque-total-7'!A:AB,24,0)) | R8: =IFERROR(IF(D8="","",VLOOKUP(D8,'produto-venda-7'!B:N,13,0)),"C") | S8: =IF(D8="","",VLOOKUP(D8,'produto-estoque-total-7'!A:AB,6,0)) | T8: =IF(D8="","",VLOOKUP(D8,'produto-estoque-total-7'!A:AB,5,0)) | U8: =IF(D8="","",VLOOKUP(D8,'produto-estoque-total-7'!A:AB,11,0)) | V8: =IF(D8="","",IFERROR(VLOOKUP(D8,'produto-entrada-7'!A:M,10,0),0)) | X8: =IF(D8="","",VLOOKUP(D8,'produto-estoque-total-7'!A:AB,8,0)) | Y8: =IF(D8="","",VLOOKUP(D8,'produto-estoque-total-7'!A:AB,9,0)) | Z8: =IF(D8="","",VLOOKUP(D8,'produto-estoque-total-7'!A:AB,10,0)) | AA8: =IFERROR(IF(D8="","",VLOOKUP(D8,'produto-venda-7'!B:N,4,0)),0) | AB8: =IFERROR(IF(D8="","",VLOOKUP(D8,'produto-venda-7'!B:N,5,0)),0) | AC8: =IF(D8="","",IFERROR(AA8/90,0)) | AD8: =IF(D8="","",IFERROR(VLOOKUP(D8,'produto-entrada-7'!A:M,4,0),0)) | AE8: =IFERROR(IF(D8="","",VLOOKUP(D8,'produto-venda-7'!B:N,10,0)),0) | AF8: =IF(D8="","",IFERROR(VLOOKUP(D8,'produto-entrada-7'!A:M,11,0),0)) | AG8: =IF(D8="","",IFERROR(VLOOKUP(D8,'produto-entrada-7'!A:M,12,0),0)) | AH8: =IF(D8="","",IFERROR(VLOOKUP(D8,'produto-entrada-7'!A:M,13,0),0)) | AI8: =IFERROR(IF(D8="","",VLOOKUP(D8,'produto-venda-7'!B:N,11,0)),0) | AJ8: =IF(D8="","",IFERROR(AI8*AB8,0)) | AK8: =IFERROR(IF(D8="","",VLOOKUP(F8,'ANALISE FORNECEDOR'!$A:$I,8,0)),"") | AL8: =IF(D8="","",AVERAGE(AM8,AK8)) | AM8: =IFERROR(IF(D8="","",VLOOKUP(F8,'ANALISE FORNECEDOR'!$A:$I,9,0)),"") | AN8: =IF(D8="","",IF(Y8>12,AI8*(U8+Y8),AI8*U8)) | AO8: =IF(D8="","",IF(Y8>12,AI8*(U8+V8+Y8),AI8*(U8+V8))) | AP8: =IF(D8="","",IF(Y8>12,AG8*(U8+Y8),AG8*U8)) | AQ8: =IF(D8="","",IF(Y8>12,AG8*(U8+V8+Y8),AG8*(U8+V8))) | AR8: =IF(D8="","",IF(OR(R8="A",R8="AA",R8="AAA"),AP8,0)) | AS8: =IF(D8="","",IF(R8="B",AP8,0)) | AT8: =IF(D8="","",IF(R8="C",AP8,0)) | AU8: =IF(D8="","",IFERROR(AN8/AJ8,0)) | AV8: =IF(D8="","",IFERROR(((AO8)/AJ8),0)) | AW8: =IF(D8="","",IF(OR(S8="S",NOT(AND(ISNUMBER(AC8),ISNUMBER(AL8),AC8*AL8>=0))),0,AC8*AL8)) | AX8: =IFERROR(IF(D8="","",AW8*AG8),0) | AY8: =IF(D8="","",IF(OR(S8="S",NOT(AND(ISNUMBER(AC8),ISNUMBER(AK8),AC8*AK8>=0))),0,AC8*AK8)) | AZ8: =IFERROR(IF(D8="","",IF(AY8=0,0,IF(((AY8)-(U8+Y8))<0,0,(AY8)-U8))),0) | BA8: =IF(D8="","",AZ8*AG8) | BB8: =IF(D8="","",IF(OR(R8="A",R8="AA",R8="AAA"),BA8,0)) | BC8: =IF(D8="","",IF(R8="B",BA8,0)) | BD8: =IF(D8="","",IF(R8="B",BA8,0)) | BE8: =IF(D8="","",IF(S8="S", 1, IF(AC8=0, 1, IF( IFERROR(((U8+Y8)*AG8)/((AC8*AK8)*AG8),0)<0, 0, IF( IFERROR(((U8+Y8)*AG8)/((AC8*AK8)*AG8),0)>1, 1, IFERROR(((U8+Y8)*AG8)/((AC8*AK8)*AG8),0) ) ) ) )) | BF8: =IF(D8="","",IF(S8="S", 1, IF(AC8=0, 1, IF( IFERROR(((U8+V8+Y8)*AG8)/((AC8*AK8)*AG8),0)<0, 0, IF( IFERROR(((U8+V8+Y8)*AG8)/((AC8*AK8)*AG8),0)>1, 1, IFERROR(((U8+V8+Y8)*AG8)/((AC8*AK8)*AG8),0) ) ) ) )) | BG8: =IF(D8="","",IF(S8="S",0,IF(AND(ISNUMBER(AC8),ISNUMBER(AM8)),IF(OR(AC8*AM8<0,ISERR(AC8*AM8)),0,AC8*AM8),0))) | BH8: =IF(D8="","",IF(BY8>TODAY()-60,0,IF(Y8>12,MAX(0,(U8+Y8)-BG8),MAX(0,U8-BG8)))) | BI8: =IF(D8="","",BH8*AG8) | BJ8: =IF(D8="","",IF(OR(R8="A",R8="AA",R8="AAA"),BI8,0)) | BK8: =IF(D8="","",IF(R8="B",BI8,0)) | BL8: =IF(D8="","",IF(R8="C",BI8,0)) | BM8: =IF(D8="","",IFERROR(MAX(0,MIN(BI8/AP8,1)),0)) | BN8: =IF(D8="","",AB8*AG8) | BO8: =IF(D8="","",(U8+V8+X8)*AG8) | BP8: =IF(D8="","",(AB8*3)*AG8) | BQ8: =IF(D8="","",IF(BO8-BP8>0,0,BO8-BP8)) | BR8: =IF(D8="","",IF(BO8-BP8-BN8>0,0,BO8-BP8-BN8)) | BS8: =IF(D8="","",IFERROR(AB8*AI8,0)) | BT8: =IF(D8="","",IFERROR(IF(X8>12, AI8*(U8+V8+X8), AI8*(U8+V8)),0)) | BU8: =IF(D8="","",IFERROR(((AB8*3)*AI8),0)) | BV8: =IF(D8="","",IF(BT8-BU8>0,0,BT8-BU8)) | BW8: =IF(D8="","",IF(BT8-BU8-BS8>0,0,BT8-BU8-BS8)) | BX8: =IF(D8="","",IFERROR(VLOOKUP(D8,'produto-entrada-7'!A:M,3,0),"SEM PEDIDO")) | BY8: =IF(D8="","",VLOOKUP(D8,'produto-estoque-total-7'!A:AB,25,0)) | BZ8: =IF(D8="","",IFERROR(VLOOKUP(D8,'produto-estoque-total-7'!A:AB,26,0)/100,0)) | CA8: =IF(D8="","",IFERROR(VLOOKUP(D8,'produto-estoque-total-7'!A:AB,27,0)/100,0)) | CB8: =IF(D8="","",V8*AF8) | CC8: =IF(D8="","",V8*AI8) | CD8: =IF(D8="","",VLOOKUP(D8,'produto-estoque-total-7'!A:AB,28,0))
A9: =IF(D9="","",VLOOKUP(D9,'produto-estoque-total-7'!A:AB,3,0)) | B9: =IF(D9="","",VLOOKUP(D9,'produto-estoque-total-7'!A:AB,12,0)) | C9: =IF(D9="","",VLOOKUP(D9,'produto-estoque-total-7'!A:AB,2,0)) | D9: =IFERROR(IF('produto-estoque-total-7'!A8="","",'produto-estoque-total-7'!A8),"") | E9: =IF(D9="","",VLOOKUP(D9,'produto-estoque-total-7'!A:AB,4,0)) | F9: =IF(D9="","",VLOOKUP(D9,'produto-estoque-total-7'!A:AB,13,0)) | G9: =IF(F9="","",VLOOKUP(F9,'FORNECEDORES X COMPRADOR'!A:D,4,0)) | H9: =IF(F9="","",VLOOKUP(F9,'FORNECEDORES X COMPRADOR'!A:E,5,0)) | I9: =IF(D9="","",VLOOKUP(D9,'produto-estoque-total-7'!A:AB,15,0)) | J9: =IF(D9="","",VLOOKUP(D9,'produto-estoque-total-7'!A:AB,19,0)) | K9: =IF(D9="","",VLOOKUP(D9,'produto-estoque-total-7'!A:AB,20,0)) | L9: =IF(D9="","",VLOOKUP(D9,'produto-estoque-total-7'!A:AB,17,0)) | M9: =IF(D9="","",VLOOKUP(D9,'produto-estoque-total-7'!A:AB,18,0)) | N9: =IF(D9="","",VLOOKUP(D9,'produto-estoque-total-7'!A:AB,21,0)) | O9: =IF(D9="","",VLOOKUP(D9,'produto-estoque-total-7'!A:AB,22,0)) | P9: =IF(D9="","",VLOOKUP(D9,'produto-estoque-total-7'!A:AB,23,0)) | Q9: =IF(D9="","",VLOOKUP(D9,'produto-estoque-total-7'!A:AB,24,0)) | R9: =IFERROR(IF(D9="","",VLOOKUP(D9,'produto-venda-7'!B:N,13,0)),"C") | S9: =IF(D9="","",VLOOKUP(D9,'produto-estoque-total-7'!A:AB,6,0)) | T9: =IF(D9="","",VLOOKUP(D9,'produto-estoque-total-7'!A:AB,5,0)) | U9: =IF(D9="","",VLOOKUP(D9,'produto-estoque-total-7'!A:AB,11,0)) | V9: =IF(D9="","",IFERROR(VLOOKUP(D9,'produto-entrada-7'!A:M,10,0),0)) | X9: =IF(D9="","",VLOOKUP(D9,'produto-estoque-total-7'!A:AB,8,0)) | Y9: =IF(D9="","",VLOOKUP(D9,'produto-estoque-total-7'!A:AB,9,0)) | Z9: =IF(D9="","",VLOOKUP(D9,'produto-estoque-total-7'!A:AB,10,0)) | AA9: =IFERROR(IF(D9="","",VLOOKUP(D9,'produto-venda-7'!B:N,4,0)),0) | AB9: =IFERROR(IF(D9="","",VLOOKUP(D9,'produto-venda-7'!B:N,5,0)),0) | AC9: =IF(D9="","",IFERROR(AA9/90,0)) | AD9: =IF(D9="","",IFERROR(VLOOKUP(D9,'produto-entrada-7'!A:M,4,0),0)) | AE9: =IFERROR(IF(D9="","",VLOOKUP(D9,'produto-venda-7'!B:N,10,0)),0) | AF9: =IF(D9="","",IFERROR(VLOOKUP(D9,'produto-entrada-7'!A:M,11,0),0)) | AG9: =IF(D9="","",IFERROR(VLOOKUP(D9,'produto-entrada-7'!A:M,12,0),0)) | AH9: =IF(D9="","",IFERROR(VLOOKUP(D9,'produto-entrada-7'!A:M,13,0),0)) | AI9: =IFERROR(IF(D9="","",VLOOKUP(D9,'produto-venda-7'!B:N,11,0)),0) | AJ9: =IF(D9="","",IFERROR(AI9*AB9,0)) | AK9: =IFERROR(IF(D9="","",VLOOKUP(F9,'ANALISE FORNECEDOR'!$A:$I,8,0)),"") | AL9: =IF(D9="","",AVERAGE(AM9,AK9)) | AM9: =IFERROR(IF(D9="","",VLOOKUP(F9,'ANALISE FORNECEDOR'!$A:$I,9,0)),"") | AN9: =IF(D9="","",IF(Y9>12,AI9*(U9+Y9),AI9*U9)) | AO9: =IF(D9="","",IF(Y9>12,AI9*(U9+V9+Y9),AI9*(U9+V9))) | AP9: =IF(D9="","",IF(Y9>12,AG9*(U9+Y9),AG9*U9)) | AQ9: =IF(D9="","",IF(Y9>12,AG9*(U9+V9+Y9),AG9*(U9+V9))) | AR9: =IF(D9="","",IF(OR(R9="A",R9="AA",R9="AAA"),AP9,0)) | AS9: =IF(D9="","",IF(R9="B",AP9,0)) | AT9: =IF(D9="","",IF(R9="C",AP9,0)) | AU9: =IF(D9="","",IFERROR(AN9/AJ9,0)) | AV9: =IF(D9="","",IFERROR(((AO9)/AJ9),0)) | AW9: =IF(D9="","",IF(OR(S9="S",NOT(AND(ISNUMBER(AC9),ISNUMBER(AL9),AC9*AL9>=0))),0,AC9*AL9)) | AX9: =IFERROR(IF(D9="","",AW9*AG9),0) | AY9: =IF(D9="","",IF(OR(S9="S",NOT(AND(ISNUMBER(AC9),ISNUMBER(AK9),AC9*AK9>=0))),0,AC9*AK9)) | AZ9: =IFERROR(IF(D9="","",IF(AY9=0,0,IF(((AY9)-(U9+Y9))<0,0,(AY9)-U9))),0) | BA9: =IF(D9="","",AZ9*AG9) | BB9: =IF(D9="","",IF(OR(R9="A",R9="AA",R9="AAA"),BA9,0)) | BC9: =IF(D9="","",IF(R9="B",BA9,0)) | BD9: =IF(D9="","",IF(R9="B",BA9,0)) | BE9: =IF(D9="","",IF(S9="S", 1, IF(AC9=0, 1, IF( IFERROR(((U9+Y9)*AG9)/((AC9*AK9)*AG9),0)<0, 0, IF( IFERROR(((U9+Y9)*AG9)/((AC9*AK9)*AG9),0)>1, 1, IFERROR(((U9+Y9)*AG9)/((AC9*AK9)*AG9),0) ) ) ) )) | BF9: =IF(D9="","",IF(S9="S", 1, IF(AC9=0, 1, IF( IFERROR(((U9+V9+Y9)*AG9)/((AC9*AK9)*AG9),0)<0, 0, IF( IFERROR(((U9+V9+Y9)*AG9)/((AC9*AK9)*AG9),0)>1, 1, IFERROR(((U9+V9+Y9)*AG9)/((AC9*AK9)*AG9),0) ) ) ) )) | BG9: =IF(D9="","",IF(S9="S",0,IF(AND(ISNUMBER(AC9),ISNUMBER(AM9)),IF(OR(AC9*AM9<0,ISERR(AC9*AM9)),0,AC9*AM9),0))) | BH9: =IF(D9="","",IF(BY9>TODAY()-60,0,IF(Y9>12,MAX(0,(U9+Y9)-BG9),MAX(0,U9-BG9)))) | BI9: =IF(D9="","",BH9*AG9) | BJ9: =IF(D9="","",IF(OR(R9="A",R9="AA",R9="AAA"),BI9,0)) | BK9: =IF(D9="","",IF(R9="B",BI9,0)) | BL9: =IF(D9="","",IF(R9="C",BI9,0)) | BM9: =IF(D9="","",IFERROR(MAX(0,MIN(BI9/AP9,1)),0)) | BN9: =IF(D9="","",AB9*AG9) | BO9: =IF(D9="","",(U9+V9+X9)*AG9) | BP9: =IF(D9="","",(AB9*3)*AG9) | BQ9: =IF(D9="","",IF(BO9-BP9>0,0,BO9-BP9)) | BR9: =IF(D9="","",IF(BO9-BP9-BN9>0,0,BO9-BP9-BN9)) | BS9: =IF(D9="","",IFERROR(AB9*AI9,0)) | BT9: =IF(D9="","",IFERROR(IF(X9>12, AI9*(U9+V9+X9), AI9*(U9+V9)),0)) | BU9: =IF(D9="","",IFERROR(((AB9*3)*AI9),0)) | BV9: =IF(D9="","",IF(BT9-BU9>0,0,BT9-BU9)) | BW9: =IF(D9="","",IF(BT9-BU9-BS9>0,0,BT9-BU9-BS9)) | BX9: =IF(D9="","",IFERROR(VLOOKUP(D9,'produto-entrada-7'!A:M,3,0),"SEM PEDIDO")) | BY9: =IF(D9="","",VLOOKUP(D9,'produto-estoque-total-7'!A:AB,25,0)) | BZ9: =IF(D9="","",IFERROR(VLOOKUP(D9,'produto-estoque-total-7'!A:AB,26,0)/100,0)) | CA9: =IF(D9="","",IFERROR(VLOOKUP(D9,'produto-estoque-total-7'!A:AB,27,0)/100,0)) | CB9: =IF(D9="","",V9*AF9) | CC9: =IF(D9="","",V9*AI9) | CD9: =IF(D9="","",VLOOKUP(D9,'produto-estoque-total-7'!A:AB,28,0))
A10: =IF(D10="","",VLOOKUP(D10,'produto-estoque-total-7'!A:AB,3,0)) | B10: =IF(D10="","",VLOOKUP(D10,'produto-estoque-total-7'!A:AB,12,0)) | C10: =IF(D10="","",VLOOKUP(D10,'produto-estoque-total-7'!A:AB,2,0)) | D10: =IFERROR(IF('produto-estoque-total-7'!A9="","",'produto-estoque-total-7'!A9),"") | E10: =IF(D10="","",VLOOKUP(D10,'produto-estoque-total-7'!A:AB,4,0)) | F10: =IF(D10="","",VLOOKUP(D10,'produto-estoque-total-7'!A:AB,13,0)) | G10: =IF(F10="","",VLOOKUP(F10,'FORNECEDORES X COMPRADOR'!A:D,4,0)) | H10: =IF(F10="","",VLOOKUP(F10,'FORNECEDORES X COMPRADOR'!A:E,5,0)) | I10: =IF(D10="","",VLOOKUP(D10,'produto-estoque-total-7'!A:AB,15,0)) | J10: =IF(D10="","",VLOOKUP(D10,'produto-estoque-total-7'!A:AB,19,0)) | K10: =IF(D10="","",VLOOKUP(D10,'produto-estoque-total-7'!A:AB,20,0)) | L10: =IF(D10="","",VLOOKUP(D10,'produto-estoque-total-7'!A:AB,17,0)) | M10: =IF(D10="","",VLOOKUP(D10,'produto-estoque-total-7'!A:AB,18,0)) | N10: =IF(D10="","",VLOOKUP(D10,'produto-estoque-total-7'!A:AB,21,0)) | O10: =IF(D10="","",VLOOKUP(D10,'produto-estoque-total-7'!A:AB,22,0)) | P10: =IF(D10="","",VLOOKUP(D10,'produto-estoque-total-7'!A:AB,23,0)) | Q10: =IF(D10="","",VLOOKUP(D10,'produto-estoque-total-7'!A:AB,24,0)) | R10: =IFERROR(IF(D10="","",VLOOKUP(D10,'produto-venda-7'!B:N,13,0)),"C") | S10: =IF(D10="","",VLOOKUP(D10,'produto-estoque-total-7'!A:AB,6,0)) | T10: =IF(D10="","",VLOOKUP(D10,'produto-estoque-total-7'!A:AB,5,0)) | U10: =IF(D10="","",VLOOKUP(D10,'produto-estoque-total-7'!A:AB,11,0)) | V10: =IF(D10="","",IFERROR(VLOOKUP(D10,'produto-entrada-7'!A:M,10,0),0)) | X10: =IF(D10="","",VLOOKUP(D10,'produto-estoque-total-7'!A:AB,8,0)) | Y10: =IF(D10="","",VLOOKUP(D10,'produto-estoque-total-7'!A:AB,9,0)) | Z10: =IF(D10="","",VLOOKUP(D10,'produto-estoque-total-7'!A:AB,10,0)) | AA10: =IFERROR(IF(D10="","",VLOOKUP(D10,'produto-venda-7'!B:N,4,0)),0) | AB10: =IFERROR(IF(D10="","",VLOOKUP(D10,'produto-venda-7'!B:N,5,0)),0) | AC10: =IF(D10="","",IFERROR(AA10/90,0)) | AD10: =IF(D10="","",IFERROR(VLOOKUP(D10,'produto-entrada-7'!A:M,4,0),0)) | AE10: =IFERROR(IF(D10="","",VLOOKUP(D10,'produto-venda-7'!B:N,10,0)),0) | AF10: =IF(D10="","",IFERROR(VLOOKUP(D10,'produto-entrada-7'!A:M,11,0),0)) | AG10: =IF(D10="","",IFERROR(VLOOKUP(D10,'produto-entrada-7'!A:M,12,0),0)) | AH10: =IF(D10="","",IFERROR(VLOOKUP(D10,'produto-entrada-7'!A:M,13,0),0)) | AI10: =IFERROR(IF(D10="","",VLOOKUP(D10,'produto-venda-7'!B:N,11,0)),0) | AJ10: =IF(D10="","",IFERROR(AI10*AB10,0)) | AK10: =IFERROR(IF(D10="","",VLOOKUP(F10,'ANALISE FORNECEDOR'!$A:$I,8,0)),"") | AL10: =IF(D10="","",AVERAGE(AM10,AK10)) | AM10: =IFERROR(IF(D10="","",VLOOKUP(F10,'ANALISE FORNECEDOR'!$A:$I,9,0)),"") | AN10: =IF(D10="","",IF(Y10>12,AI10*(U10+Y10),AI10*U10)) | AO10: =IF(D10="","",IF(Y10>12,AI10*(U10+V10+Y10),AI10*(U10+V10))) | AP10: =IF(D10="","",IF(Y10>12,AG10*(U10+Y10),AG10*U10)) | AQ10: =IF(D10="","",IF(Y10>12,AG10*(U10+V10+Y10),AG10*(U10+V10))) | AR10: =IF(D10="","",IF(OR(R10="A",R10="AA",R10="AAA"),AP10,0)) | AS10: =IF(D10="","",IF(R10="B",AP10,0)) | AT10: =IF(D10="","",IF(R10="C",AP10,0)) | AU10: =IF(D10="","",IFERROR(AN10/AJ10,0)) | AV10: =IF(D10="","",IFERROR(((AO10)/AJ10),0)) | AW10: =IF(D10="","",IF(OR(S10="S",NOT(AND(ISNUMBER(AC10),ISNUMBER(AL10),AC10*AL10>=0))),0,AC10*AL10)) | AX10: =IFERROR(IF(D10="","",AW10*AG10),0) | AY10: =IF(D10="","",IF(OR(S10="S",NOT(AND(ISNUMBER(AC10),ISNUMBER(AK10),AC10*AK10>=0))),0,AC10*AK10)) | AZ10: =IFERROR(IF(D10="","",IF(AY10=0,0,IF(((AY10)-(U10+Y10))<0,0,(AY10)-U10))),0) | BA10: =IF(D10="","",AZ10*AG10) | BB10: =IF(D10="","",IF(OR(R10="A",R10="AA",R10="AAA"),BA10,0)) | BC10: =IF(D10="","",IF(R10="B",BA10,0)) | BD10: =IF(D10="","",IF(R10="B",BA10,0)) | BE10: =IF(D10="","",IF(S10="S", 1, IF(AC10=0, 1, IF( IFERROR(((U10+Y10)*AG10)/((AC10*AK10)*AG10),0)<0, 0, IF( IFERROR(((U10+Y10)*AG10)/((AC10*AK10)*AG10),0)>1, 1, IFERROR(((U10+Y10)*AG10)/((AC10*AK10)*AG10),0) ) ) ) )) | BF10: =IF(D10="","",IF(S10="S", 1, IF(AC10=0, 1, IF( IFERROR(((U10+V10+Y10)*AG10)/((AC10*AK10)*AG10),0)<0, 0, IF( IFERROR(((U10+V10+Y10)*AG10)/((AC10*AK10)*AG10),0)>1, 1, IFERROR(((U10+V10+Y10)*AG10)/((AC10*AK10)*AG10),0) ) ) ) )) | BG10: =IF(D10="","",IF(S10="S",0,IF(AND(ISNUMBER(AC10),ISNUMBER(AM10)),IF(OR(AC10*AM10<0,ISERR(AC10*AM10)),0,AC10*AM10),0))) | BH10: =IF(D10="","",IF(BY10>TODAY()-60,0,IF(Y10>12,MAX(0,(U10+Y10)-BG10),MAX(0,U10-BG10)))) | BI10: =IF(D10="","",BH10*AG10) | BJ10: =IF(D10="","",IF(OR(R10="A",R10="AA",R10="AAA"),BI10,0)) | BK10: =IF(D10="","",IF(R10="B",BI10,0)) | BL10: =IF(D10="","",IF(R10="C",BI10,0)) | BM10: =IF(D10="","",IFERROR(MAX(0,MIN(BI10/AP10,1)),0)) | BN10: =IF(D10="","",AB10*AG10) | BO10: =IF(D10="","",(U10+V10+X10)*AG10) | BP10: =IF(D10="","",(AB10*3)*AG10) | BQ10: =IF(D10="","",IF(BO10-BP10>0,0,BO10-BP10)) | BR10: =IF(D10="","",IF(BO10-BP10-BN10>0,0,BO10-BP10-BN10)) | BS10: =IF(D10="","",IFERROR(AB10*AI10,0)) | BT10: =IF(D10="","",IFERROR(IF(X10>12, AI10*(U10+V10+X10), AI10*(U10+V10)),0)) | BU10: =IF(D10="","",IFERROR(((AB10*3)*AI10),0)) | BV10: =IF(D10="","",IF(BT10-BU10>0,0,BT10-BU10)) | BW10: =IF(D10="","",IF(BT10-BU10-BS10>0,0,BT10-BU10-BS10)) | BX10: =IF(D10="","",IFERROR(VLOOKUP(D10,'produto-entrada-7'!A:M,3,0),"SEM PEDIDO")) | BY10: =IF(D10="","",VLOOKUP(D10,'produto-estoque-total-7'!A:AB,25,0)) | BZ10: =IF(D10="","",IFERROR(VLOOKUP(D10,'produto-estoque-total-7'!A:AB,26,0)/100,0)) | CA10: =IF(D10="","",IFERROR(VLOOKUP(D10,'produto-estoque-total-7'!A:AB,27,0)/100,0)) | CB10: =IF(D10="","",V10*AF10) | CC10: =IF(D10="","",V10*AI10) | CD10: =IF(D10="","",VLOOKUP(D10,'produto-estoque-total-7'!A:AB,28,0))
A11: =IF(D11="","",VLOOKUP(D11,'produto-estoque-total-7'!A:AB,3,0)) | B11: =IF(D11="","",VLOOKUP(D11,'produto-estoque-total-7'!A:AB,12,0)) | C11: =IF(D11="","",VLOOKUP(D11,'produto-estoque-total-7'!A:AB,2,0)) | D11: =IFERROR(IF('produto-estoque-total-7'!A10="","",'produto-estoque-total-7'!A10),"") | E11: =IF(D11="","",VLOOKUP(D11,'produto-estoque-total-7'!A:AB,4,0)) | F11: =IF(D11="","",VLOOKUP(D11,'produto-estoque-total-7'!A:AB,13,0)) | G11: =IF(F11="","",VLOOKUP(F11,'FORNECEDORES X COMPRADOR'!A:D,4,0)) | H11: =IF(F11="","",VLOOKUP(F11,'FORNECEDORES X COMPRADOR'!A:E,5,0)) | I11: =IF(D11="","",VLOOKUP(D11,'produto-estoque-total-7'!A:AB,15,0)) | J11: =IF(D11="","",VLOOKUP(D11,'produto-estoque-total-7'!A:AB,19,0)) | K11: =IF(D11="","",VLOOKUP(D11,'produto-estoque-total-7'!A:AB,20,0)) | L11: =IF(D11="","",VLOOKUP(D11,'produto-estoque-total-7'!A:AB,17,0)) | M11: =IF(D11="","",VLOOKUP(D11,'produto-estoque-total-7'!A:AB,18,0)) | N11: =IF(D11="","",VLOOKUP(D11,'produto-estoque-total-7'!A:AB,21,0)) | O11: =IF(D11="","",VLOOKUP(D11,'produto-estoque-total-7'!A:AB,22,0)) | P11: =IF(D11="","",VLOOKUP(D11,'produto-estoque-total-7'!A:AB,23,0)) | Q11: =IF(D11="","",VLOOKUP(D11,'produto-estoque-total-7'!A:AB,24,0)) | R11: =IFERROR(IF(D11="","",VLOOKUP(D11,'produto-venda-7'!B:N,13,0)),"C") | S11: =IF(D11="","",VLOOKUP(D11,'produto-estoque-total-7'!A:AB,6,0)) | T11: =IF(D11="","",VLOOKUP(D11,'produto-estoque-total-7'!A:AB,5,0)) | U11: =IF(D11="","",VLOOKUP(D11,'produto-estoque-total-7'!A:AB,11,0)) | V11: =IF(D11="","",IFERROR(VLOOKUP(D11,'produto-entrada-7'!A:M,10,0),0)) | X11: =IF(D11="","",VLOOKUP(D11,'produto-estoque-total-7'!A:AB,8,0)) | Y11: =IF(D11="","",VLOOKUP(D11,'produto-estoque-total-7'!A:AB,9,0)) | Z11: =IF(D11="","",VLOOKUP(D11,'produto-estoque-total-7'!A:AB,10,0)) | AA11: =IFERROR(IF(D11="","",VLOOKUP(D11,'produto-venda-7'!B:N,4,0)),0) | AB11: =IFERROR(IF(D11="","",VLOOKUP(D11,'produto-venda-7'!B:N,5,0)),0) | AC11: =IF(D11="","",IFERROR(AA11/90,0)) | AD11: =IF(D11="","",IFERROR(VLOOKUP(D11,'produto-entrada-7'!A:M,4,0),0)) | AE11: =IFERROR(IF(D11="","",VLOOKUP(D11,'produto-venda-7'!B:N,10,0)),0) | AF11: =IF(D11="","",IFERROR(VLOOKUP(D11,'produto-entrada-7'!A:M,11,0),0)) | AG11: =IF(D11="","",IFERROR(VLOOKUP(D11,'produto-entrada-7'!A:M,12,0),0)) | AH11: =IF(D11="","",IFERROR(VLOOKUP(D11,'produto-entrada-7'!A:M,13,0),0)) | AI11: =IFERROR(IF(D11="","",VLOOKUP(D11,'produto-venda-7'!B:N,11,0)),0) | AJ11: =IF(D11="","",IFERROR(AI11*AB11,0)) | AK11: =IFERROR(IF(D11="","",VLOOKUP(F11,'ANALISE FORNECEDOR'!$A:$I,8,0)),"") | AL11: =IF(D11="","",AVERAGE(AM11,AK11)) | AM11: =IFERROR(IF(D11="","",VLOOKUP(F11,'ANALISE FORNECEDOR'!$A:$I,9,0)),"") | AN11: =IF(D11="","",IF(Y11>12,AI11*(U11+Y11),AI11*U11)) | AO11: =IF(D11="","",IF(Y11>12,AI11*(U11+V11+Y11),AI11*(U11+V11))) | AP11: =IF(D11="","",IF(Y11>12,AG11*(U11+Y11),AG11*U11)) | AQ11: =IF(D11="","",IF(Y11>12,AG11*(U11+V11+Y11),AG11*(U11+V11))) | AR11: =IF(D11="","",IF(OR(R11="A",R11="AA",R11="AAA"),AP11,0)) | AS11: =IF(D11="","",IF(R11="B",AP11,0)) | AT11: =IF(D11="","",IF(R11="C",AP11,0)) | AU11: =IF(D11="","",IFERROR(AN11/AJ11,0)) | AV11: =IF(D11="","",IFERROR(((AO11)/AJ11),0)) | AW11: =IF(D11="","",IF(OR(S11="S",NOT(AND(ISNUMBER(AC11),ISNUMBER(AL11),AC11*AL11>=0))),0,AC11*AL11)) | AX11: =IFERROR(IF(D11="","",AW11*AG11),0) | AY11: =IF(D11="","",IF(OR(S11="S",NOT(AND(ISNUMBER(AC11),ISNUMBER(AK11),AC11*AK11>=0))),0,AC11*AK11)) | AZ11: =IFERROR(IF(D11="","",IF(AY11=0,0,IF(((AY11)-(U11+Y11))<0,0,(AY11)-U11))),0) | BA11: =IF(D11="","",AZ11*AG11) | BB11: =IF(D11="","",IF(OR(R11="A",R11="AA",R11="AAA"),BA11,0)) | BC11: =IF(D11="","",IF(R11="B",BA11,0)) | BD11: =IF(D11="","",IF(R11="B",BA11,0)) | BE11: =IF(D11="","",IF(S11="S", 1, IF(AC11=0, 1, IF( IFERROR(((U11+Y11)*AG11)/((AC11*AK11)*AG11),0)<0, 0, IF( IFERROR(((U11+Y11)*AG11)/((AC11*AK11)*AG11),0)>1, 1, IFERROR(((U11+Y11)*AG11)/((AC11*AK11)*AG11),0) ) ) ) )) | BF11: =IF(D11="","",IF(S11="S", 1, IF(AC11=0, 1, IF( IFERROR(((U11+V11+Y11)*AG11)/((AC11*AK11)*AG11),0)<0, 0, IF( IFERROR(((U11+V11+Y11)*AG11)/((AC11*AK11)*AG11),0)>1, 1, IFERROR(((U11+V11+Y11)*AG11)/((AC11*AK11)*AG11),0) ) ) ) )) | BG11: =IF(D11="","",IF(S11="S",0,IF(AND(ISNUMBER(AC11),ISNUMBER(AM11)),IF(OR(AC11*AM11<0,ISERR(AC11*AM11)),0,AC11*AM11),0))) | BH11: =IF(D11="","",IF(BY11>TODAY()-60,0,IF(Y11>12,MAX(0,(U11+Y11)-BG11),MAX(0,U11-BG11)))) | BI11: =IF(D11="","",BH11*AG11) | BJ11: =IF(D11="","",IF(OR(R11="A",R11="AA",R11="AAA"),BI11,0)) | BK11: =IF(D11="","",IF(R11="B",BI11,0)) | BL11: =IF(D11="","",IF(R11="C",BI11,0)) | BM11: =IF(D11="","",IFERROR(MAX(0,MIN(BI11/AP11,1)),0)) | BN11: =IF(D11="","",AB11*AG11) | BO11: =IF(D11="","",(U11+V11+X11)*AG11) | BP11: =IF(D11="","",(AB11*3)*AG11) | BQ11: =IF(D11="","",IF(BO11-BP11>0,0,BO11-BP11)) | BR11: =IF(D11="","",IF(BO11-BP11-BN11>0,0,BO11-BP11-BN11)) | BS11: =IF(D11="","",IFERROR(AB11*AI11,0)) | BT11: =IF(D11="","",IFERROR(IF(X11>12, AI11*(U11+V11+X11), AI11*(U11+V11)),0)) | BU11: =IF(D11="","",IFERROR(((AB11*3)*AI11),0)) | BV11: =IF(D11="","",IF(BT11-BU11>0,0,BT11-BU11)) | BW11: =IF(D11="","",IF(BT11-BU11-BS11>0,0,BT11-BU11-BS11)) | BX11: =IF(D11="","",IFERROR(VLOOKUP(D11,'produto-entrada-7'!A:M,3,0),"SEM PEDIDO")) | BY11: =IF(D11="","",VLOOKUP(D11,'produto-estoque-total-7'!A:AB,25,0)) | BZ11: =IF(D11="","",IFERROR(VLOOKUP(D11,'produto-estoque-total-7'!A:AB,26,0)/100,0)) | CA11: =IF(D11="","",IFERROR(VLOOKUP(D11,'produto-estoque-total-7'!A:AB,27,0)/100,0)) | CB11: =IF(D11="","",V11*AF11) | CC11: =IF(D11="","",V11*AI11) | CD11: =IF(D11="","",VLOOKUP(D11,'produto-estoque-total-7'!A:AB,28,0))
A12: =IF(D12="","",VLOOKUP(D12,'produto-estoque-total-7'!A:AB,3,0)) | B12: =IF(D12="","",VLOOKUP(D12,'produto-estoque-total-7'!A:AB,12,0)) | C12: =IF(D12="","",VLOOKUP(D12,'produto-estoque-total-7'!A:AB,2,0)) | D12: =IFERROR(IF('produto-estoque-total-7'!A11="","",'produto-estoque-total-7'!A11),"") | E12: =IF(D12="","",VLOOKUP(D12,'produto-estoque-total-7'!A:AB,4,0)) | F12: =IF(D12="","",VLOOKUP(D12,'produto-estoque-total-7'!A:AB,13,0)) | G12: =IF(F12="","",VLOOKUP(F12,'FORNECEDORES X COMPRADOR'!A:D,4,0)) | H12: =IF(F12="","",VLOOKUP(F12,'FORNECEDORES X COMPRADOR'!A:E,5,0)) | I12: =IF(D12="","",VLOOKUP(D12,'produto-estoque-total-7'!A:AB,15,0)) | J12: =IF(D12="","",VLOOKUP(D12,'produto-estoque-total-7'!A:AB,19,0)) | K12: =IF(D12="","",VLOOKUP(D12,'produto-estoque-total-7'!A:AB,20,0)) | L12: =IF(D12="","",VLOOKUP(D12,'produto-estoque-total-7'!A:AB,17,0)) | M12: =IF(D12="","",VLOOKUP(D12,'produto-estoque-total-7'!A:AB,18,0)) | N12: =IF(D12="","",VLOOKUP(D12,'produto-estoque-total-7'!A:AB,21,0)) | O12: =IF(D12="","",VLOOKUP(D12,'produto-estoque-total-7'!A:AB,22,0)) | P12: =IF(D12="","",VLOOKUP(D12,'produto-estoque-total-7'!A:AB,23,0)) | Q12: =IF(D12="","",VLOOKUP(D12,'produto-estoque-total-7'!A:AB,24,0)) | R12: =IFERROR(IF(D12="","",VLOOKUP(D12,'produto-venda-7'!B:N,13,0)),"C") | S12: =IF(D12="","",VLOOKUP(D12,'produto-estoque-total-7'!A:AB,6,0)) | T12: =IF(D12="","",VLOOKUP(D12,'produto-estoque-total-7'!A:AB,5,0)) | U12: =IF(D12="","",VLOOKUP(D12,'produto-estoque-total-7'!A:AB,11,0)) | V12: =IF(D12="","",IFERROR(VLOOKUP(D12,'produto-entrada-7'!A:M,10,0),0)) | X12: =IF(D12="","",VLOOKUP(D12,'produto-estoque-total-7'!A:AB,8,0)) | Y12: =IF(D12="","",VLOOKUP(D12,'produto-estoque-total-7'!A:AB,9,0)) | Z12: =IF(D12="","",VLOOKUP(D12,'produto-estoque-total-7'!A:AB,10,0)) | AA12: =IFERROR(IF(D12="","",VLOOKUP(D12,'produto-venda-7'!B:N,4,0)),0) | AB12: =IFERROR(IF(D12="","",VLOOKUP(D12,'produto-venda-7'!B:N,5,0)),0) | AC12: =IF(D12="","",IFERROR(AA12/90,0)) | AD12: =IF(D12="","",IFERROR(VLOOKUP(D12,'produto-entrada-7'!A:M,4,0),0)) | AE12: =IFERROR(IF(D12="","",VLOOKUP(D12,'produto-venda-7'!B:N,10,0)),0) | AF12: =IF(D12="","",IFERROR(VLOOKUP(D12,'produto-entrada-7'!A:M,11,0),0)) | AG12: =IF(D12="","",IFERROR(VLOOKUP(D12,'produto-entrada-7'!A:M,12,0),0)) | AH12: =IF(D12="","",IFERROR(VLOOKUP(D12,'produto-entrada-7'!A:M,13,0),0)) | AI12: =IFERROR(IF(D12="","",VLOOKUP(D12,'produto-venda-7'!B:N,11,0)),0) | AJ12: =IF(D12="","",IFERROR(AI12*AB12,0)) | AK12: =IFERROR(IF(D12="","",VLOOKUP(F12,'ANALISE FORNECEDOR'!$A:$I,8,0)),"") | AL12: =IF(D12="","",AVERAGE(AM12,AK12)) | AM12: =IFERROR(IF(D12="","",VLOOKUP(F12,'ANALISE FORNECEDOR'!$A:$I,9,0)),"") | AN12: =IF(D12="","",IF(Y12>12,AI12*(U12+Y12),AI12*U12)) | AO12: =IF(D12="","",IF(Y12>12,AI12*(U12+V12+Y12),AI12*(U12+V12))) | AP12: =IF(D12="","",IF(Y12>12,AG12*(U12+Y12),AG12*U12)) | AQ12: =IF(D12="","",IF(Y12>12,AG12*(U12+V12+Y12),AG12*(U12+V12))) | AR12: =IF(D12="","",IF(OR(R12="A",R12="AA",R12="AAA"),AP12,0)) | AS12: =IF(D12="","",IF(R12="B",AP12,0)) | AT12: =IF(D12="","",IF(R12="C",AP12,0)) | AU12: =IF(D12="","",IFERROR(AN12/AJ12,0)) | AV12: =IF(D12="","",IFERROR(((AO12)/AJ12),0)) | AW12: =IF(D12="","",IF(OR(S12="S",NOT(AND(ISNUMBER(AC12),ISNUMBER(AL12),AC12*AL12>=0))),0,AC12*AL12)) | AX12: =IFERROR(IF(D12="","",AW12*AG12),0) | AY12: =IF(D12="","",IF(OR(S12="S",NOT(AND(ISNUMBER(AC12),ISNUMBER(AK12),AC12*AK12>=0))),0,AC12*AK12)) | AZ12: =IFERROR(IF(D12="","",IF(AY12=0,0,IF(((AY12)-(U12+Y12))<0,0,(AY12)-U12))),0) | BA12: =IF(D12="","",AZ12*AG12) | BB12: =IF(D12="","",IF(OR(R12="A",R12="AA",R12="AAA"),BA12,0)) | BC12: =IF(D12="","",IF(R12="B",BA12,0)) | BD12: =IF(D12="","",IF(R12="B",BA12,0)) | BE12: =IF(D12="","",IF(S12="S", 1, IF(AC12=0, 1, IF( IFERROR(((U12+Y12)*AG12)/((AC12*AK12)*AG12),0)<0, 0, IF( IFERROR(((U12+Y12)*AG12)/((AC12*AK12)*AG12),0)>1, 1, IFERROR(((U12+Y12)*AG12)/((AC12*AK12)*AG12),0) ) ) ) )) | BF12: =IF(D12="","",IF(S12="S", 1, IF(AC12=0, 1, IF( IFERROR(((U12+V12+Y12)*AG12)/((AC12*AK12)*AG12),0)<0, 0, IF( IFERROR(((U12+V12+Y12)*AG12)/((AC12*AK12)*AG12),0)>1, 1, IFERROR(((U12+V12+Y12)*AG12)/((AC12*AK12)*AG12),0) ) ) ) )) | BG12: =IF(D12="","",IF(S12="S",0,IF(AND(ISNUMBER(AC12),ISNUMBER(AM12)),IF(OR(AC12*AM12<0,ISERR(AC12*AM12)),0,AC12*AM12),0))) | BH12: =IF(D12="","",IF(BY12>TODAY()-60,0,IF(Y12>12,MAX(0,(U12+Y12)-BG12),MAX(0,U12-BG12)))) | BI12: =IF(D12="","",BH12*AG12) | BJ12: =IF(D12="","",IF(OR(R12="A",R12="AA",R12="AAA"),BI12,0)) | BK12: =IF(D12="","",IF(R12="B",BI12,0)) | BL12: =IF(D12="","",IF(R12="C",BI12,0)) | BM12: =IF(D12="","",IFERROR(MAX(0,MIN(BI12/AP12,1)),0)) | BN12: =IF(D12="","",AB12*AG12) | BO12: =IF(D12="","",(U12+V12+X12)*AG12) | BP12: =IF(D12="","",(AB12*3)*AG12) | BQ12: =IF(D12="","",IF(BO12-BP12>0,0,BO12-BP12)) | BR12: =IF(D12="","",IF(BO12-BP12-BN12>0,0,BO12-BP12-BN12)) | BS12: =IF(D12="","",IFERROR(AB12*AI12,0)) | BT12: =IF(D12="","",IFERROR(IF(X12>12, AI12*(U12+V12+X12), AI12*(U12+V12)),0)) | BU12: =IF(D12="","",IFERROR(((AB12*3)*AI12),0)) | BV12: =IF(D12="","",IF(BT12-BU12>0,0,BT12-BU12)) | BW12: =IF(D12="","",IF(BT12-BU12-BS12>0,0,BT12-BU12-BS12)) | BX12: =IF(D12="","",IFERROR(VLOOKUP(D12,'produto-entrada-7'!A:M,3,0),"SEM PEDIDO")) | BY12: =IF(D12="","",VLOOKUP(D12,'produto-estoque-total-7'!A:AB,25,0)) | BZ12: =IF(D12="","",IFERROR(VLOOKUP(D12,'produto-estoque-total-7'!A:AB,26,0)/100,0)) | CA12: =IF(D12="","",IFERROR(VLOOKUP(D12,'produto-estoque-total-7'!A:AB,27,0)/100,0)) | CB12: =IF(D12="","",V12*AF12) | CC12: =IF(D12="","",V12*AI12) | CD12: =IF(D12="","",VLOOKUP(D12,'produto-estoque-total-7'!A:AB,28,0))
A13: =IF(D13="","",VLOOKUP(D13,'produto-estoque-total-7'!A:AB,3,0)) | B13: =IF(D13="","",VLOOKUP(D13,'produto-estoque-total-7'!A:AB,12,0)) | C13: =IF(D13="","",VLOOKUP(D13,'produto-estoque-total-7'!A:AB,2,0)) | D13: =IFERROR(IF('produto-estoque-total-7'!A12="","",'produto-estoque-total-7'!A12),"") | E13: =IF(D13="","",VLOOKUP(D13,'produto-estoque-total-7'!A:AB,4,0)) | F13: =IF(D13="","",VLOOKUP(D13,'produto-estoque-total-7'!A:AB,13,0)) | G13: =IF(F13="","",VLOOKUP(F13,'FORNECEDORES X COMPRADOR'!A:D,4,0)) | H13: =IF(F13="","",VLOOKUP(F13,'FORNECEDORES X COMPRADOR'!A:E,5,0)) | I13: =IF(D13="","",VLOOKUP(D13,'produto-estoque-total-7'!A:AB,15,0)) | J13: =IF(D13="","",VLOOKUP(D13,'produto-estoque-total-7'!A:AB,19,0)) | K13: =IF(D13="","",VLOOKUP(D13,'produto-estoque-total-7'!A:AB,20,0)) | L13: =IF(D13="","",VLOOKUP(D13,'produto-estoque-total-7'!A:AB,17,0)) | M13: =IF(D13="","",VLOOKUP(D13,'produto-estoque-total-7'!A:AB,18,0)) | N13: =IF(D13="","",VLOOKUP(D13,'produto-estoque-total-7'!A:AB,21,0)) | O13: =IF(D13="","",VLOOKUP(D13,'produto-estoque-total-7'!A:AB,22,0)) | P13: =IF(D13="","",VLOOKUP(D13,'produto-estoque-total-7'!A:AB,23,0)) | Q13: =IF(D13="","",VLOOKUP(D13,'produto-estoque-total-7'!A:AB,24,0)) | R13: =IFERROR(IF(D13="","",VLOOKUP(D13,'produto-venda-7'!B:N,13,0)),"C") | S13: =IF(D13="","",VLOOKUP(D13,'produto-estoque-total-7'!A:AB,6,0)) | T13: =IF(D13="","",VLOOKUP(D13,'produto-estoque-total-7'!A:AB,5,0)) | U13: =IF(D13="","",VLOOKUP(D13,'produto-estoque-total-7'!A:AB,11,0)) | V13: =IF(D13="","",IFERROR(VLOOKUP(D13,'produto-entrada-7'!A:M,10,0),0)) | X13: =IF(D13="","",VLOOKUP(D13,'produto-estoque-total-7'!A:AB,8,0)) | Y13: =IF(D13="","",VLOOKUP(D13,'produto-estoque-total-7'!A:AB,9,0)) | Z13: =IF(D13="","",VLOOKUP(D13,'produto-estoque-total-7'!A:AB,10,0)) | AA13: =IFERROR(IF(D13="","",VLOOKUP(D13,'produto-venda-7'!B:N,4,0)),0) | AB13: =IFERROR(IF(D13="","",VLOOKUP(D13,'produto-venda-7'!B:N,5,0)),0) | AC13: =IF(D13="","",IFERROR(AA13/90,0)) | AD13: =IF(D13="","",IFERROR(VLOOKUP(D13,'produto-entrada-7'!A:M,4,0),0)) | AE13: =IFERROR(IF(D13="","",VLOOKUP(D13,'produto-venda-7'!B:N,10,0)),0) | AF13: =IF(D13="","",IFERROR(VLOOKUP(D13,'produto-entrada-7'!A:M,11,0),0)) | AG13: =IF(D13="","",IFERROR(VLOOKUP(D13,'produto-entrada-7'!A:M,12,0),0)) | AH13: =IF(D13="","",IFERROR(VLOOKUP(D13,'produto-entrada-7'!A:M,13,0),0)) | AI13: =IFERROR(IF(D13="","",VLOOKUP(D13,'produto-venda-7'!B:N,11,0)),0) | AJ13: =IF(D13="","",IFERROR(AI13*AB13,0)) | AK13: =IFERROR(IF(D13="","",VLOOKUP(F13,'ANALISE FORNECEDOR'!$A:$I,8,0)),"") | AL13: =IF(D13="","",AVERAGE(AM13,AK13)) | AM13: =IFERROR(IF(D13="","",VLOOKUP(F13,'ANALISE FORNECEDOR'!$A:$I,9,0)),"") | AN13: =IF(D13="","",IF(Y13>12,AI13*(U13+Y13),AI13*U13)) | AO13: =IF(D13="","",IF(Y13>12,AI13*(U13+V13+Y13),AI13*(U13+V13))) | AP13: =IF(D13="","",IF(Y13>12,AG13*(U13+Y13),AG13*U13)) | AQ13: =IF(D13="","",IF(Y13>12,AG13*(U13+V13+Y13),AG13*(U13+V13))) | AR13: =IF(D13="","",IF(OR(R13="A",R13="AA",R13="AAA"),AP13,0)) | AS13: =IF(D13="","",IF(R13="B",AP13,0)) | AT13: =IF(D13="","",IF(R13="C",AP13,0)) | AU13: =IF(D13="","",IFERROR(AN13/AJ13,0)) | AV13: =IF(D13="","",IFERROR(((AO13)/AJ13),0)) | AW13: =IF(D13="","",IF(OR(S13="S",NOT(AND(ISNUMBER(AC13),ISNUMBER(AL13),AC13*AL13>=0))),0,AC13*AL13)) | AX13: =IFERROR(IF(D13="","",AW13*AG13),0) | AY13: =IF(D13="","",IF(OR(S13="S",NOT(AND(ISNUMBER(AC13),ISNUMBER(AK13),AC13*AK13>=0))),0,AC13*AK13)) | AZ13: =IFERROR(IF(D13="","",IF(AY13=0,0,IF(((AY13)-(U13+Y13))<0,0,(AY13)-U13))),0) | BA13: =IF(D13="","",AZ13*AG13) | BB13: =IF(D13="","",IF(OR(R13="A",R13="AA",R13="AAA"),BA13,0)) | BC13: =IF(D13="","",IF(R13="B",BA13,0)) | BD13: =IF(D13="","",IF(R13="B",BA13,0)) | BE13: =IF(D13="","",IF(S13="S", 1, IF(AC13=0, 1, IF( IFERROR(((U13+Y13)*AG13)/((AC13*AK13)*AG13),0)<0, 0, IF( IFERROR(((U13+Y13)*AG13)/((AC13*AK13)*AG13),0)>1, 1, IFERROR(((U13+Y13)*AG13)/((AC13*AK13)*AG13),0) ) ) ) )) | BF13: =IF(D13="","",IF(S13="S", 1, IF(AC13=0, 1, IF( IFERROR(((U13+V13+Y13)*AG13)/((AC13*AK13)*AG13),0)<0, 0, IF( IFERROR(((U13+V13+Y13)*AG13)/((AC13*AK13)*AG13),0)>1, 1, IFERROR(((U13+V13+Y13)*AG13)/((AC13*AK13)*AG13),0) ) ) ) )) | BG13: =IF(D13="","",IF(S13="S",0,IF(AND(ISNUMBER(AC13),ISNUMBER(AM13)),IF(OR(AC13*AM13<0,ISERR(AC13*AM13)),0,AC13*AM13),0))) | BH13: =IF(D13="","",IF(BY13>TODAY()-60,0,IF(Y13>12,MAX(0,(U13+Y13)-BG13),MAX(0,U13-BG13)))) | BI13: =IF(D13="","",BH13*AG13) | BJ13: =IF(D13="","",IF(OR(R13="A",R13="AA",R13="AAA"),BI13,0)) | BK13: =IF(D13="","",IF(R13="B",BI13,0)) | BL13: =IF(D13="","",IF(R13="C",BI13,0)) | BM13: =IF(D13="","",IFERROR(MAX(0,MIN(BI13/AP13,1)),0)) | BN13: =IF(D13="","",AB13*AG13) | BO13: =IF(D13="","",(U13+V13+X13)*AG13) | BP13: =IF(D13="","",(AB13*3)*AG13) | BQ13: =IF(D13="","",IF(BO13-BP13>0,0,BO13-BP13)) | BR13: =IF(D13="","",IF(BO13-BP13-BN13>0,0,BO13-BP13-BN13)) | BS13: =IF(D13="","",IFERROR(AB13*AI13,0)) | BT13: =IF(D13="","",IFERROR(IF(X13>12, AI13*(U13+V13+X13), AI13*(U13+V13)),0)) | BU13: =IF(D13="","",IFERROR(((AB13*3)*AI13),0)) | BV13: =IF(D13="","",IF(BT13-BU13>0,0,BT13-BU13)) | BW13: =IF(D13="","",IF(BT13-BU13-BS13>0,0,BT13-BU13-BS13)) | BX13: =IF(D13="","",IFERROR(VLOOKUP(D13,'produto-entrada-7'!A:M,3,0),"SEM PEDIDO")) | BY13: =IF(D13="","",VLOOKUP(D13,'produto-estoque-total-7'!A:AB,25,0)) | BZ13: =IF(D13="","",IFERROR(VLOOKUP(D13,'produto-estoque-total-7'!A:AB,26,0)/100,0)) | CA13: =IF(D13="","",IFERROR(VLOOKUP(D13,'produto-estoque-total-7'!A:AB,27,0)/100,0)) | CB13: =IF(D13="","",V13*AF13) | CC13: =IF(D13="","",V13*AI13) | CD13: =IF(D13="","",VLOOKUP(D13,'produto-estoque-total-7'!A:AB,28,0))
A14: =IF(D14="","",VLOOKUP(D14,'produto-estoque-total-7'!A:AB,3,0)) | B14: =IF(D14="","",VLOOKUP(D14,'produto-estoque-total-7'!A:AB,12,0)) | C14: =IF(D14="","",VLOOKUP(D14,'produto-estoque-total-7'!A:AB,2,0)) | D14: =IFERROR(IF('produto-estoque-total-7'!A13="","",'produto-estoque-total-7'!A13),"") | E14: =IF(D14="","",VLOOKUP(D14,'produto-estoque-total-7'!A:AB,4,0)) | F14: =IF(D14="","",VLOOKUP(D14,'produto-estoque-total-7'!A:AB,13,0)) | G14: =IF(F14="","",VLOOKUP(F14,'FORNECEDORES X COMPRADOR'!A:D,4,0)) | H14: =IF(F14="","",VLOOKUP(F14,'FORNECEDORES X COMPRADOR'!A:E,5,0)) | I14: =IF(D14="","",VLOOKUP(D14,'produto-estoque-total-7'!A:AB,15,0)) | J14: =IF(D14="","",VLOOKUP(D14,'produto-estoque-total-7'!A:AB,19,0)) | K14: =IF(D14="","",VLOOKUP(D14,'produto-estoque-total-7'!A:AB,20,0)) | L14: =IF(D14="","",VLOOKUP(D14,'produto-estoque-total-7'!A:AB,17,0)) | M14: =IF(D14="","",VLOOKUP(D14,'produto-estoque-total-7'!A:AB,18,0)) | N14: =IF(D14="","",VLOOKUP(D14,'produto-estoque-total-7'!A:AB,21,0)) | O14: =IF(D14="","",VLOOKUP(D14,'produto-estoque-total-7'!A:AB,22,0)) | P14: =IF(D14="","",VLOOKUP(D14,'produto-estoque-total-7'!A:AB,23,0)) | Q14: =IF(D14="","",VLOOKUP(D14,'produto-estoque-total-7'!A:AB,24,0)) | R14: =IFERROR(IF(D14="","",VLOOKUP(D14,'produto-venda-7'!B:N,13,0)),"C") | S14: =IF(D14="","",VLOOKUP(D14,'produto-estoque-total-7'!A:AB,6,0)) | T14: =IF(D14="","",VLOOKUP(D14,'produto-estoque-total-7'!A:AB,5,0)) | U14: =IF(D14="","",VLOOKUP(D14,'produto-estoque-total-7'!A:AB,11,0)) | V14: =IF(D14="","",IFERROR(VLOOKUP(D14,'produto-entrada-7'!A:M,10,0),0)) | X14: =IF(D14="","",VLOOKUP(D14,'produto-estoque-total-7'!A:AB,8,0)) | Y14: =IF(D14="","",VLOOKUP(D14,'produto-estoque-total-7'!A:AB,9,0)) | Z14: =IF(D14="","",VLOOKUP(D14,'produto-estoque-total-7'!A:AB,10,0)) | AA14: =IFERROR(IF(D14="","",VLOOKUP(D14,'produto-venda-7'!B:N,4,0)),0) | AB14: =IFERROR(IF(D14="","",VLOOKUP(D14,'produto-venda-7'!B:N,5,0)),0) | AC14: =IF(D14="","",IFERROR(AA14/90,0)) | AD14: =IF(D14="","",IFERROR(VLOOKUP(D14,'produto-entrada-7'!A:M,4,0),0)) | AE14: =IFERROR(IF(D14="","",VLOOKUP(D14,'produto-venda-7'!B:N,10,0)),0) | AF14: =IF(D14="","",IFERROR(VLOOKUP(D14,'produto-entrada-7'!A:M,11,0),0)) | AG14: =IF(D14="","",IFERROR(VLOOKUP(D14,'produto-entrada-7'!A:M,12,0),0)) | AH14: =IF(D14="","",IFERROR(VLOOKUP(D14,'produto-entrada-7'!A:M,13,0),0)) | AI14: =IFERROR(IF(D14="","",VLOOKUP(D14,'produto-venda-7'!B:N,11,0)),0) | AJ14: =IF(D14="","",IFERROR(AI14*AB14,0)) | AK14: =IFERROR(IF(D14="","",VLOOKUP(F14,'ANALISE FORNECEDOR'!$A:$I,8,0)),"") | AL14: =IF(D14="","",AVERAGE(AM14,AK14)) | AM14: =IFERROR(IF(D14="","",VLOOKUP(F14,'ANALISE FORNECEDOR'!$A:$I,9,0)),"") | AN14: =IF(D14="","",IF(Y14>12,AI14*(U14+Y14),AI14*U14)) | AO14: =IF(D14="","",IF(Y14>12,AI14*(U14+V14+Y14),AI14*(U14+V14))) | AP14: =IF(D14="","",IF(Y14>12,AG14*(U14+Y14),AG14*U14)) | AQ14: =IF(D14="","",IF(Y14>12,AG14*(U14+V14+Y14),AG14*(U14+V14))) | AR14: =IF(D14="","",IF(OR(R14="A",R14="AA",R14="AAA"),AP14,0)) | AS14: =IF(D14="","",IF(R14="B",AP14,0)) | AT14: =IF(D14="","",IF(R14="C",AP14,0)) | AU14: =IF(D14="","",IFERROR(AN14/AJ14,0)) | AV14: =IF(D14="","",IFERROR(((AO14)/AJ14),0)) | AW14: =IF(D14="","",IF(OR(S14="S",NOT(AND(ISNUMBER(AC14),ISNUMBER(AL14),AC14*AL14>=0))),0,AC14*AL14)) | AX14: =IFERROR(IF(D14="","",AW14*AG14),0) | AY14: =IF(D14="","",IF(OR(S14="S",NOT(AND(ISNUMBER(AC14),ISNUMBER(AK14),AC14*AK14>=0))),0,AC14*AK14)) | AZ14: =IFERROR(IF(D14="","",IF(AY14=0,0,IF(((AY14)-(U14+Y14))<0,0,(AY14)-U14))),0) | BA14: =IF(D14="","",AZ14*AG14) | BB14: =IF(D14="","",IF(OR(R14="A",R14="AA",R14="AAA"),BA14,0)) | BC14: =IF(D14="","",IF(R14="B",BA14,0)) | BD14: =IF(D14="","",IF(R14="B",BA14,0)) | BE14: =IF(D14="","",IF(S14="S", 1, IF(AC14=0, 1, IF( IFERROR(((U14+Y14)*AG14)/((AC14*AK14)*AG14),0)<0, 0, IF( IFERROR(((U14+Y14)*AG14)/((AC14*AK14)*AG14),0)>1, 1, IFERROR(((U14+Y14)*AG14)/((AC14*AK14)*AG14),0) ) ) ) )) | BF14: =IF(D14="","",IF(S14="S", 1, IF(AC14=0, 1, IF( IFERROR(((U14+V14+Y14)*AG14)/((AC14*AK14)*AG14),0)<0, 0, IF( IFERROR(((U14+V14+Y14)*AG14)/((AC14*AK14)*AG14),0)>1, 1, IFERROR(((U14+V14+Y14)*AG14)/((AC14*AK14)*AG14),0) ) ) ) )) | BG14: =IF(D14="","",IF(S14="S",0,IF(AND(ISNUMBER(AC14),ISNUMBER(AM14)),IF(OR(AC14*AM14<0,ISERR(AC14*AM14)),0,AC14*AM14),0))) | BH14: =IF(D14="","",IF(BY14>TODAY()-60,0,IF(Y14>12,MAX(0,(U14+Y14)-BG14),MAX(0,U14-BG14)))) | BI14: =IF(D14="","",BH14*AG14) | BJ14: =IF(D14="","",IF(OR(R14="A",R14="AA",R14="AAA"),BI14,0)) | BK14: =IF(D14="","",IF(R14="B",BI14,0)) | BL14: =IF(D14="","",IF(R14="C",BI14,0)) | BM14: =IF(D14="","",IFERROR(MAX(0,MIN(BI14/AP14,1)),0)) | BN14: =IF(D14="","",AB14*AG14) | BO14: =IF(D14="","",(U14+V14+X14)*AG14) | BP14: =IF(D14="","",(AB14*3)*AG14) | BQ14: =IF(D14="","",IF(BO14-BP14>0,0,BO14-BP14)) | BR14: =IF(D14="","",IF(BO14-BP14-BN14>0,0,BO14-BP14-BN14)) | BS14: =IF(D14="","",IFERROR(AB14*AI14,0)) | BT14: =IF(D14="","",IFERROR(IF(X14>12, AI14*(U14+V14+X14), AI14*(U14+V14)),0)) | BU14: =IF(D14="","",IFERROR(((AB14*3)*AI14),0)) | BV14: =IF(D14="","",IF(BT14-BU14>0,0,BT14-BU14)) | BW14: =IF(D14="","",IF(BT14-BU14-BS14>0,0,BT14-BU14-BS14)) | BX14: =IF(D14="","",IFERROR(VLOOKUP(D14,'produto-entrada-7'!A:M,3,0),"SEM PEDIDO")) | BY14: =IF(D14="","",VLOOKUP(D14,'produto-estoque-total-7'!A:AB,25,0)) | BZ14: =IF(D14="","",IFERROR(VLOOKUP(D14,'produto-estoque-total-7'!A:AB,26,0)/100,0)) | CA14: =IF(D14="","",IFERROR(VLOOKUP(D14,'produto-estoque-total-7'!A:AB,27,0)/100,0)) | CB14: =IF(D14="","",V14*AF14) | CC14: =IF(D14="","",V14*AI14) | CD14: =IF(D14="","",VLOOKUP(D14,'produto-estoque-total-7'!A:AB,28,0))
... A1000: =IF(D1000="","",VLOOKUP(D1000,'produto-estoque-total-7'!A:AB,3,0)) | B1000: =IF(D1000="","",VLOOKUP(D1000,'produto-estoque-total-7'!A:AB,12,0)) | C1000: =IF(D1000="","",VLOOKUP(D1000,'produto-estoque-total-7'!A:AB,2,0)) | D1000: =IFERROR(IF('produto-estoque-total-7'!A999="","",'produto-estoque-total-7'!A999),"") | E1000: =IF(D1000="","",VLOOKUP(D1000,'produto-estoque-total-7'!A:AB,4,0)) | F1000: =IF(D1000="","",VLOOKUP(D1000,'produto-estoque-total-7'!A:AB,13,0)) | G1000: =IF(F1000="","",VLOOKUP(F1000,'FORNECEDORES X COMPRADOR'!A:D,4,0)) | H1000: =IF(F1000="","",VLOOKUP(F1000,'FORNECEDORES X COMPRADOR'!A:E,5,0)) | I1000: =IF(D1000="","",VLOOKUP(D1000,'produto-estoque-total-7'!A:AB,15,0)) | J1000: =IF(D1000="","",VLOOKUP(D1000,'produto-estoque-total-7'!A:AB,19,0)) | K1000: =IF(D1000="","",VLOOKUP(D1000,'produto-estoque-total-7'!A:AB,20,0)) | L1000: =IF(D1000="","",VLOOKUP(D1000,'produto-estoque-total-7'!A:AB,17,0)) | M1000: =IF(D1000="","",VLOOKUP(D1000,'produto-estoque-total-7'!A:AB,18,0)) | N1000: =IF(D1000="","",VLOOKUP(D1000,'produto-estoque-total-7'!A:AB,21,0)) | O1000: =IF(D1000="","",VLOOKUP(D1000,'produto-estoque-total-7'!A:AB,22,0)) | P1000: =IF(D1000="","",VLOOKUP(D1000,'produto-estoque-total-7'!A:AB,23,0)) | Q1000: =IF(D1000="","",VLOOKUP(D1000,'produto-estoque-total-7'!A:AB,24,0)) | R1000: =IFERROR(IF(D1000="","",VLOOKUP(D1000,'produto-venda-7'!B:N,13,0)),"C") | S1000: =IF(D1000="","",VLOOKUP(D1000,'produto-estoque-total-7'!A:AB,6,0)) | T1000: =IF(D1000="","",VLOOKUP(D1000,'produto-estoque-total-7'!A:AB,5,0)) | U1000: =IF(D1000="","",VLOOKUP(D1000,'produto-estoque-total-7'!A:AB,11,0)) | V1000: =IF(D1000="","",IFERROR(VLOOKUP(D1000,'produto-entrada-7'!A:M,10,0),0)) | X1000: =IF(D1000="","",VLOOKUP(D1000,'produto-estoque-total-7'!A:AB,8,0)) | Y1000: =IF(D1000="","",VLOOKUP(D1000,'produto-estoque-total-7'!A:AB,9,0)) | Z1000: =IF(D1000="","",VLOOKUP(D1000,'produto-estoque-total-7'!A:AB,10,0)) | AA1000: =IFERROR(IF(D1000="","",VLOOKUP(D1000,'produto-venda-7'!B:N,4,0)),0) | AB1000: =IFERROR(IF(D1000="","",VLOOKUP(D1000,'produto-venda-7'!B:N,5,0)),0) | AC1000: =IF(D1000="","",IFERROR(AA1000/90,0)) | AD1000: =IF(D1000="","",IFERROR(VLOOKUP(D1000,'produto-entrada-7'!A:M,4,0),0)) | AE1000: =IFERROR(IF(D1000="","",VLOOKUP(D1000,'produto-venda-7'!B:N,10,0)),0) | AF1000: =IF(D1000="","",IFERROR(VLOOKUP(D1000,'produto-entrada-7'!A:M,11,0),0)) | AG1000: =IF(D1000="","",IFERROR(VLOOKUP(D1000,'produto-entrada-7'!A:M,12,0),0)) | AH1000: =IF(D1000="","",IFERROR(VLOOKUP(D1000,'produto-entrada-7'!A:M,13,0),0)) | AI1000: =IFERROR(IF(D1000="","",VLOOKUP(D1000,'produto-venda-7'!B:N,11,0)),0) | AJ1000: =IF(D1000="","",IFERROR(AI1000*AB1000,0)) | AK1000: =IFERROR(IF(D1000="","",VLOOKUP(F1000,'ANALISE FORNECEDOR'!$A:$I,8,0)),"") | AL1000: =IF(D1000="","",AVERAGE(AM1000,AK1000)) | AM1000: =IFERROR(IF(D1000="","",VLOOKUP(F1000,'ANALISE FORNECEDOR'!$A:$I,9,0)),"") | AN1000: =IF(D1000="","",IF(Y1000>12,AI1000*(U1000+Y1000),AI1000*U1000)) | AO1000: =IF(D1000="","",IF(Y1000>12,AI1000*(U1000+V1000+Y1000),AI1000*(U1000+V1000))) | AP1000: =IF(D1000="","",IF(Y1000>12,AG1000*(U1000+Y1000),AG1000*U1000)) | AQ1000: =IF(D1000="","",IF(Y1000>12,AG1000*(U1000+V1000+Y1000),AG1000*(U1000+V1000))) | AR1000: =IF(D1000="","",IF(OR(R1000="A",R1000="AA",R1000="AAA"),AP1000,0)) | AS1000: =IF(D1000="","",IF(R1000="B",AP1000,0)) | AT1000: =IF(D1000="","",IF(R1000="C",AP1000,0)) | AU1000: =IF(D1000="","",IFERROR(AN1000/AJ1000,0)) | AV1000: =IF(D1000="","",IFERROR(((AO1000)/AJ1000),0)) | AW1000: =IF(D1000="","",IF(OR(S1000="S",NOT(AND(ISNUMBER(AC1000),ISNUMBER(AL1000),AC1000*AL1000>=0))),0,AC1000*AL1000)) | AX1000: =IFERROR(IF(D1000="","",AW1000*AG1000),0) | AY1000: =IF(D1000="","",IF(OR(S1000="S",NOT(AND(ISNUMBER(AC1000),ISNUMBER(AK1000),AC1000*AK1000>=0))),0,AC1000*AK1000)) | AZ1000: =IFERROR(IF(D1000="","",IF(AY1000=0,0,IF(((AY1000)-(U1000+Y1000))<0,0,(AY1000)-U1000))),0) | BA1000: =IF(D1000="","",AZ1000*AG1000) | BB1000: =IF(D1000="","",IF(OR(R1000="A",R1000="AA",R1000="AAA"),BA1000,0)) | BC1000: =IF(D1000="","",IF(R1000="B",BA1000,0)) | BD1000: =IF(D1000="","",IF(R1000="B",BA1000,0)) | BE1000: =IF(D1000="","",IF(S1000="S", 1, IF(AC1000=0, 1, IF( IFERROR(((U1000+Y1000)*AG1000)/((AC1000*AK1000)*AG1000),0)<0, 0, IF( IFERROR(((U1000+Y1000)*AG1000)/((AC1000*AK1000)*AG1000),0)>1, 1, IFERROR(((U1000+Y1000)*AG1000)/((AC1000*AK1000)*AG1000),0) ) ) ) )) | BF1000: =IF(D1000="","",IF(S1000="S", 1, IF(AC1000=0, 1, IF( IFERROR(((U1000+V1000+Y1000)*AG1000)/((AC1000*AK1000)*AG1000),0)<0, 0, IF( IFERROR(((U1000+V1000+Y1000)*AG1000)/((AC1000*AK1000)*AG1000),0)>1, 1, IFERROR(((U1000+V1000+Y1000)*AG1000)/((AC1000*AK1000)*AG1000),0) ) ) ) )) | BG1000: =IF(D1000="","",IF(S1000="S",0,IF(AND(ISNUMBER(AC1000),ISNUMBER(AM1000)),IF(OR(AC1000*AM1000<0,ISERR(AC1000*AM1000)),0,AC1000*AM1000),0))) | BH1000: =IF(D1000="","",IF(BY1000>TODAY()-60,0,IF(Y1000>12,MAX(0,(U1000+Y1000)-BG1000),MAX(0,U1000-BG1000)))) | BI1000: =IF(D1000="","",BH1000*AG1000) | BJ1000: =IF(D1000="","",IF(OR(R1000="A",R1000="AA",R1000="AAA"),BI1000,0)) | BK1000: =IF(D1000="","",IF(R1000="B",BI1000,0)) | BL1000: =IF(D1000="","",IF(R1000="C",BI1000,0)) | BM1000: =IF(D1000="","",IFERROR(MAX(0,MIN(BI1000/AP1000,1)),0)) | BN1000: =IF(D1000="","",AB1000*AG1000) | BO1000: =IF(D1000="","",(U1000+V1000+X1000)*AG1000) | BP1000: =IF(D1000="","",(AB1000*3)*AG1000) | BQ1000: =IF(D1000="","",IF(BO1000-BP1000>0,0,BO1000-BP1000)) | BR1000: =IF(D1000="","",IF(BO1000-BP1000-BN1000>0,0,BO1000-BP1000-BN1000)) | BS1000: =IF(D1000="","",IFERROR(AB1000*AI1000,0)) | BT1000: =IF(D1000="","",IFERROR(IF(X1000>12, AI1000*(U1000+V1000+X1000), AI1000*(U1000+V1000)),0)) | BU1000: =IF(D1000="","",IFERROR(((AB1000*3)*AI1000),0)) | BV1000: =IF(D1000="","",IF(BT1000-BU1000>0,0,BT1000-BU1000)) | BW1000: =IF(D1000="","",IF(BT1000-BU1000-BS1000>0,0,BT1000-BU1000-BS1000)) | BX1000: =IF(D1000="","",IFERROR(VLOOKUP(D1000,'produto-entrada-7'!A:M,3,0),"SEM PEDIDO")) | BY1000: =IF(D1000="","",VLOOKUP(D1000,'produto-estoque-total-7'!A:AB,25,0)) | BZ1000: =IF(D1000="","",IFERROR(VLOOKUP(D1000,'produto-estoque-total-7'!A:AB,26,0)/100,0)) | CA1000: =IF(D1000="","",IFERROR(VLOOKUP(D1000,'produto-estoque-total-7'!A:AB,27,0)/100,0)) | CB1000: =IF(D1000="","",V1000*AF1000) | CC1000: =IF(D1000="","",V1000*AI1000) | CD1000: =IF(D1000="","",VLOOKUP(D1000,'produto-estoque-total-7'!A:AB,28,0))

Sheet ANALISE FORNECEDOR
A1: FILIAL | B1: ='ANALISE PRODUTO'!A3 | D1: =D115 | E1: =E115 | F1: =F115 | G1: =G115 | H1: =H115 | I1: =I115 | J1: =J115 | K1: =K115 | ... AI1: =AI115 | AL1: =AL115 | AM1: =AM115 | AN1: =AN115 | AO1: =AO115 | AP1: =AP115 | AQ1: =AQ115 | AR1: =AR115 | AS1: =AS115 | ... CL1: =CL115 | CN1: =CN115 | CO1: =CO115 | CP1: =CP115 | CQ1: =CQ115 | CR1: =CR115 | CS1: =CS115 | CT1: =CT115 | CU1: =CU115 | ... EM1: =EM115 | EO1: =EO115 | EP1: =EP115 | EQ1: =EQ115 | ER1: =ER115 | ES1: =ES115 | EU1: =EU115 | EV1: =EV115 | EW1: =EW115 | EX1: =EX115 | EY1: =EY115 | EZ1: =EZ115 | FA1: =FA115 | FB1: =FB115 | ... FF1: =FF115
A3: COD | B3: Fornecedor | C3: COMPRADOR | D3: NIVEL SERVIÇO RUPTURA S/ PENDÊNCIA | E3: NIVEL SERVIÇO RUPTURA C/ PENDÊNCIA | F3: MÊS S/ PENDÊNCIA | G3: MÊS + PENDÊNCIA | H3: PRAZO RUPTURA | I3: PRAZO EXCESSO | J3: VALOR ESTOQUE PREÇO CUSTO | K3: VALOR ESTOQUE PREÇO VENDA | L3: RUPTURA VALOR A | M3: RUPTURA VALOR B | N3: RUPTURA VALOR C | O3: RUPTURA VALOR | P3: % RUPTURA TOTAL | Q3: % RUPTURA CURVA A | R3: EXCESSO VALOR A | S3: EXCESSO VALOR B | T3: EXCESSO VALOR C | U3: EXCESSO VALOR | V3: % EXCESSO TOTAL | W3: % EXCESSO CURVA B/C | X3: SKU INDUSTRIA | Y3: SKU INDUSTRIA FL | Z3: SKU INDUSTRIA ATIVOS | AA3: PMP | AB3: PRAZO CLIENTE | AC3: VALOR VENDA ATUAL | AD3: VALOR VENDA PROJETADA | AE3: PROJETO | AF3: % PROJETO | AG3: LUCRO PROJETO | AH3: LUCRO REALIZADO | AI3: % LUCRO | AJ3: DATA ULTIMA ENTRADA | AL3: FATURAMENTO jan/23 | AM3: FATURAMENTO fev/23 | AN3: FATURAMENTO mar/23 | AO3: FATURAMENTO abr/23 | AP3: FATURAMENTO mai/23 | AQ3: FATURAMENTO jun/23 | AR3: FATURAMENTO jul/23 | AS3: FATURAMENTO ago/23 | AT3: FATURAMENTO set/23 | AU3: FATURAMENTO out/23 | AV3: FATURAMENTO nov/23 | AW3: FATURAMENTO dez/23 | AX3: FATURAMENTO 2023 | AY3: FATURAMENTO jan/24 | AZ3: FATURAMENTO fev/24 | BA3: FATURAMENTO mar/24 | BB3: FATURAMENTO abr/24 | BC3: FATURAMENTO mai/24 | BD3: FATURAMENTO jun/24 | BE3: FATURAMENTO jul/24 | BF3: FATURAMENTO ago/24 | BG3: FATURAMENTO set/24 | BH3: FATURAMENTO out/24 | BI3: FATURAMENTO nov/24 | BJ3: FATURAMENTO dez/24 | BK3: FATURAMENTO 2024 | BL3: FATURAMENTO jan/25 | BM3: FATURAMENTO fev/25 | BN3: FATURAMENTO mar/25 | BO3: FATURAMENTO abr/25 | BP3: FATURAMENTO mai/25 | BQ3: FATURAMENTO jun/25 | BR3: FATURAMENTO jul/25 | BS3: FATURAMENTO ago/25 | BT3: FATURAMENTO set/25 | BU3: FATURAMENTO out/25 | BV3: FATURAMENTO nov/25 | BW3: FATURAMENTO dez/25 | BX3: FATURAMENTO 2025 | BY3: FATURAMENTO jan/26 | BZ3: FATURAMENTO fev/26 | CA3: FATURAMENTO mar/26 | CB3: FATURAMENTO abr/26 | CC3: FATURAMENTO mai/26 | CD3: FATURAMENTO jun/26 | CE3: FATURAMENTO jul/26 | CF3: FATURAMENTO ago/26 | CG3: FATURAMENTO set/26 | CH3: FATURAMENTO out/26 | CI3: FATURAMENTO nov/26 | CJ3: FATURAMENTO dez/26 | CK3: FATURAMENTO 2026 | CL3: MÉDIA 2026 | CN3: ENTRADA jan/23 | CO3: ENTRADA fev/23 | CP3: ENTRADA mar/23 | CQ3: ENTRADA mar/23 | CR3: ENTRADA mai/23 | CS3: ENTRADA jun/23 | CT3: ENTRADA jul/23 | CU3: ENTRADA ago/23 | CV3: ENTRADA set/23 | CW3: ENTRADA out/23 | CX3: ENTRADA nov/23 | CY3: ENTRADA dez/23 | CZ3: ENTRADA 2023 | DA3: ENTRADA jan/24 | DB3: ENTRADA fev/24 | DC3: ENTRADA mar/24 | DD3: ENTRADA abr/24 | DE3: ENTRADA mai/24 | DF3: ENTRADA jun/24 | DG3: ENTRADA jul/24 | DH3: ENTRADA ago/24 | DI3: ENTRADA set/24 | DJ3: ENTRADA out/24 | DK3: ENTRADA nov/24 | DL3: ENTRADA dez/24 | DM3: ENTRADA 2024 | DN3: ENTRADA jan/25 | DO3: ENTRADA fev/25 | DP3: ENTRADA mar/25 | DQ3: ENTRADA abr/25 | DR3: ENTRADA mai/25 | DS3: ENTRADA jun/25 | DT3: ENTRADA jul/25 | DU3: ENTRADA ago/25 | DV3: ENTRADA set/25 | DW3: ENTRADA out/25 | DX3: ENTRADA nov/25 | DY3: 1012 | DZ3: ENTRADA 2025 | EA3: ENTRADA jan/26 | EB3: ENTRADA fev/26 | EC3: ENTRADA mar/26 | ED3: ENTRADA abr/26 | EE3: ENTRADA mai/26 | EF3: ENTRADA jun/26 | EG3: ENTRADA jul/26 | EH3: ENTRADA ago/26 | EI3: ENTRADA set/26 | EJ3: ENTRADA out/26 | EK3: ENTRADA nov/26 | EL3: ENTRADA dez/26 | EM3: ENTRADA 2026 | EO3: LEAD TIME TOTAL | EP3: LEAD TIME NOTAS 48H | EQ3: ATRASO EMISSÃO | ER3: SALDO A RECEBER | ES3: SALDO A APLICAR | EU3: VENDA MÉDIA MÊS (CUSTO) | EV3: ESTOQUE ATUAL + DEMANDA | EW3: ESTOQUE IDEAL | EX3: COMPRA MÊS ATUAL | EY3: COMPRA PRÓXIMO MÊS | EZ3: VENDA MÉDIA MÊS (VENDA) | FA3: ESTOQUE ATUAL + DEMANDA | FB3: ESTOQUE IDEAL | FC3: COMPRA MÊS ATUAL | FD3: COMPRA PRÓXIMO MÊS | FE3: PEDIDO PENDENTE A PREÇO COMPRA | FF3: PEDIDO PENDENTE A PREÇO VENDA | FH3: POSITIVAÇÃO jan/23 | FI3: POSITIVAÇÃO fev/23 | FJ3: POSITIVAÇÃO mar/23 | FK3: POSITIVAÇÃO mar/23 | FL3: POSITIVAÇÃO mai/23 | FM3: POSITIVAÇÃO jun/23 | FN3: POSITIVAÇÃO jul/23 | FO3: POSITIVAÇÃO ago/23 | FP3: POSITIVAÇÃO set/23 | FQ3: POSITIVAÇÃO out/23 | FR3: POSITIVAÇÃO nov/23 | FS3: POSITIVAÇÃO dez/23 | FT3: POSITIVAÇÃO 2023 | FU3: POSITIVAÇÃO jan/24 | FV3: POSITIVAÇÃO fev/24 | FW3: POSITIVAÇÃO mar/24 | FX3: POSITIVAÇÃO abr/24 | FY3: POSITIVAÇÃO mai/24 | FZ3: POSITIVAÇÃO jun/24 | GA3: POSITIVAÇÃO jul/24 | GB3: POSITIVAÇÃO ago/24 | GC3: POSITIVAÇÃO set/24 | GD3: POSITIVAÇÃO out/24 | GE3: POSITIVAÇÃO nov/24 | GF3: POSITIVAÇÃO dez/24 | GG3: POSITIVAÇÃO 2024 | GH3: POSITIVAÇÃO jan/25 | GI3: POSITIVAÇÃO fev/25 | GJ3: POSITIVAÇÃO mar/25 | GK3: POSITIVAÇÃO abr/25 | GL3: POSITIVAÇÃO mai/25 | GM3: POSITIVAÇÃO jun/25 | GN3: POSITIVAÇÃO jul/25 | GO3: POSITIVAÇÃO ago/25 | GP3: POSITIVAÇÃO set/25 | GQ3: POSITIVAÇÃO out/25 | GR3: POSITIVAÇÃO nov/25 | GS3: POSITIVAÇÃO dez/25 | GT3: POSITIVAÇÃO 2025
A4: 36063 | B4: =VLOOKUP(A4,'FORNECEDORES X COMPRADOR'!$A:$D,4,0) | C4: =VLOOKUP(A4,'FORNECEDORES X COMPRADOR'!$A:$E,5,0) | D4: =IFERROR(AVERAGEIF('ANALISE PRODUTO'!F:F,A4,'ANALISE PRODUTO'!BE:BE),"") | E4: =IFERROR(AVERAGEIF('ANALISE PRODUTO'!F:F,A4,'ANALISE PRODUTO'!BF:BF),"") | F4: {=IFERROR( IF( SUMPRODUCT( IFERROR(--('ANALISE PRODUTO'!$F$3:$F$10000=A4),0) * IFERROR(--'ANALISE PRODUTO'!$AJ$3:$AJ$10000,0) )=0, "", SUMPRODUCT( IFERROR(--('ANALISE PRODUTO'!$F$3:$F$10000=A4),0) * IFERROR(--'ANALISE PRODUTO'!$AN$3:$AN$10000,0) ) / SUMPRODUCT( IFERROR(--('ANALISE PRODUTO'!$F$3:$F$10000=A4),0) * IFERROR(--'ANALISE PRODUTO'!$AJ$3:$AJ$10000,0) ) ), "" )} | G4: {=IFERROR( IF( SUMPRODUCT( IFERROR(--('ANALISE PRODUTO'!$F$3:$F$10000=A4),0) * IFERROR(--'ANALISE PRODUTO'!$AJ$3:$AJ$10000,0) )=0, "", SUMPRODUCT( IFERROR(--('ANALISE PRODUTO'!$F$3:$F$10000=A4),0) * IFERROR(--'ANALISE PRODUTO'!$AO$3:$AO$10000,0) ) / SUMPRODUCT( IFERROR(--('ANALISE PRODUTO'!$F$3:$F$10000=A4),0) * IFERROR(--'ANALISE PRODUTO'!$AJ$3:$AJ$10000,0) ) ), "" )} | H4: 60 | I4: 90 | J4: =SUMIF('ANALISE PRODUTO'!F:F, A4, 'ANALISE PRODUTO'!AP:AP) | K4: =SUMIF('ANALISE PRODUTO'!F:F, A4, 'ANALISE PRODUTO'!AN:AN) | L4: =SUMIF('ANALISE PRODUTO'!F:F, A4, 'ANALISE PRODUTO'!BB:BB) | M4: =SUMIF('ANALISE PRODUTO'!F:F, A4, 'ANALISE PRODUTO'!BC:BC) | N4: =SUMIF('ANALISE PRODUTO'!F:F, A4, 'ANALISE PRODUTO'!BD:BD) | O4: =SUMIF('ANALISE PRODUTO'!F:F, A4, 'ANALISE PRODUTO'!BA:BA) | P4: =IF(J4=0, 0, IF(O4/J4=0, 0, O4/J4)) | Q4: =IF(J4=0, 0, IF(L4/J4=0, 0, L4/J4)) | R4: =SUMIF('ANALISE PRODUTO'!F:F, A4, 'ANALISE PRODUTO'!BJ:BJ) | S4: =SUMIF('ANALISE PRODUTO'!F:F, A4, 'ANALISE PRODUTO'!BK:BK) | T4: =SUMIF('ANALISE PRODUTO'!F:F, A4, 'ANALISE PRODUTO'!BL:BL) | U4: =SUMIFS('ANALISE PRODUTO'!BI:BI, 'ANALISE PRODUTO'!F:F, A4) | V4: =IF(C4="DESCONTINUADO", 0, IF(J4=0, 0, IF(U4/J4=0, 0, U4/J4))) | W4: =IF(OR(C4="DESCONTINUADO", J4=0), 0, IFERROR((S4+T4)/J4, 0)) | X4: =COUNTIF('ANALISE PRODUTO'!F:F, A4) | Y4: =COUNTIFS('ANALISE PRODUTO'!F:F, A4, 'ANALISE PRODUTO'!S:S, "S") | Z4: =X4-Y4 | AA4: =IFERROR(IF(COUNTIF('contas-pagas-fornecedor-7'!$C:$C,B4)>1, AVERAGEIF('contas-pagas-fornecedor-7'!$C:$C,B4,'contas-pagas-fornecedor-7'!$I:$I), VLOOKUP(B4,'contas-pagas-fornecedor-7'!$C:$Q,7,FALSE)), "") | AB4: {=IFERROR( INDEX('fornecedor-venda-por-filial-ger'!J:J, MATCH(1, ('fornecedor-venda-por-filial-ger'!A:A=A4) * ('fornecedor-venda-por-filial-ger'!B:B=$B$1), 0) ), "")} | AC4: {=IFERROR( INDEX('fornecedor-venda-por-filial-ger'!O:O, MATCH(1, ('fornecedor-venda-por-filial-ger'!A:A=A4) * ('fornecedor-venda-por-filial-ger'!B:B=$B$1), 0) ), "")} | AD4: =IFERROR(VLOOKUP(A4,'venda-fornecedor-12-meses-7'!A:AC,3,0),"") | AE4: {=IFERROR( INDEX('fornecedor-venda-por-filial-ger'!N:N, MATCH(1, ('fornecedor-venda-por-filial-ger'!A:A=A4) * ('fornecedor-venda-por-filial-ger'!B:B=$B$1), 0) ), "")} | AF4: =IF(J4<=0,"100,00%",IFERROR(AD4/AE4,1)) | AG4: {=IFERROR( INDEX('fornecedor-venda-por-filial-ger'!L:L, MATCH(1, ('fornecedor-venda-por-filial-ger'!A:A=A4)* ('fornecedor-venda-por-filial-ger'!B:B=$B$1), 0) )/100, "")} | AH4: {=IFERROR( INDEX('fornecedor-venda-por-filial-ger'!S:S, MATCH(1, ('fornecedor-venda-por-filial-ger'!A:A=A4) * ('fornecedor-venda-por-filial-ger'!B:B=$B$1), 0) )/100, "")} | AI4: =IFERROR(IF(OR(AH4="",AG4=""),"",IF(J4=0,0,AH4-AG4)),"") | AJ4: {=IF(MAX(IF('ANALISE PRODUTO'!F:F=A4,'ANALISE PRODUTO'!AD:AD))=0,"SEM ENTRADA",MAX(IF('ANALISE PRODUTO'!F:F=A4,'ANALISE PRODUTO'!AD:AD)))} | AL4: =IF(IFERROR(VLOOKUP($A4,'VENDA 2023'!$1:$1048576,3 + (COLUMN(A1)-1)*2,FALSE),"")=0,"",IFERROR(VLOOKUP($A4,'VENDA 2023'!$1:$1048576,3 + (COLUMN(A1)-1)*2,FALSE),"")) | AM4: =IF(IFERROR(VLOOKUP($A4,'VENDA 2023'!$1:$1048576,3 + (COLUMN(B1)-1)*2,FALSE),"")=0,"",IFERROR(VLOOKUP($A4,'VENDA 2023'!$1:$1048576,3 + (COLUMN(B1)-1)*2,FALSE),"")) | AN4: =IF(IFERROR(VLOOKUP($A4,'VENDA 2023'!$1:$1048576,3 + (COLUMN(C1)-1)*2,FALSE),"")=0,"",IFERROR(VLOOKUP($A4,'VENDA 2023'!$1:$1048576,3 + (COLUMN(C1)-1)*2,FALSE),"")) | AO4: =IF(IFERROR(VLOOKUP($A4,'VENDA 2023'!$1:$1048576,3 + (COLUMN(D1)-1)*2,FALSE),"")=0,"",IFERROR(VLOOKUP($A4,'VENDA 2023'!$1:$1048576,3 + (COLUMN(D1)-1)*2,FALSE),"")) | AP4: =IF(IFERROR(VLOOKUP($A4,'VENDA 2023'!$1:$1048576,3 + (COLUMN(E1)-1)*2,FALSE),"")=0,"",IFERROR(VLOOKUP($A4,'VENDA 2023'!$1:$1048576,3 + (COLUMN(E1)-1)*2,FALSE),"")) | AQ4: =IF(IFERROR(VLOOKUP($A4,'VENDA 2023'!$1:$1048576,3 + (COLUMN(F1)-1)*2,FALSE),"")=0,"",IFERROR(VLOOKUP($A4,'VENDA 2023'!$1:$1048576,3 + (COLUMN(F1)-1)*2,FALSE),"")) | AR4: =IF(IFERROR(VLOOKUP($A4,'VENDA 2023'!$1:$1048576,3 + (COLUMN(G1)-1)*2,FALSE),"")=0,"",IFERROR(VLOOKUP($A4,'VENDA 2023'!$1:$1048576,3 + (COLUMN(G1)-1)*2,FALSE),"")) | AS4: =IF(IFERROR(VLOOKUP($A4,'VENDA 2023'!$1:$1048576,3 + (COLUMN(H1)-1)*2,FALSE),"")=0,"",IFERROR(VLOOKUP($A4,'VENDA 2023'!$1:$1048576,3 + (COLUMN(H1)-1)*2,FALSE),"")) | ... AW4: =IF(IFERROR(VLOOKUP($A4,'VENDA 2023'!$1:$1048576,3 + (COLUMN(L1)-1)*2,FALSE),"")=0,"",IFERROR(VLOOKUP($A4,'VENDA 2023'!$1:$1048576,3 + (COLUMN(L1)-1)*2,FALSE),"")) | AX4: =IF(COUNT(AL4:AW4)=0,"",SUM(AL4:AW4)) | AY4: =IF(IFERROR(VLOOKUP($A4,'VENDA 2024'!$1:$1048576,3 + (COLUMN(A1)-1)*2,FALSE),"")=0,"",IFERROR(VLOOKUP($A4,'VENDA 2024'!$1:$1048576,3 + (COLUMN(A1)-1)*2,FALSE),"")) | AZ4: =IF(IFERROR(VLOOKUP($A4,'VENDA 2024'!$1:$1048576,3 + (COLUMN(B1)-1)*2,FALSE),"")=0,"",IFERROR(VLOOKUP($A4,'VENDA 2024'!$1:$1048576,3 + (COLUMN(B1)-1)*2,FALSE),"")) | BA4: =IF(IFERROR(VLOOKUP($A4,'VENDA 2024'!$1:$1048576,3 + (COLUMN(C1)-1)*2,FALSE),"")=0,"",IFERROR(VLOOKUP($A4,'VENDA 2024'!$1:$1048576,3 + (COLUMN(C1)-1)*2,FALSE),"")) | BB4: =IF(IFERROR(VLOOKUP($A4,'VENDA 2024'!$1:$1048576,3 + (COLUMN(D1)-1)*2,FALSE),"")=0,"",IFERROR(VLOOKUP($A4,'VENDA 2024'!$1:$1048576,3 + (COLUMN(D1)-1)*2,FALSE),"")) | BC4: =IF(IFERROR(VLOOKUP($A4,'VENDA 2024'!$1:$1048576,3 + (COLUMN(E1)-1)*2,FALSE),"")=0,"",IFERROR(VLOOKUP($A4,'VENDA 2024'!$1:$1048576,3 + (COLUMN(E1)-1)*2,FALSE),"")) | BD4: =IF(IFERROR(VLOOKUP($A4,'VENDA 2024'!$1:$1048576,3 + (COLUMN(F1)-1)*2,FALSE),"")=0,"",IFERROR(VLOOKUP($A4,'VENDA 2024'!$1:$1048576,3 + (COLUMN(F1)-1)*2,FALSE),"")) | BE4: =IF(IFERROR(VLOOKUP($A4,'VENDA 2024'!$1:$1048576,3 + (COLUMN(G1)-1)*2,FALSE),"")=0,"",IFERROR(VLOOKUP($A4,'VENDA 2024'!$1:$1048576,3 + (COLUMN(G1)-1)*2,FALSE),"")) | BF4: =IF(IFERROR(VLOOKUP($A4,'VENDA 2024'!$1:$1048576,3 + (COLUMN(H1)-1)*2,FALSE),"")=0,"",IFERROR(VLOOKUP($A4,'VENDA 2024'!$1:$1048576,3 + (COLUMN(H1)-1)*2,FALSE),"")) | ... BJ4: =IF(IFERROR(VLOOKUP($A4,'VENDA 2024'!$1:$1048576,3 + (COLUMN(L1)-1)*2,FALSE),"")=0,"",IFERROR(VLOOKUP($A4,'VENDA 2024'!$1:$1048576,3 + (COLUMN(L1)-1)*2,FALSE),"")) | BK4: =IF(COUNT(AY4:BJ4)=0,"",SUM(AY4:BJ4)) | BL4: =IF(IFERROR(VLOOKUP($A4,'VENDA 2025'!$1:$1048576,3 + (COLUMN(A1)-1)*2,FALSE),"")=0,"",IFERROR(VLOOKUP($A4,'VENDA 2025'!$1:$1048576,3 + (COLUMN(A1)-1)*2,FALSE),"")) | BM4: =IF(IFERROR(VLOOKUP($A4,'VENDA 2025'!$1:$1048576,3 + (COLUMN(B1)-1)*2,FALSE),"")=0,"",IFERROR(VLOOKUP($A4,'VENDA 2025'!$1:$1048576,3 + (COLUMN(B1)-1)*2,FALSE),"")) | BN4: =IF(IFERROR(VLOOKUP($A4,'VENDA 2025'!$1:$1048576,3 + (COLUMN(C1)-1)*2,FALSE),"")=0,"",IFERROR(VLOOKUP($A4,'VENDA 2025'!$1:$1048576,3 + (COLUMN(C1)-1)*2,FALSE),"")) | BO4: =IF(IFERROR(VLOOKUP($A4,'VENDA 2025'!$1:$1048576,3 + (COLUMN(D1)-1)*2,FALSE),"")=0,"",IFERROR(VLOOKUP($A4,'VENDA 2025'!$1:$1048576,3 + (COLUMN(D1)-1)*2,FALSE),"")) | BP4: =IF(IFERROR(VLOOKUP($A4,'VENDA 2025'!$1:$1048576,3 + (COLUMN(E1)-1)*2,FALSE),"")=0,"",IFERROR(VLOOKUP($A4,'VENDA 2025'!$1:$1048576,3 + (COLUMN(E1)-1)*2,FALSE),"")) | BQ4: =IF(IFERROR(VLOOKUP($A4,'VENDA 2025'!$1:$1048576,3 + (COLUMN(F1)-1)*2,FALSE),"")=0,"",IFERROR(VLOOKUP($A4,'VENDA 2025'!$1:$1048576,3 + (COLUMN(F1)-1)*2,FALSE),"")) | BR4: =IF(IFERROR(VLOOKUP($A4,'VENDA 2025'!$1:$1048576,3 + (COLUMN(G1)-1)*2,FALSE),"")=0,"",IFERROR(VLOOKUP($A4,'VENDA 2025'!$1:$1048576,3 + (COLUMN(G1)-1)*2,FALSE),"")) | BS4: =IF(IFERROR(VLOOKUP($A4,'VENDA 2025'!$1:$1048576,3 + (COLUMN(H1)-1)*2,FALSE),"")=0,"",IFERROR(VLOOKUP($A4,'VENDA 2025'!$1:$1048576,3 + (COLUMN(H1)-1)*2,FALSE),"")) | ... BW4: =IF(IFERROR(VLOOKUP($A4,'VENDA 2025'!$1:$1048576,3 + (COLUMN(L1)-1)*2,FALSE),"")=0,"",IFERROR(VLOOKUP($A4,'VENDA 2025'!$1:$1048576,3 + (COLUMN(L1)-1)*2,FALSE),"")) | BX4: =IF(COUNT(BL4:BW4)=0,"",SUM(BL4:BW4)) | BY4: =IF(IFERROR(VLOOKUP($A4,'venda-fornecedor-12-meses-7'!$1:$1048576,4 + (COLUMN(A1)-1)*2,FALSE),"")=0,"",IFERROR(VLOOKUP($A4,'venda-fornecedor-12-meses-7'!$1:$1048576,4 + (COLUMN(A1)-1)*2,FALSE),"")) | BZ4: =IF(IFERROR(VLOOKUP($A4,'venda-fornecedor-12-meses-7'!$1:$1048576,4 + (COLUMN(B1)-1)*2,FALSE),"")=0,"",IFERROR(VLOOKUP($A4,'venda-fornecedor-12-meses-7'!$1:$1048576,4 + (COLUMN(B1)-1)*2,FALSE),"")) | CA4: =IF(IFERROR(VLOOKUP($A4,'venda-fornecedor-12-meses-7'!$1:$1048576,4 + (COLUMN(C1)-1)*2,FALSE),"")=0,"",IFERROR(VLOOKUP($A4,'venda-fornecedor-12-meses-7'!$1:$1048576,4 + (COLUMN(C1)-1)*2,FALSE),"")) | CB4: =IF(IFERROR(VLOOKUP($A4,'venda-fornecedor-12-meses-7'!$1:$1048576,4 + (COLUMN(D1)-1)*2,FALSE),"")=0,"",IFERROR(VLOOKUP($A4,'venda-fornecedor-12-meses-7'!$1:$1048576,4 + (COLUMN(D1)-1)*2,FALSE),"")) | CC4: =IF(IFERROR(VLOOKUP($A4,'venda-fornecedor-12-meses-7'!$1:$1048576,4 + (COLUMN(E1)-1)*2,FALSE),"")=0,"",IFERROR(VLOOKUP($A4,'venda-fornecedor-12-meses-7'!$1:$1048576,4 + (COLUMN(E1)-1)*2,FALSE),"")) | CD4: =IF(IFERROR(VLOOKUP($A4,'venda-fornecedor-12-meses-7'!$1:$1048576,4 + (COLUMN(F1)-1)*2,FALSE),"")=0,"",IFERROR(VLOOKUP($A4,'venda-fornecedor-12-meses-7'!$1:$1048576,4 + (COLUMN(F1)-1)*2,FALSE),"")) | CE4: =IF(IFERROR(VLOOKUP($A4,'venda-fornecedor-12-meses-7'!$1:$1048576,4 + (COLUMN(G1)-1)*2,FALSE),"")=0,"",IFERROR(VLOOKUP($A4,'venda-fornecedor-12-meses-7'!$1:$1048576,4 + (COLUMN(G1)-1)*2,FALSE),"")) | CF4: =IF(IFERROR(VLOOKUP($A4,'venda-fornecedor-12-meses-7'!$1:$1048576,4 + (COLUMN(H1)-1)*2,FALSE),"")=0,"",IFERROR(VLOOKUP($A4,'venda-fornecedor-12-meses-7'!$1:$1048576,4 + (COLUMN(H1)-1)*2,FALSE),"")) | ... CJ4: =IF(IFERROR(VLOOKUP($A4,'venda-fornecedor-12-meses-7'!$1:$1048576,4 + (COLUMN(L1)-1)*2,FALSE),"")=0,"",IFERROR(VLOOKUP($A4,'venda-fornecedor-12-meses-7'!$1:$1048576,4 + (COLUMN(L1)-1)*2,FALSE),"")) | CK4: =IF(COUNT(BY4:CJ4)=0,"",SUM(BY4:CJ4)) | CL4: =IF(COUNT(BY4:CJ4)=0,"",AVERAGE(BY4:CJ4)) | CN4: =IF(IFERROR(VLOOKUP($A4,'ENTRADA 2023'!$1:$1048576,3 + (COLUMN(A1)-1)*1,FALSE),"")=0,"",IFERROR(VLOOKUP($A4,'ENTRADA 2023'!$1:$1048576,3 + (COLUMN(A1)-1)*1,FALSE),"")) | CO4: =IF(IFERROR(VLOOKUP($A4,'ENTRADA 2023'!$1:$1048576,3 + (COLUMN(B1)-1)*1,FALSE),"")=0,"",IFERROR(VLOOKUP($A4,'ENTRADA 2023'!$1:$1048576,3 + (COLUMN(B1)-1)*1,FALSE),"")) | CP4: =IF(IFERROR(VLOOKUP($A4,'ENTRADA 2023'!$1:$1048576,3 + (COLUMN(C1)-1)*1,FALSE),"")=0,"",IFERROR(VLOOKUP($A4,'ENTRADA 2023'!$1:$1048576,3 + (COLUMN(C1)-1)*1,FALSE),"")) | CQ4: =IF(IFERROR(VLOOKUP($A4,'ENTRADA 2023'!$1:$1048576,3 + (COLUMN(D1)-1)*1,FALSE),"")=0,"",IFERROR(VLOOKUP($A4,'ENTRADA 2023'!$1:$1048576,3 + (COLUMN(D1)-1)*1,FALSE),"")) | CR4: =IF(IFERROR(VLOOKUP($A4,'ENTRADA 2023'!$1:$1048576,3 + (COLUMN(E1)-1)*1,FALSE),"")=0,"",IFERROR(VLOOKUP($A4,'ENTRADA 2023'!$1:$1048576,3 + (COLUMN(E1)-1)*1,FALSE),"")) | CS4: =IF(IFERROR(VLOOKUP($A4,'ENTRADA 2023'!$1:$1048576,3 + (COLUMN(F1)-1)*1,FALSE),"")=0,"",IFERROR(VLOOKUP($A4,'ENTRADA 2023'!$1:$1048576,3 + (COLUMN(F1)-1)*1,FALSE),"")) | CT4: =IF(IFERROR(VLOOKUP($A4,'ENTRADA 2023'!$1:$1048576,3 + (COLUMN(G1)-1)*1,FALSE),"")=0,"",IFERROR(VLOOKUP($A4,'ENTRADA 2023'!$1:$1048576,3 + (COLUMN(G1)-1)*1,FALSE),"")) | CU4: =IF(IFERROR(VLOOKUP($A4,'ENTRADA 2023'!$1:$1048576,3 + (COLUMN(H1)-1)*1,FALSE),"")=0,"",IFERROR(VLOOKUP($A4,'ENTRADA 2023'!$1:$1048576,3 + (COLUMN(H1)-1)*1,FALSE),"")) | ... CY4: =IF(IFERROR(VLOOKUP($A4,'ENTRADA 2023'!$1:$1048576,3 + (COLUMN(L1)-1)*1,FALSE),"")=0,"",IFERROR(VLOOKUP($A4,'ENTRADA 2023'!$1:$1048576,3 + (COLUMN(L1)-1)*1,FALSE),"")) | CZ4: =IF(COUNT(CN4:CY4)=0,"",SUM(CN4:CY4)) | DA4: =IF(IFERROR(VLOOKUP($A4,'ENTRADA 2024'!$1:$1048576,3 + (COLUMN(A1)-1)*1,FALSE),"")=0,"",IFERROR(VLOOKUP($A4,'ENTRADA 2024'!$1:$1048576,3 + (COLUMN(A1)-1)*1,FALSE),"")) | DB4: =IF(IFERROR(VLOOKUP($A4,'ENTRADA 2024'!$1:$1048576,3 + (COLUMN(B1)-1)*1,FALSE),"")=0,"",IFERROR(VLOOKUP($A4,'ENTRADA 2024'!$1:$1048576,3 + (COLUMN(B1)-1)*1,FALSE),"")) | DC4: =IF(IFERROR(VLOOKUP($A4,'ENTRADA 2024'!$1:$1048576,3 + (COLUMN(C1)-1)*1,FALSE),"")=0,"",IFERROR(VLOOKUP($A4,'ENTRADA 2024'!$1:$1048576,3 + (COLUMN(C1)-1)*1,FALSE),"")) | DD4: =IF(IFERROR(VLOOKUP($A4,'ENTRADA 2024'!$1:$1048576,3 + (COLUMN(D1)-1)*1,FALSE),"")=0,"",IFERROR(VLOOKUP($A4,'ENTRADA 2024'!$1:$1048576,3 + (COLUMN(D1)-1)*1,FALSE),"")) | DE4: =IF(IFERROR(VLOOKUP($A4,'ENTRADA 2024'!$1:$1048576,3 + (COLUMN(E1)-1)*1,FALSE),"")=0,"",IFERROR(VLOOKUP($A4,'ENTRADA 2024'!$1:$1048576,3 + (COLUMN(E1)-1)*1,FALSE),"")) | DF4: =IF(IFERROR(VLOOKUP($A4,'ENTRADA 2024'!$1:$1048576,3 + (COLUMN(F1)-1)*1,FALSE),"")=0,"",IFERROR(VLOOKUP($A4,'ENTRADA 2024'!$1:$1048576,3 + (COLUMN(F1)-1)*1,FALSE),"")) | DG4: =IF(IFERROR(VLOOKUP($A4,'ENTRADA 2024'!$1:$1048576,3 + (COLUMN(G1)-1)*1,FALSE),"")=0,"",IFERROR(VLOOKUP($A4,'ENTRADA 2024'!$1:$1048576,3 + (COLUMN(G1)-1)*1,FALSE),"")) | DH4: =IF(IFERROR(VLOOKUP($A4,'ENTRADA 2024'!$1:$1048576,3 + (COLUMN(H1)-1)*1,FALSE),"")=0,"",IFERROR(VLOOKUP($A4,'ENTRADA 2024'!$1:$1048576,3 + (COLUMN(H1)-1)*1,FALSE),"")) | ... DL4: =IF(IFERROR(VLOOKUP($A4,'ENTRADA 2024'!$1:$1048576,3 + (COLUMN(L1)-1)*1,FALSE),"")=0,"",IFERROR(VLOOKUP($A4,'ENTRADA 2024'!$1:$1048576,3 + (COLUMN(L1)-1)*1,FALSE),"")) | DM4: =IF(COUNT(DA4:DL4)=0,"",SUM(DA4:DL4)) | DN4: =IF(IFERROR(VLOOKUP($A4,'ENTRADA 2025'!$1:$1048576,3 + (COLUMN(A1)-1)*1,FALSE),"")=0,"",IFERROR(VLOOKUP($A4,'ENTRADA 2025'!$1:$1048576,3 + (COLUMN(A1)-1)*1,FALSE),"")) | DO4: =IF(IFERROR(VLOOKUP($A4,'ENTRADA 2025'!$1:$1048576,3 + (COLUMN(B1)-1)*1,FALSE),"")=0,"",IFERROR(VLOOKUP($A4,'ENTRADA 2025'!$1:$1048576,3 + (COLUMN(B1)-1)*1,FALSE),"")) | DP4: =IF(IFERROR(VLOOKUP($A4,'ENTRADA 2025'!$1:$1048576,3 + (COLUMN(C1)-1)*1,FALSE),"")=0,"",IFERROR(VLOOKUP($A4,'ENTRADA 2025'!$1:$1048576,3 + (COLUMN(C1)-1)*1,FALSE),"")) | DQ4: =IF(IFERROR(VLOOKUP($A4,'ENTRADA 2025'!$1:$1048576,3 + (COLUMN(D1)-1)*1,FALSE),"")=0,"",IFERROR(VLOOKUP($A4,'ENTRADA 2025'!$1:$1048576,3 + (COLUMN(D1)-1)*1,FALSE),"")) | DR4: =IF(IFERROR(VLOOKUP($A4,'ENTRADA 2025'!$1:$1048576,3 + (COLUMN(E1)-1)*1,FALSE),"")=0,"",IFERROR(VLOOKUP($A4,'ENTRADA 2025'!$1:$1048576,3 + (COLUMN(E1)-1)*1,FALSE),"")) | DS4: =IF(IFERROR(VLOOKUP($A4,'ENTRADA 2025'!$1:$1048576,3 + (COLUMN(F1)-1)*1,FALSE),"")=0,"",IFERROR(VLOOKUP($A4,'ENTRADA 2025'!$1:$1048576,3 + (COLUMN(F1)-1)*1,FALSE),"")) | DT4: =IF(IFERROR(VLOOKUP($A4,'ENTRADA 2025'!$1:$1048576,3 + (COLUMN(G1)-1)*1,FALSE),"")=0,"",IFERROR(VLOOKUP($A4,'ENTRADA 2025'!$1:$1048576,3 + (COLUMN(G1)-1)*1,FALSE),"")) | DU4: =IF(IFERROR(VLOOKUP($A4,'ENTRADA 2025'!$1:$1048576,3 + (COLUMN(H1)-1)*1,FALSE),"")=0,"",IFERROR(VLOOKUP($A4,'ENTRADA 2025'!$1:$1048576,3 + (COLUMN(H1)-1)*1,FALSE),"")) | ... DY4: =IF(IFERROR(VLOOKUP($A4,'ENTRADA 2025'!$1:$1048576,3 + (COLUMN(L1)-1)*1,FALSE),"")=0,"",IFERROR(VLOOKUP($A4,'ENTRADA 2025'!$1:$1048576,3 + (COLUMN(L1)-1)*1,FALSE),"")) | DZ4: =IF(COUNT(DN4:DY4)=0,"",SUM(DN4:DY4)) | EA4: =IF(IFERROR(VLOOKUP($A4,'entrada-fornecedor-12-meses-7'!$1:$1048576,3 + (COLUMN(A1)-1)*1,FALSE),"")=0,"",IFERROR(VLOOKUP($A4,'entrada-fornecedor-12-meses-7'!$1:$1048576,3 + (COLUMN(A1)-1)*1,FALSE),"")) | EB4: =IF(IFERROR(VLOOKUP($A4,'entrada-fornecedor-12-meses-7'!$1:$1048576,3 + (COLUMN(B1)-1)*1,FALSE),"")=0,"",IFERROR(VLOOKUP($A4,'entrada-fornecedor-12-meses-7'!$1:$1048576,3 + (COLUMN(B1)-1)*1,FALSE),"")) | EC4: =IF(IFERROR(VLOOKUP($A4,'entrada-fornecedor-12-meses-7'!$1:$1048576,3 + (COLUMN(C1)-1)*1,FALSE),"")=0,"",IFERROR(VLOOKUP($A4,'entrada-fornecedor-12-meses-7'!$1:$1048576,3 + (COLUMN(C1)-1)*1,FALSE),"")) | ED4: =IF(IFERROR(VLOOKUP($A4,'entrada-fornecedor-12-meses-7'!$1:$1048576,3 + (COLUMN(D1)-1)*1,FALSE),"")=0,"",IFERROR(VLOOKUP($A4,'entrada-fornecedor-12-meses-7'!$1:$1048576,3 + (COLUMN(D1)-1)*1,FALSE),"")) | EE4: =IF(IFERROR(VLOOKUP($A4,'entrada-fornecedor-12-meses-7'!$1:$1048576,3 + (COLUMN(E1)-1)*1,FALSE),"")=0,"",IFERROR(VLOOKUP($A4,'entrada-fornecedor-12-meses-7'!$1:$1048576,3 + (COLUMN(E1)-1)*1,FALSE),"")) | EF4: =IF(IFERROR(VLOOKUP($A4,'entrada-fornecedor-12-meses-7'!$1:$1048576,3 + (COLUMN(F1)-1)*1,FALSE),"")=0,"",IFERROR(VLOOKUP($A4,'entrada-fornecedor-12-meses-7'!$1:$1048576,3 + (COLUMN(F1)-1)*1,FALSE),"")) | EG4: =IF(IFERROR(VLOOKUP($A4,'entrada-fornecedor-12-meses-7'!$1:$1048576,3 + (COLUMN(G1)-1)*1,FALSE),"")=0,"",IFERROR(VLOOKUP($A4,'entrada-fornecedor-12-meses-7'!$1:$1048576,3 + (COLUMN(G1)-1)*1,FALSE),"")) | EH4: =IF(IFERROR(VLOOKUP($A4,'entrada-fornecedor-12-meses-7'!$1:$1048576,3 + (COLUMN(H1)-1)*1,FALSE),"")=0,"",IFERROR(VLOOKUP($A4,'entrada-fornecedor-12-meses-7'!$1:$1048576,3 + (COLUMN(H1)-1)*1,FALSE),"")) | ... EL4: =IF(IFERROR(VLOOKUP($A4,'entrada-fornecedor-12-meses-7'!$1:$1048576,3 + (COLUMN(L1)-1)*1,FALSE),"")=0,"",IFERROR(VLOOKUP($A4,'entrada-fornecedor-12-meses-7'!$1:$1048576,3 + (COLUMN(L1)-1)*1,FALSE),"")) | EM4: =IF(COUNT(EA4:EL4)=0,"",SUM(EA4:EL4)) | EO4: =IFERROR(AVERAGEIF('lead-time-compras-7'!B:B,A4,'lead-time-compras-7'!S:S),"") | EP4: =IFERROR( AVERAGEIFS( 'notas-fiscais-entrada-830-7'!H:H, 'notas-fiscais-entrada-830-7'!O:O, A4, 'notas-fiscais-entrada-830-7'!E:E, $B$1 ), "" ) | EQ4: =IFERROR(AVERAGEIF('lead-time-compras-7'!B:B,A4,'lead-time-compras-7'!Q:Q),"") | ER4: =SUMIF('fornecedor-saldo-receber-7'!A:A, A4, 'fornecedor-saldo-receber-7'!L:L) | ES4: =SUMIF('fornecedor-verba-aplicar-7'!A:A, A4, 'fornecedor-verba-aplicar-7'!D:D) | EU4: =SUMIF('ANALISE PRODUTO'!F:F, A4, 'ANALISE PRODUTO'!BN:BN) | EV4: =SUMIF('ANALISE PRODUTO'!F:F, A4, 'ANALISE PRODUTO'!BO:BO) | EW4: =SUMIF('ANALISE PRODUTO'!F:F, A4, 'ANALISE PRODUTO'!BP:BP) | EX4: =SUMIF('ANALISE PRODUTO'!F:F, A4, 'ANALISE PRODUTO'!BQ:BQ) | EY4: =SUMIF('ANALISE PRODUTO'!F:F, A4, 'ANALISE PRODUTO'!BR:BR) | EZ4: =SUMIF('ANALISE PRODUTO'!F:F, A4, 'ANALISE PRODUTO'!BS:BS) | FA4: =SUMIF('ANALISE PRODUTO'!F:F, A4, 'ANALISE PRODUTO'!BT:BT) | FB4: =SUMIF('ANALISE PRODUTO'!F:F, A4, 'ANALISE PRODUTO'!BU:BU) | FC4: =SUMIF('ANALISE PRODUTO'!F:F, A4, 'ANALISE PRODUTO'!BV:BV) | FD4: =SUMIF('ANALISE PRODUTO'!F:F, A4, 'ANALISE PRODUTO'!BW:BW) | FE4: =SUMIF('ANALISE PRODUTO'!F:F, A4, 'ANALISE PRODUTO'!CB:CB) | FF4: =SUMIF('ANALISE PRODUTO'!F:F, A4, 'ANALISE PRODUTO'!CC:CC) | FH4: =IF(IFERROR(VLOOKUP($A4,'VENDA 2023'!$1:$1048576,4 + (COLUMN(A1)-1)*2,FALSE),"")=0,"",IFERROR(VLOOKUP($A4,'VENDA 2023'!$1:$1048576,4 + (COLUMN(A1)-1)*2,FALSE),"")) | FI4: =IF(IFERROR(VLOOKUP($A4,'VENDA 2023'!$1:$1048576,4 + (COLUMN(B1)-1)*2,FALSE),"")=0,"",IFERROR(VLOOKUP($A4,'VENDA 2023'!$1:$1048576,4 + (COLUMN(B1)-1)*2,FALSE),"")) | FJ4: =IF(IFERROR(VLOOKUP($A4,'VENDA 2023'!$1:$1048576,4 + (COLUMN(C1)-1)*2,FALSE),"")=0,"",IFERROR(VLOOKUP($A4,'VENDA 2023'!$1:$1048576,4 + (COLUMN(C1)-1)*2,FALSE),"")) | FK4: =IF(IFERROR(VLOOKUP($A4,'VENDA 2023'!$1:$1048576,4 + (COLUMN(D1)-1)*2,FALSE),"")=0,"",IFERROR(VLOOKUP($A4,'VENDA 2023'!$1:$1048576,4 + (COLUMN(D1)-1)*2,FALSE),"")) | FL4: =IF(IFERROR(VLOOKUP($A4,'VENDA 2023'!$1:$1048576,4 + (COLUMN(E1)-1)*2,FALSE),"")=0,"",IFERROR(VLOOKUP($A4,'VENDA 2023'!$1:$1048576,4 + (COLUMN(E1)-1)*2,FALSE),"")) | FM4: =IF(IFERROR(VLOOKUP($A4,'VENDA 2023'!$1:$1048576,4 + (COLUMN(F1)-1)*2,FALSE),"")=0,"",IFERROR(VLOOKUP($A4,'VENDA 2023'!$1:$1048576,4 + (COLUMN(F1)-1)*2,FALSE),"")) | FN4: =IF(IFERROR(VLOOKUP($A4,'VENDA 2023'!$1:$1048576,4 + (COLUMN(G1)-1)*2,FALSE),"")=0,"",IFERROR(VLOOKUP($A4,'VENDA 2023'!$1:$1048576,4 + (COLUMN(G1)-1)*2,FALSE),"")) | FO4: =IF(IFERROR(VLOOKUP($A4,'VENDA 2023'!$1:$1048576,4 + (COLUMN(H1)-1)*2,FALSE),"")=0,"",IFERROR(VLOOKUP($A4,'VENDA 2023'!$1:$1048576,4 + (COLUMN(H1)-1)*2,FALSE),"")) | ... FS4: =IF(IFERROR(VLOOKUP($A4,'VENDA 2023'!$1:$1048576,4 + (COLUMN(L1)-1)*2,FALSE),"")=0,"",IFERROR(VLOOKUP($A4,'VENDA 2023'!$1:$1048576,4 + (COLUMN(L1)-1)*2,FALSE),"")) | FT4: =IF(COUNT(FH4:FS4)=0,"",SUM(FH4:FS4)) | FU4: =IF(IFERROR(VLOOKUP($A4,'VENDA 2024'!$1:$1048576,4 + (COLUMN(A1)-1)*2,FALSE),"")=0,"",IFERROR(VLOOKUP($A4,'VENDA 2024'!$1:$1048576,4 + (COLUMN(A1)-1)*2,FALSE),"")) | FV4: =IF(IFERROR(VLOOKUP($A4,'VENDA 2024'!$1:$1048576,4 + (COLUMN(B1)-1)*2,FALSE),"")=0,"",IFERROR(VLOOKUP($A4,'VENDA 2024'!$1:$1048576,4 + (COLUMN(B1)-1)*2,FALSE),"")) | FW4: =IF(IFERROR(VLOOKUP($A4,'VENDA 2024'!$1:$1048576,4 + (COLUMN(C1)-1)*2,FALSE),"")=0,"",IFERROR(VLOOKUP($A4,'VENDA 2024'!$1:$1048576,4 + (COLUMN(C1)-1)*2,FALSE),"")) | FX4: =IF(IFERROR(VLOOKUP($A4,'VENDA 2024'!$1:$1048576,4 + (COLUMN(D1)-1)*2,FALSE),"")=0,"",IFERROR(VLOOKUP($A4,'VENDA 2024'!$1:$1048576,4 + (COLUMN(D1)-1)*2,FALSE),"")) | FY4: =IF(IFERROR(VLOOKUP($A4,'VENDA 2024'!$1:$1048576,4 + (COLUMN(E1)-1)*2,FALSE),"")=0,"",IFERROR(VLOOKUP($A4,'VENDA 2024'!$1:$1048576,4 + (COLUMN(E1)-1)*2,FALSE),"")) | FZ4: =IF(IFERROR(VLOOKUP($A4,'VENDA 2024'!$1:$1048576,4 + (COLUMN(F1)-1)*2,FALSE),"")=0,"",IFERROR(VLOOKUP($A4,'VENDA 2024'!$1:$1048576,4 + (COLUMN(F1)-1)*2,FALSE),"")) | GA4: =IF(IFERROR(VLOOKUP($A4,'VENDA 2024'!$1:$1048576,4 + (COLUMN(G1)-1)*2,FALSE),"")=0,"",IFERROR(VLOOKUP($A4,'VENDA 2024'!$1:$1048576,4 + (COLUMN(G1)-1)*2,FALSE),"")) | GB4: =IF(IFERROR(VLOOKUP($A4,'VENDA 2024'!$1:$1048576,4 + (COLUMN(H1)-1)*2,FALSE),"")=0,"",IFERROR(VLOOKUP($A4,'VENDA 2024'!$1:$1048576,4 + (COLUMN(H1)-1)*2,FALSE),"")) | ... GF4: =IF(IFERROR(VLOOKUP($A4,'VENDA 2024'!$1:$1048576,4 + (COLUMN(L1)-1)*2,FALSE),"")=0,"",IFERROR(VLOOKUP($A4,'VENDA 2024'!$1:$1048576,4 + (COLUMN(L1)-1)*2,FALSE),"")) | GG4: =IF(COUNT(FU4:GF4)=0,"",SUM(FU4:GF4)) | GH4: =IF(IFERROR(VLOOKUP($A4,'venda-fornecedor-12-meses-7'!$1:$1048576,5 + (COLUMN(A1)-1)*2,FALSE),"")=0,"",IFERROR(VLOOKUP($A4,'venda-fornecedor-12-meses-7'!$1:$1048576,5 + (COLUMN(A1)-1)*2,FALSE),"")) | GI4: =IF(IFERROR(VLOOKUP($A4,'venda-fornecedor-12-meses-7'!$1:$1048576,5 + (COLUMN(B1)-1)*2,FALSE),"")=0,"",IFERROR(VLOOKUP($A4,'venda-fornecedor-12-meses-7'!$1:$1048576,5 + (COLUMN(B1)-1)*2,FALSE),"")) | GJ4: =IF(IFERROR(VLOOKUP($A4,'venda-fornecedor-12-meses-7'!$1:$1048576,5 + (COLUMN(C1)-1)*2,FALSE),"")=0,"",IFERROR(VLOOKUP($A4,'venda-fornecedor-12-meses-7'!$1:$1048576,5 + (COLUMN(C1)-1)*2,FALSE),"")) | GK4: =IF(IFERROR(VLOOKUP($A4,'venda-fornecedor-12-meses-7'!$1:$1048576,5 + (COLUMN(D1)-1)*2,FALSE),"")=0,"",IFERROR(VLOOKUP($A4,'venda-fornecedor-12-meses-7'!$1:$1048576,5 + (COLUMN(D1)-1)*2,FALSE),"")) | GL4: =IF(IFERROR(VLOOKUP($A4,'venda-fornecedor-12-meses-7'!$1:$1048576,5 + (COLUMN(E1)-1)*2,FALSE),"")=0,"",IFERROR(VLOOKUP($A4,'venda-fornecedor-12-meses-7'!$1:$1048576,5 + (COLUMN(E1)-1)*2,FALSE),"")) | GM4: =IF(IFERROR(VLOOKUP($A4,'venda-fornecedor-12-meses-7'!$1:$1048576,5 + (COLUMN(F1)-1)*2,FALSE),"")=0,"",IFERROR(VLOOKUP($A4,'venda-fornecedor-12-meses-7'!$1:$1048576,5 + (COLUMN(F1)-1)*2,FALSE),"")) | GN4: =IF(IFERROR(VLOOKUP($A4,'venda-fornecedor-12-meses-7'!$1:$1048576,5 + (COLUMN(G1)-1)*2,FALSE),"")=0,"",IFERROR(VLOOKUP($A4,'venda-fornecedor-12-meses-7'!$1:$1048576,5 + (COLUMN(G1)-1)*2,FALSE),"")) | GO4: =IF(IFERROR(VLOOKUP($A4,'venda-fornecedor-12-meses-7'!$1:$1048576,5 + (COLUMN(H1)-1)*2,FALSE),"")=0,"",IFERROR(VLOOKUP($A4,'venda-fornecedor-12-meses-7'!$1:$1048576,5 + (COLUMN(H1)-1)*2,FALSE),"")) | ... GS4: =IF(IFERROR(VLOOKUP($A4,'venda-fornecedor-12-meses-7'!$1:$1048576,5 + (COLUMN(L1)-1)*2,FALSE),"")=0,"",IFERROR(VLOOKUP($A4,'venda-fornecedor-12-meses-7'!$1:$1048576,5 + (COLUMN(L1)-1)*2,FALSE),"")) | GT4: =IF(COUNT(GH4:GS4)=0,"",SUM(GH4:GS4))
A5: 24 | B5: =VLOOKUP(A5,'FORNECEDORES X COMPRADOR'!$A:$D,4,0) | C5: =VLOOKUP(A5,'FORNECEDORES X COMPRADOR'!$A:$E,5,0) | D5: =IFERROR(AVERAGEIF('ANALISE PRODUTO'!F:F,A5,'ANALISE PRODUTO'!BE:BE),"") | E5: =IFERROR(AVERAGEIF('ANALISE PRODUTO'!F:F,A5,'ANALISE PRODUTO'!BF:BF),"") | F5: {=IFERROR( IF( SUMPRODUCT( IFERROR(--('ANALISE PRODUTO'!$F$3:$F$10000=A5),0) * IFERROR(--'ANALISE PRODUTO'!$AJ$3:$AJ$10000,0) )=0, "", SUMPRODUCT( IFERROR(--('ANALISE PRODUTO'!$F$3:$F$10000=A5),0) * IFERROR(--'ANALISE PRODUTO'!$AN$3:$AN$10000,0) ) / SUMPRODUCT( IFERROR(--('ANALISE PRODUTO'!$F$3:$F$10000=A5),0) * IFERROR(--'ANALISE PRODUTO'!$AJ$3:$AJ$10000,0) ) ), "" )} | G5: {=IFERROR( IF( SUMPRODUCT( IFERROR(--('ANALISE PRODUTO'!$F$3:$F$10000=A5),0) * IFERROR(--'ANALISE PRODUTO'!$AJ$3:$AJ$10000,0) )=0, "", SUMPRODUCT( IFERROR(--('ANALISE PRODUTO'!$F$3:$F$10000=A5),0) * IFERROR(--'ANALISE PRODUTO'!$AO$3:$AO$10000,0) ) / SUMPRODUCT( IFERROR(--('ANALISE PRODUTO'!$F$3:$F$10000=A5),0) * IFERROR(--'ANALISE PRODUTO'!$AJ$3:$AJ$10000,0) ) ), "" )} | H5: 60 | I5: 90 | J5: =SUMIF('ANALISE PRODUTO'!F:F, A5, 'ANALISE PRODUTO'!AP:AP) | K5: =SUMIF('ANALISE PRODUTO'!F:F, A5, 'ANALISE PRODUTO'!AN:AN) | L5: =SUMIF('ANALISE PRODUTO'!F:F, A5, 'ANALISE PRODUTO'!BB:BB) | M5: =SUMIF('ANALISE PRODUTO'!F:F, A5, 'ANALISE PRODUTO'!BC:BC) | N5: =SUMIF('ANALISE PRODUTO'!F:F, A5, 'ANALISE PRODUTO'!BD:BD) | O5: =SUMIF('ANALISE PRODUTO'!F:F, A5, 'ANALISE PRODUTO'!BA:BA) | P5: =IF(J5=0, 0, IF(O5/J5=0, 0, O5/J5)) | Q5: =IF(J5=0, 0, IF(L5/J5=0, 0, L5/J5)) | R5: =SUMIF('ANALISE PRODUTO'!F:F, A5, 'ANALISE PRODUTO'!BJ:BJ) | S5: =SUMIF('ANALISE PRODUTO'!F:F, A5, 'ANALISE PRODUTO'!BK:BK) | T5: =SUMIF('ANALISE PRODUTO'!F:F, A5, 'ANALISE PRODUTO'!BL:BL) | U5: =SUMIFS('ANALISE PRODUTO'!BI:BI, 'ANALISE PRODUTO'!F:F, A5) | V5: =IF(C5="DESCONTINUADO", 0, IF(J5=0, 0, IF(U5/J5=0, 0, U5/J5))) | W5: =IF(OR(C5="DESCONTINUADO", J5=0), 0, IFERROR((S5+T5)/J5, 0)) | X5: =COUNTIF('ANALISE PRODUTO'!F:F, A5) | Y5: =COUNTIFS('ANALISE PRODUTO'!F:F, A5, 'ANALISE PRODUTO'!S:S, "S") | Z5: =X5-Y5 | AA5: =IFERROR(IF(COUNTIF('contas-pagas-fornecedor-7'!$C:$C,B5)>1, AVERAGEIF('contas-pagas-fornecedor-7'!$C:$C,B5,'contas-pagas-fornecedor-7'!$I:$I), VLOOKUP(B5,'contas-pagas-fornecedor-7'!$C:$Q,7,FALSE)), "") | AB5: {=IFERROR( INDEX('fornecedor-venda-por-filial-ger'!J:J, MATCH(1, ('fornecedor-venda-por-filial-ger'!A:A=A5) * ('fornecedor-venda-por-filial-ger'!B:B=$B$1), 0) ), "")} | AC5: {=IFERROR( INDEX('fornecedor-venda-por-filial-ger'!O:O, MATCH(1, ('fornecedor-venda-por-filial-ger'!A:A=A5) * ('fornecedor-venda-por-filial-ger'!B:B=$B$1), 0) ), "")} | AD5: =IFERROR(VLOOKUP(A5,'venda-fornecedor-12-meses-7'!A:AC,3,0),"") | AE5: {=IFERROR( INDEX('fornecedor-venda-por-filial-ger'!N:N, MATCH(1, ('fornecedor-venda-por-filial-ger'!A:A=A5) * ('fornecedor-venda-por-filial-ger'!B:B=$B$1), 0) ), "")} | AF5: =IF(J5<=0,"100,00%",IFERROR(AD5/AE5,1)) | AG5: {=IFERROR( INDEX('fornecedor-venda-por-filial-ger'!L:L, MATCH(1, ('fornecedor-venda-por-filial-ger'!A:A=A5)* ('fornecedor-venda-por-filial-ger'!B:B=$B$1), 0) )/100, "")} | AH5: {=IFERROR( INDEX('fornecedor-venda-por-filial-ger'!S:S, MATCH(1, ('fornecedor-venda-por-filial-ger'!A:A=A5) * ('fornecedor-venda-por-filial-ger'!B:B=$B$1), 0) )/100, "")} | AI5: =IFERROR(IF(OR(AH5="",AG5=""),"",IF(J5=0,0,AH5-AG5)),"") | AJ5: {=IF(MAX(IF('ANALISE PRODUTO'!F:F=A5,'ANALISE PRODUTO'!AD:AD))=0,"SEM ENTRADA",MAX(IF('ANALISE PRODUTO'!F:F=A5,'ANALISE PRODUTO'!AD:AD)))} | AL5: =IF(IFERROR(VLOOKUP($A5,'VENDA 2023'!$1:$1048576,3 + (COLUMN(A2)-1)*2,FALSE),"")=0,"",IFERROR(VLOOKUP($A5,'VENDA 2023'!$1:$1048576,3 + (COLUMN(A2)-1)*2,FALSE),"")) | AM5: =IF(IFERROR(VLOOKUP($A5,'VENDA 2023'!$1:$1048576,3 + (COLUMN(B2)-1)*2,FALSE),"")=0,"",IFERROR(VLOOKUP($A5,'VENDA 2023'!$1:$1048576,3 + (COLUMN(B2)-1)*2,FALSE),"")) | AN5: =IF(IFERROR(VLOOKUP($A5,'VENDA 2023'!$1:$1048576,3 + (COLUMN(C2)-1)*2,FALSE),"")=0,"",IFERROR(VLOOKUP($A5,'VENDA 2023'!$1:$1048576,3 + (COLUMN(C2)-1)*2,FALSE),"")) | AO5: =IF(IFERROR(VLOOKUP($A5,'VENDA 2023'!$1:$1048576,3 + (COLUMN(D2)-1)*2,FALSE),"")=0,"",IFERROR(VLOOKUP($A5,'VENDA 2023'!$1:$1048576,3 + (COLUMN(D2)-1)*2,FALSE),"")) | AP5: =IF(IFERROR(VLOOKUP($A5,'VENDA 2023'!$1:$1048576,3 + (COLUMN(E2)-1)*2,FALSE),"")=0,"",IFERROR(VLOOKUP($A5,'VENDA 2023'!$1:$1048576,3 + (COLUMN(E2)-1)*2,FALSE),"")) | AQ5: =IF(IFERROR(VLOOKUP($A5,'VENDA 2023'!$1:$1048576,3 + (COLUMN(F2)-1)*2,FALSE),"")=0,"",IFERROR(VLOOKUP($A5,'VENDA 2023'!$1:$1048576,3 + (COLUMN(F2)-1)*2,FALSE),"")) | AR5: =IF(IFERROR(VLOOKUP($A5,'VENDA 2023'!$1:$1048576,3 + (COLUMN(G2)-1)*2,FALSE),"")=0,"",IFERROR(VLOOKUP($A5,'VENDA 2023'!$1:$1048576,3 + (COLUMN(G2)-1)*2,FALSE),"")) | AS5: =IF(IFERROR(VLOOKUP($A5,'VENDA 2023'!$1:$1048576,3 + (COLUMN(H2)-1)*2,FALSE),"")=0,"",IFERROR(VLOOKUP($A5,'VENDA 2023'!$1:$1048576,3 + (COLUMN(H2)-1)*2,FALSE),"")) | ... AW5: =IF(IFERROR(VLOOKUP($A5,'VENDA 2023'!$1:$1048576,3 + (COLUMN(L2)-1)*2,FALSE),"")=0,"",IFERROR(VLOOKUP($A5,'VENDA 2023'!$1:$1048576,3 + (COLUMN(L2)-1)*2,FALSE),"")) | AX5: =IF(COUNT(AL5:AW5)=0,"",SUM(AL5:AW5)) | AY5: =IF(IFERROR(VLOOKUP($A5,'VENDA 2024'!$1:$1048576,3 + (COLUMN(A2)-1)*2,FALSE),"")=0,"",IFERROR(VLOOKUP($A5,'VENDA 2024'!$1:$1048576,3 + (COLUMN(A2)-1)*2,FALSE),"")) | AZ5: =IF(IFERROR(VLOOKUP($A5,'VENDA 2024'!$1:$1048576,3 + (COLUMN(B2)-1)*2,FALSE),"")=0,"",IFERROR(VLOOKUP($A5,'VENDA 2024'!$1:$1048576,3 + (COLUMN(B2)-1)*2,FALSE),"")) | BA5: =IF(IFERROR(VLOOKUP($A5,'VENDA 2024'!$1:$1048576,3 + (COLUMN(C2)-1)*2,FALSE),"")=0,"",IFERROR(VLOOKUP($A5,'VENDA 2024'!$1:$1048576,3 + (COLUMN(C2)-1)*2,FALSE),"")) | BB5: =IF(IFERROR(VLOOKUP($A5,'VENDA 2024'!$1:$1048576,3 + (COLUMN(D2)-1)*2,FALSE),"")=0,"",IFERROR(VLOOKUP($A5,'VENDA 2024'!$1:$1048576,3 + (COLUMN(D2)-1)*2,FALSE),"")) | BC5: =IF(IFERROR(VLOOKUP($A5,'VENDA 2024'!$1:$1048576,3 + (COLUMN(E2)-1)*2,FALSE),"")=0,"",IFERROR(VLOOKUP($A5,'VENDA 2024'!$1:$1048576,3 + (COLUMN(E2)-1)*2,FALSE),"")) | BD5: =IF(IFERROR(VLOOKUP($A5,'VENDA 2024'!$1:$1048576,3 + (COLUMN(F2)-1)*2,FALSE),"")=0,"",IFERROR(VLOOKUP($A5,'VENDA 2024'!$1:$1048576,3 + (COLUMN(F2)-1)*2,FALSE),"")) | BE5: =IF(IFERROR(VLOOKUP($A5,'VENDA 2024'!$1:$1048576,3 + (COLUMN(G2)-1)*2,FALSE),"")=0,"",IFERROR(VLOOKUP($A5,'VENDA 2024'!$1:$1048576,3 + (COLUMN(G2)-1)*2,FALSE),"")) | BF5: =IF(IFERROR(VLOOKUP($A5,'VENDA 2024'!$1:$1048576,3 + (COLUMN(H2)-1)*2,FALSE),"")=0,"",IFERROR(VLOOKUP($A5,'VENDA 2024'!$1:$1048576,3 + (COLUMN(H2)-1)*2,FALSE),"")) | ... BJ5: =IF(IFERROR(VLOOKUP($A5,'VENDA 2024'!$1:$1048576,3 + (COLUMN(L2)-1)*2,FALSE),"")=0,"",IFERROR(VLOOKUP($A5,'VENDA 2024'!$1:$1048576,3 + (COLUMN(L2)-1)*2,FALSE),"")) | BK5: =IF(COUNT(AY5:BJ5)=0,"",SUM(AY5:BJ5)) | BL5: =IF(IFERROR(VLOOKUP($A5,'VENDA 2025'!$1:$1048576,3 + (COLUMN(A2)-1)*2,FALSE),"")=0,"",IFERROR(VLOOKUP($A5,'VENDA 2025'!$1:$1048576,3 + (COLUMN(A2)-1)*2,FALSE),"")) | BM5: =IF(IFERROR(VLOOKUP($A5,'VENDA 2025'!$1:$1048576,3 + (COLUMN(B2)-1)*2,FALSE),"")=0,"",IFERROR(VLOOKUP($A5,'VENDA 2025'!$1:$1048576,3 + (COLUMN(B2)-1)*2,FALSE),"")) | BN5: =IF(IFERROR(VLOOKUP($A5,'VENDA 2025'!$1:$1048576,3 + (COLUMN(C2)-1)*2,FALSE),"")=0,"",IFERROR(VLOOKUP($A5,'VENDA 2025'!$1:$1048576,3 + (COLUMN(C2)-1)*2,FALSE),"")) | BO5: =IF(IFERROR(VLOOKUP($A5,'VENDA 2025'!$1:$1048576,3 + (COLUMN(D2)-1)*2,FALSE),"")=0,"",IFERROR(VLOOKUP($A5,'VENDA 2025'!$1:$1048576,3 + (COLUMN(D2)-1)*2,FALSE),"")) | BP5: =IF(IFERROR(VLOOKUP($A5,'VENDA 2025'!$1:$1048576,3 + (COLUMN(E2)-1)*2,FALSE),"")=0,"",IFERROR(VLOOKUP($A5,'VENDA 2025'!$1:$1048576,3 + (COLUMN(E2)-1)*2,FALSE),"")) | BQ5: =IF(IFERROR(VLOOKUP($A5,'VENDA 2025'!$1:$1048576,3 + (COLUMN(F2)-1)*2,FALSE),"")=0,"",IFERROR(VLOOKUP($A5,'VENDA 2025'!$1:$1048576,3 + (COLUMN(F2)-1)*2,FALSE),"")) | BR5: =IF(IFERROR(VLOOKUP($A5,'VENDA 2025'!$1:$1048576,3 + (COLUMN(G2)-1)*2,FALSE),"")=0,"",IFERROR(VLOOKUP($A5,'VENDA 2025'!$1:$1048576,3 + (COLUMN(G2)-1)*2,FALSE),"")) | BS5: =IF(IFERROR(VLOOKUP($A5,'VENDA 2025'!$1:$1048576,3 + (COLUMN(H2)-1)*2,FALSE),"")=0,"",IFERROR(VLOOKUP($A5,'VENDA 2025'!$1:$1048576,3 + (COLUMN(H2)-1)*2,FALSE),"")) | ... BW5: =IF(IFERROR(VLOOKUP($A5,'VENDA 2025'!$1:$1048576,3 + (COLUMN(L2)-1)*2,FALSE),"")=0,"",IFERROR(VLOOKUP($A5,'VENDA 2025'!$1:$1048576,3 + (COLUMN(L2)-1)*2,FALSE),"")) | BX5: =IF(COUNT(BL5:BW5)=0,"",SUM(BL5:BW5)) | BY5: =IF(IFERROR(VLOOKUP($A5,'venda-fornecedor-12-meses-7'!$1:$1048576,4 + (COLUMN(A2)-1)*2,FALSE),"")=0,"",IFERROR(VLOOKUP($A5,'venda-fornecedor-12-meses-7'!$1:$1048576,4 + (COLUMN(A2)-1)*2,FALSE),"")) | BZ5: =IF(IFERROR(VLOOKUP($A5,'venda-fornecedor-12-meses-7'!$1:$1048576,4 + (COLUMN(B2)-1)*2,FALSE),"")=0,"",IFERROR(VLOOKUP($A5,'venda-fornecedor-12-meses-7'!$1:$1048576,4 + (COLUMN(B2)-1)*2,FALSE),"")) | CA5: =IF(IFERROR(VLOOKUP($A5,'venda-fornecedor-12-meses-7'!$1:$1048576,4 + (COLUMN(C2)-1)*2,FALSE),"")=0,"",IFERROR(VLOOKUP($A5,'venda-fornecedor-12-meses-7'!$1:$1048576,4 + (COLUMN(C2)-1)*2,FALSE),"")) | CB5: =IF(IFERROR(VLOOKUP($A5,'venda-fornecedor-12-meses-7'!$1:$1048576,4 + (COLUMN(D2)-1)*2,FALSE),"")=0,"",IFERROR(VLOOKUP($A5,'venda-fornecedor-12-meses-7'!$1:$1048576,4 + (COLUMN(D2)-1)*2,FALSE),"")) | CC5: =IF(IFERROR(VLOOKUP($A5,'venda-fornecedor-12-meses-7'!$1:$1048576,4 + (COLUMN(E2)-1)*2,FALSE),"")=0,"",IFERROR(VLOOKUP($A5,'venda-fornecedor-12-meses-7'!$1:$1048576,4 + (COLUMN(E2)-1)*2,FALSE),"")) | CD5: =IF(IFERROR(VLOOKUP($A5,'venda-fornecedor-12-meses-7'!$1:$1048576,4 + (COLUMN(F2)-1)*2,FALSE),"")=0,"",IFERROR(VLOOKUP($A5,'venda-fornecedor-12-meses-7'!$1:$1048576,4 + (COLUMN(F2)-1)*2,FALSE),"")) | CE5: =IF(IFERROR(VLOOKUP($A5,'venda-fornecedor-12-meses-7'!$1:$1048576,4 + (COLUMN(G2)-1)*2,FALSE),"")=0,"",IFERROR(VLOOKUP($A5,'venda-fornecedor-12-meses-7'!$1:$1048576,4 + (COLUMN(G2)-1)*2,FALSE),"")) | CF5: =IF(IFERROR(VLOOKUP($A5,'venda-fornecedor-12-meses-7'!$1:$1048576,4 + (COLUMN(H2)-1)*2,FALSE),"")=0,"",IFERROR(VLOOKUP($A5,'venda-fornecedor-12-meses-7'!$1:$1048576,4 + (COLUMN(H2)-1)*2,FALSE),"")) | ... CJ5: =IF(IFERROR(VLOOKUP($A5,'venda-fornecedor-12-meses-7'!$1:$1048576,4 + (COLUMN(L2)-1)*2,FALSE),"")=0,"",IFERROR(VLOOKUP($A5,'venda-fornecedor-12-meses-7'!$1:$1048576,4 + (COLUMN(L2)-1)*2,FALSE),"")) | CK5: =IF(COUNT(BY5:CJ5)=0,"",SUM(BY5:CJ5)) | CL5: =IF(COUNT(BY5:CJ5)=0,"",AVERAGE(BY5:CJ5)) | CN5: =IF(IFERROR(VLOOKUP($A5,'ENTRADA 2023'!$1:$1048576,3 + (COLUMN(A2)-1)*1,FALSE),"")=0,"",IFERROR(VLOOKUP($A5,'ENTRADA 2023'!$1:$1048576,3 + (COLUMN(A2)-1)*1,FALSE),"")) | CO5: =IF(IFERROR(VLOOKUP($A5,'ENTRADA 2023'!$1:$1048576,3 + (COLUMN(B2)-1)*1,FALSE),"")=0,"",IFERROR(VLOOKUP($A5,'ENTRADA 2023'!$1:$1048576,3 + (COLUMN(B2)-1)*1,FALSE),"")) | CP5: =IF(IFERROR(VLOOKUP($A5,'ENTRADA 2023'!$1:$1048576,3 + (COLUMN(C2)-1)*1,FALSE),"")=0,"",IFERROR(VLOOKUP($A5,'ENTRADA 2023'!$1:$1048576,3 + (COLUMN(C2)-1)*1,FALSE),"")) | CQ5: =IF(IFERROR(VLOOKUP($A5,'ENTRADA 2023'!$1:$1048576,3 + (COLUMN(D2)-1)*1,FALSE),"")=0,"",IFERROR(VLOOKUP($A5,'ENTRADA 2023'!$1:$1048576,3 + (COLUMN(D2)-1)*1,FALSE),"")) | CR5: =IF(IFERROR(VLOOKUP($A5,'ENTRADA 2023'!$1:$1048576,3 + (COLUMN(E2)-1)*1,FALSE),"")=0,"",IFERROR(VLOOKUP($A5,'ENTRADA 2023'!$1:$1048576,3 + (COLUMN(E2)-1)*1,FALSE),"")) | CS5: =IF(IFERROR(VLOOKUP($A5,'ENTRADA 2023'!$1:$1048576,3 + (COLUMN(F2)-1)*1,FALSE),"")=0,"",IFERROR(VLOOKUP($A5,'ENTRADA 2023'!$1:$1048576,3 + (COLUMN(F2)-1)*1,FALSE),"")) | CT5: =IF(IFERROR(VLOOKUP($A5,'ENTRADA 2023'!$1:$1048576,3 + (COLUMN(G2)-1)*1,FALSE),"")=0,"",IFERROR(VLOOKUP($A5,'ENTRADA 2023'!$1:$1048576,3 + (COLUMN(G2)-1)*1,FALSE),"")) | CU5: =IF(IFERROR(VLOOKUP($A5,'ENTRADA 2023'!$1:$1048576,3 + (COLUMN(H2)-1)*1,FALSE),"")=0,"",IFERROR(VLOOKUP($A5,'ENTRADA 2023'!$1:$1048576,3 + (COLUMN(H2)-1)*1,FALSE),"")) | ... CY5: =IF(IFERROR(VLOOKUP($A5,'ENTRADA 2023'!$1:$1048576,3 + (COLUMN(L2)-1)*1,FALSE),"")=0,"",IFERROR(VLOOKUP($A5,'ENTRADA 2023'!$1:$1048576,3 + (COLUMN(L2)-1)*1,FALSE),"")) | CZ5: =IF(COUNT(CN5:CY5)=0,"",SUM(CN5:CY5)) | DA5: =IF(IFERROR(VLOOKUP($A5,'ENTRADA 2024'!$1:$1048576,3 + (COLUMN(A2)-1)*1,FALSE),"")=0,"",IFERROR(VLOOKUP($A5,'ENTRADA 2024'!$1:$1048576,3 + (COLUMN(A2)-1)*1,FALSE),"")) | DB5: =IF(IFERROR(VLOOKUP($A5,'ENTRADA 2024'!$1:$1048576,3 + (COLUMN(B2)-1)*1,FALSE),"")=0,"",IFERROR(VLOOKUP($A5,'ENTRADA 2024'!$1:$1048576,3 + (COLUMN(B2)-1)*1,FALSE),"")) | DC5: =IF(IFERROR(VLOOKUP($A5,'ENTRADA 2024'!$1:$1048576,3 + (COLUMN(C2)-1)*1,FALSE),"")=0,"",IFERROR(VLOOKUP($A5,'ENTRADA 2024'!$1:$1048576,3 + (COLUMN(C2)-1)*1,FALSE),"")) | DD5: =IF(IFERROR(VLOOKUP($A5,'ENTRADA 2024'!$1:$1048576,3 + (COLUMN(D2)-1)*1,FALSE),"")=0,"",IFERROR(VLOOKUP($A5,'ENTRADA 2024'!$1:$1048576,3 + (COLUMN(D2)-1)*1,FALSE),"")) | DE5: =IF(IFERROR(VLOOKUP($A5,'ENTRADA 2024'!$1:$1048576,3 + (COLUMN(E2)-1)*1,FALSE),"")=0,"",IFERROR(VLOOKUP($A5,'ENTRADA 2024'!$1:$1048576,3 + (COLUMN(E2)-1)*1,FALSE),"")) | DF5: =IF(IFERROR(VLOOKUP($A5,'ENTRADA 2024'!$1:$1048576,3 + (COLUMN(F2)-1)*1,FALSE),"")=0,"",IFERROR(VLOOKUP($A5,'ENTRADA 2024'!$1:$1048576,3 + (COLUMN(F2)-1)*1,FALSE),"")) | DG5: =IF(IFERROR(VLOOKUP($A5,'ENTRADA 2024'!$1:$1048576,3 + (COLUMN(G2)-1)*1,FALSE),"")=0,"",IFERROR(VLOOKUP($A5,'ENTRADA 2024'!$1:$1048576,3 + (COLUMN(G2)-1)*1,FALSE),"")) | DH5: =IF(IFERROR(VLOOKUP($A5,'ENTRADA 2024'!$1:$1048576,3 + (COLUMN(H2)-1)*1,FALSE),"")=0,"",IFERROR(VLOOKUP($A5,'ENTRADA 2024'!$1:$1048576,3 + (COLUMN(H2)-1)*1,FALSE),"")) | ... DL5: =IF(IFERROR(VLOOKUP($A5,'ENTRADA 2024'!$1:$1048576,3 + (COLUMN(L2)-1)*1,FALSE),"")=0,"",IFERROR(VLOOKUP($A5,'ENTRADA 2024'!$1:$1048576,3 + (COLUMN(L2)-1)*1,FALSE),"")) | DM5: =IF(COUNT(DA5:DL5)=0,"",SUM(DA5:DL5)) | DN5: =IF(IFERROR(VLOOKUP($A5,'ENTRADA 2025'!$1:$1048576,3 + (COLUMN(A2)-1)*1,FALSE),"")=0,"",IFERROR(VLOOKUP($A5,'ENTRADA 2025'!$1:$1048576,3 + (COLUMN(A2)-1)*1,FALSE),"")) | DO5: =IF(IFERROR(VLOOKUP($A5,'ENTRADA 2025'!$1:$1048576,3 + (COLUMN(B2)-1)*1,FALSE),"")=0,"",IFERROR(VLOOKUP($A5,'ENTRADA 2025'!$1:$1048576,3 + (COLUMN(B2)-1)*1,FALSE),"")) | DP5: =IF(IFERROR(VLOOKUP($A5,'ENTRADA 2025'!$1:$1048576,3 + (COLUMN(C2)-1)*1,FALSE),"")=0,"",IFERROR(VLOOKUP($A5,'ENTRADA 2025'!$1:$1048576,3 + (COLUMN(C2)-1)*1,FALSE),"")) | DQ5: =IF(IFERROR(VLOOKUP($A5,'ENTRADA 2025'!$1:$1048576,3 + (COLUMN(D2)-1)*1,FALSE),"")=0,"",IFERROR(VLOOKUP($A5,'ENTRADA 2025'!$1:$1048576,3 + (COLUMN(D2)-1)*1,FALSE),"")) | DR5: =IF(IFERROR(VLOOKUP($A5,'ENTRADA 2025'!$1:$1048576,3 + (COLUMN(E2)-1)*1,FALSE),"")=0,"",IFERROR(VLOOKUP($A5,'ENTRADA 2025'!$1:$1048576,3 + (COLUMN(E2)-1)*1,FALSE),"")) | DS5: =IF(IFERROR(VLOOKUP($A5,'ENTRADA 2025'!$1:$1048576,3 + (COLUMN(F2)-1)*1,FALSE),"")=0,"",IFERROR(VLOOKUP($A5,'ENTRADA 2025'!$1:$1048576,3 + (COLUMN(F2)-1)*1,FALSE),"")) | DT5: =IF(IFERROR(VLOOKUP($A5,'ENTRADA 2025'!$1:$1048576,3 + (COLUMN(G2)-1)*1,FALSE),"")=0,"",IFERROR(VLOOKUP($A5,'ENTRADA 2025'!$1:$1048576,3 + (COLUMN(G2)-1)*1,FALSE),"")) | DU5: =IF(IFERROR(VLOOKUP($A5,'ENTRADA 2025'!$1:$1048576,3 + (COLUMN(H2)-1)*1,FALSE),"")=0,"",IFERROR(VLOOKUP($A5,'ENTRADA 2025'!$1:$1048576,3 + (COLUMN(H2)-1)*1,FALSE),"")) | ... DY5: =IF(IFERROR(VLOOKUP($A5,'ENTRADA 2025'!$1:$1048576,3 + (COLUMN(L2)-1)*1,FALSE),"")=0,"",IFERROR(VLOOKUP($A5,'ENTRADA 2025'!$1:$1048576,3 + (COLUMN(L2)-1)*1,FALSE),"")) | DZ5: =IF(COUNT(DN5:DY5)=0,"",SUM(DN5:DY5)) | EA5: =IF(IFERROR(VLOOKUP($A5,'entrada-fornecedor-12-meses-7'!$1:$1048576,3 + (COLUMN(A2)-1)*1,FALSE),"")=0,"",IFERROR(VLOOKUP($A5,'entrada-fornecedor-12-meses-7'!$1:$1048576,3 + (COLUMN(A2)-1)*1,FALSE),"")) | EB5: =IF(IFERROR(VLOOKUP($A5,'entrada-fornecedor-12-meses-7'!$1:$1048576,3 + (COLUMN(B2)-1)*1,FALSE),"")=0,"",IFERROR(VLOOKUP($A5,'entrada-fornecedor-12-meses-7'!$1:$1048576,3 + (COLUMN(B2)-1)*1,FALSE),"")) | EC5: =IF(IFERROR(VLOOKUP($A5,'entrada-fornecedor-12-meses-7'!$1:$1048576,3 + (COLUMN(C2)-1)*1,FALSE),"")=0,"",IFERROR(VLOOKUP($A5,'entrada-fornecedor-12-meses-7'!$1:$1048576,3 + (COLUMN(C2)-1)*1,FALSE),"")) | ED5: =IF(IFERROR(VLOOKUP($A5,'entrada-fornecedor-12-meses-7'!$1:$1048576,3 + (COLUMN(D2)-1)*1,FALSE),"")=0,"",IFERROR(VLOOKUP($A5,'entrada-fornecedor-12-meses-7'!$1:$1048576,3 + (COLUMN(D2)-1)*1,FALSE),"")) | EE5: =IF(IFERROR(VLOOKUP($A5,'entrada-fornecedor-12-meses-7'!$1:$1048576,3 + (COLUMN(E2)-1)*1,FALSE),"")=0,"",IFERROR(VLOOKUP($A5,'entrada-fornecedor-12-meses-7'!$1:$1048576,3 + (COLUMN(E2)-1)*1,FALSE),"")) | EF5: =IF(IFERROR(VLOOKUP($A5,'entrada-fornecedor-12-meses-7'!$1:$1048576,3 + (COLUMN(F2)-1)*1,FALSE),"")=0,"",IFERROR(VLOOKUP($A5,'entrada-fornecedor-12-meses-7'!$1:$1048576,3 + (COLUMN(F2)-1)*1,FALSE),"")) | EG5: =IF(IFERROR(VLOOKUP($A5,'entrada-fornecedor-12-meses-7'!$1:$1048576,3 + (COLUMN(G2)-1)*1,FALSE),"")=0,"",IFERROR(VLOOKUP($A5,'entrada-fornecedor-12-meses-7'!$1:$1048576,3 + (COLUMN(G2)-1)*1,FALSE),"")) | EH5: =IF(IFERROR(VLOOKUP($A5,'entrada-fornecedor-12-meses-7'!$1:$1048576,3 + (COLUMN(H2)-1)*1,FALSE),"")=0,"",IFERROR(VLOOKUP($A5,'entrada-fornecedor-12-meses-7'!$1:$1048576,3 + (COLUMN(H2)-1)*1,FALSE),"")) | ... EL5: =IF(IFERROR(VLOOKUP($A5,'entrada-fornecedor-12-meses-7'!$1:$1048576,3 + (COLUMN(L2)-1)*1,FALSE),"")=0,"",IFERROR(VLOOKUP($A5,'entrada-fornecedor-12-meses-7'!$1:$1048576,3 + (COLUMN(L2)-1)*1,FALSE),"")) | EM5: =IF(COUNT(EA5:EL5)=0,"",SUM(EA5:EL5)) | EO5: =IFERROR(AVERAGEIF('lead-time-compras-7'!B:B,A5,'lead-time-compras-7'!S:S),"") | EP5: =IFERROR( AVERAGEIFS( 'notas-fiscais-entrada-830-7'!H:H, 'notas-fiscais-entrada-830-7'!O:O, A5, 'notas-fiscais-entrada-830-7'!E:E, $B$1 ), "" ) | EQ5: =IFERROR(AVERAGEIF('lead-time-compras-7'!B:B,A5,'lead-time-compras-7'!Q:Q),"") | ER5: =SUMIF('fornecedor-saldo-receber-7'!A:A, A5, 'fornecedor-saldo-receber-7'!L:L) | ES5: =SUMIF('fornecedor-verba-aplicar-7'!A:A, A5, 'fornecedor-verba-aplicar-7'!D:D) | EU5: =SUMIF('ANALISE PRODUTO'!F:F, A5, 'ANALISE PRODUTO'!BN:BN) | EV5: =SUMIF('ANALISE PRODUTO'!F:F, A5, 'ANALISE PRODUTO'!BO:BO) | EW5: =SUMIF('ANALISE PRODUTO'!F:F, A5, 'ANALISE PRODUTO'!BP:BP) | EX5: =SUMIF('ANALISE PRODUTO'!F:F, A5, 'ANALISE PRODUTO'!BQ:BQ) | EY5: =SUMIF('ANALISE PRODUTO'!F:F, A5, 'ANALISE PRODUTO'!BR:BR) | EZ5: =SUMIF('ANALISE PRODUTO'!F:F, A5, 'ANALISE PRODUTO'!BS:BS) | FA5: =SUMIF('ANALISE PRODUTO'!F:F, A5, 'ANALISE PRODUTO'!BT:BT) | FB5: =SUMIF('ANALISE PRODUTO'!F:F, A5, 'ANALISE PRODUTO'!BU:BU) | FC5: =SUMIF('ANALISE PRODUTO'!F:F, A5, 'ANALISE PRODUTO'!BV:BV) | FD5: =SUMIF('ANALISE PRODUTO'!F:F, A5, 'ANALISE PRODUTO'!BW:BW) | FE5: =SUMIF('ANALISE PRODUTO'!F:F, A5, 'ANALISE PRODUTO'!CB:CB) | FF5: =SUMIF('ANALISE PRODUTO'!F:F, A5, 'ANALISE PRODUTO'!CC:CC) | FH5: =IF(IFERROR(VLOOKUP($A5,'VENDA 2023'!$1:$1048576,4 + (COLUMN(A2)-1)*2,FALSE),"")=0,"",IFERROR(VLOOKUP($A5,'VENDA 2023'!$1:$1048576,4 + (COLUMN(A2)-1)*2,FALSE),"")) | FI5: =IF(IFERROR(VLOOKUP($A5,'VENDA 2023'!$1:$1048576,4 + (COLUMN(B2)-1)*2,FALSE),"")=0,"",IFERROR(VLOOKUP($A5,'VENDA 2023'!$1:$1048576,4 + (COLUMN(B2)-1)*2,FALSE),"")) | FJ5: =IF(IFERROR(VLOOKUP($A5,'VENDA 2023'!$1:$1048576,4 + (COLUMN(C2)-1)*2,FALSE),"")=0,"",IFERROR(VLOOKUP($A5,'VENDA 2023'!$1:$1048576,4 + (COLUMN(C2)-1)*2,FALSE),"")) | FK5: =IF(IFERROR(VLOOKUP($A5,'VENDA 2023'!$1:$1048576,4 + (COLUMN(D2)-1)*2,FALSE),"")=0,"",IFERROR(VLOOKUP($A5,'VENDA 2023'!$1:$1048576,4 + (COLUMN(D2)-1)*2,FALSE),"")) | FL5: =IF(IFERROR(VLOOKUP($A5,'VENDA 2023'!$1:$1048576,4 + (COLUMN(E2)-1)*2,FALSE),"")=0,"",IFERROR(VLOOKUP($A5,'VENDA 2023'!$1:$1048576,4 + (COLUMN(E2)-1)*2,FALSE),"")) | FM5: =IF(IFERROR(VLOOKUP($A5,'VENDA 2023'!$1:$1048576,4 + (COLUMN(F2)-1)*2,FALSE),"")=0,"",IFERROR(VLOOKUP($A5,'VENDA 2023'!$1:$1048576,4 + (COLUMN(F2)-1)*2,FALSE),"")) | FN5: =IF(IFERROR(VLOOKUP($A5,'VENDA 2023'!$1:$1048576,4 + (COLUMN(G2)-1)*2,FALSE),"")=0,"",IFERROR(VLOOKUP($A5,'VENDA 2023'!$1:$1048576,4 + (COLUMN(G2)-1)*2,FALSE),"")) | FO5: =IF(IFERROR(VLOOKUP($A5,'VENDA 2023'!$1:$1048576,4 + (COLUMN(H2)-1)*2,FALSE),"")=0,"",IFERROR(VLOOKUP($A5,'VENDA 2023'!$1:$1048576,4 + (COLUMN(H2)-1)*2,FALSE),"")) | ... FS5: =IF(IFERROR(VLOOKUP($A5,'VENDA 2023'!$1:$1048576,4 + (COLUMN(L2)-1)*2,FALSE),"")=0,"",IFERROR(VLOOKUP($A5,'VENDA 2023'!$1:$1048576,4 + (COLUMN(L2)-1)*2,FALSE),"")) | FT5: =IF(COUNT(FH5:FS5)=0,"",SUM(FH5:FS5)) | FU5: =IF(IFERROR(VLOOKUP($A5,'VENDA 2024'!$1:$1048576,4 + (COLUMN(A2)-1)*2,FALSE),"")=0,"",IFERROR(VLOOKUP($A5,'VENDA 2024'!$1:$1048576,4 + (COLUMN(A2)-1)*2,FALSE),"")) | FV5: =IF(IFERROR(VLOOKUP($A5,'VENDA 2024'!$1:$1048576,4 + (COLUMN(B2)-1)*2,FALSE),"")=0,"",IFERROR(VLOOKUP($A5,'VENDA 2024'!$1:$1048576,4 + (COLUMN(B2)-1)*2,FALSE),"")) | FW5: =IF(IFERROR(VLOOKUP($A5,'VENDA 2024'!$1:$1048576,4 + (COLUMN(C2)-1)*2,FALSE),"")=0,"",IFERROR(VLOOKUP($A5,'VENDA 2024'!$1:$1048576,4 + (COLUMN(C2)-1)*2,FALSE),"")) | FX5: =IF(IFERROR(VLOOKUP($A5,'VENDA 2024'!$1:$1048576,4 + (COLUMN(D2)-1)*2,FALSE),"")=0,"",IFERROR(VLOOKUP($A5,'VENDA 2024'!$1:$1048576,4 + (COLUMN(D2)-1)*2,FALSE),"")) | FY5: =IF(IFERROR(VLOOKUP($A5,'VENDA 2024'!$1:$1048576,4 + (COLUMN(E2)-1)*2,FALSE),"")=0,"",IFERROR(VLOOKUP($A5,'VENDA 2024'!$1:$1048576,4 + (COLUMN(E2)-1)*2,FALSE),"")) | FZ5: =IF(IFERROR(VLOOKUP($A5,'VENDA 2024'!$1:$1048576,4 + (COLUMN(F2)-1)*2,FALSE),"")=0,"",IFERROR(VLOOKUP($A5,'VENDA 2024'!$1:$1048576,4 + (COLUMN(F2)-1)*2,FALSE),"")) | GA5: =IF(IFERROR(VLOOKUP($A5,'VENDA 2024'!$1:$1048576,4 + (COLUMN(G2)-1)*2,FALSE),"")=0,"",IFERROR(VLOOKUP($A5,'VENDA 2024'!$1:$1048576,4 + (COLUMN(G2)-1)*2,FALSE),"")) | GB5: =IF(IFERROR(VLOOKUP($A5,'VENDA 2024'!$1:$1048576,4 + (COLUMN(H2)-1)*2,FALSE),"")=0,"",IFERROR(VLOOKUP($A5,'VENDA 2024'!$1:$1048576,4 + (COLUMN(H2)-1)*2,FALSE),"")) | ... GF5: =IF(IFERROR(VLOOKUP($A5,'VENDA 2024'!$1:$1048576,4 + (COLUMN(L2)-1)*2,FALSE),"")=0,"",IFERROR(VLOOKUP($A5,'VENDA 2024'!$1:$1048576,4 + (COLUMN(L2)-1)*2,FALSE),"")) | GG5: =IF(COUNT(FU5:GF5)=0,"",SUM(FU5:GF5)) | GH5: =IF(IFERROR(VLOOKUP($A5,'venda-fornecedor-12-meses-7'!$1:$1048576,5 + (COLUMN(A2)-1)*2,FALSE),"")=0,"",IFERROR(VLOOKUP($A5,'venda-fornecedor-12-meses-7'!$1:$1048576,5 + (COLUMN(A2)-1)*2,FALSE),"")) | GI5: =IF(IFERROR(VLOOKUP($A5,'venda-fornecedor-12-meses-7'!$1:$1048576,5 + (COLUMN(B2)-1)*2,FALSE),"")=0,"",IFERROR(VLOOKUP($A5,'venda-fornecedor-12-meses-7'!$1:$1048576,5 + (COLUMN(B2)-1)*2,FALSE),"")) | GJ5: =IF(IFERROR(VLOOKUP($A5,'venda-fornecedor-12-meses-7'!$1:$1048576,5 + (COLUMN(C2)-1)*2,FALSE),"")=0,"",IFERROR(VLOOKUP($A5,'venda-fornecedor-12-meses-7'!$1:$1048576,5 + (COLUMN(C2)-1)*2,FALSE),"")) | GK5: =IF(IFERROR(VLOOKUP($A5,'venda-fornecedor-12-meses-7'!$1:$1048576,5 + (COLUMN(D2)-1)*2,FALSE),"")=0,"",IFERROR(VLOOKUP($A5,'venda-fornecedor-12-meses-7'!$1:$1048576,5 + (COLUMN(D2)-1)*2,FALSE),"")) | GL5: =IF(IFERROR(VLOOKUP($A5,'venda-fornecedor-12-meses-7'!$1:$1048576,5 + (COLUMN(E2)-1)*2,FALSE),"")=0,"",IFERROR(VLOOKUP($A5,'venda-fornecedor-12-meses-7'!$1:$1048576,5 + (COLUMN(E2)-1)*2,FALSE),"")) | GM5: =IF(IFERROR(VLOOKUP($A5,'venda-fornecedor-12-meses-7'!$1:$1048576,5 + (COLUMN(F2)-1)*2,FALSE),"")=0,"",IFERROR(VLOOKUP($A5,'venda-fornecedor-12-meses-7'!$1:$1048576,5 + (COLUMN(F2)-1)*2,FALSE),"")) | GN5: =IF(IFERROR(VLOOKUP($A5,'venda-fornecedor-12-meses-7'!$1:$1048576,5 + (COLUMN(G2)-1)*2,FALSE),"")=0,"",IFERROR(VLOOKUP($A5,'venda-fornecedor-12-meses-7'!$1:$1048576,5 + (COLUMN(G2)-1)*2,FALSE),"")) | GO5: =IF(IFERROR(VLOOKUP($A5,'venda-fornecedor-12-meses-7'!$1:$1048576,5 + (COLUMN(H2)-1)*2,FALSE),"")=0,"",IFERROR(VLOOKUP($A5,'venda-fornecedor-12-meses-7'!$1:$1048576,5 + (COLUMN(H2)-1)*2,FALSE),"")) | ... GS5: =IF(IFERROR(VLOOKUP($A5,'venda-fornecedor-12-meses-7'!$1:$1048576,5 + (COLUMN(L2)-1)*2,FALSE),"")=0,"",IFERROR(VLOOKUP($A5,'venda-fornecedor-12-meses-7'!$1:$1048576,5 + (COLUMN(L2)-1)*2,FALSE),"")) | GT5: =IF(COUNT(GH5:GS5)=0,"",SUM(GH5:GS5))
A6: 51 | B6: =VLOOKUP(A6,'FORNECEDORES X COMPRADOR'!$A:$D,4,0) | C6: =VLOOKUP(A6,'FORNECEDORES X COMPRADOR'!$A:$E,5,0) | D6: =IFERROR(AVERAGEIF('ANALISE PRODUTO'!F:F,A6,'ANALISE PRODUTO'!BE:BE),"") | E6: =IFERROR(AVERAGEIF('ANALISE PRODUTO'!F:F,A6,'ANALISE PRODUTO'!BF:BF),"") | F6: {=IFERROR( IF( SUMPRODUCT( IFERROR(--('ANALISE PRODUTO'!$F$3:$F$10000=A6),0) * IFERROR(--'ANALISE PRODUTO'!$AJ$3:$AJ$10000,0) )=0, "", SUMPRODUCT( IFERROR(--('ANALISE PRODUTO'!$F$3:$F$10000=A6),0) * IFERROR(--'ANALISE PRODUTO'!$AN$3:$AN$10000,0) ) / SUMPRODUCT( IFERROR(--('ANALISE PRODUTO'!$F$3:$F$10000=A6),0) * IFERROR(--'ANALISE PRODUTO'!$AJ$3:$AJ$10000,0) ) ), "" )} | G6: {=IFERROR( IF( SUMPRODUCT( IFERROR(--('ANALISE PRODUTO'!$F$3:$F$10000=A6),0) * IFERROR(--'ANALISE PRODUTO'!$AJ$3:$AJ$10000,0) )=0, "", SUMPRODUCT( IFERROR(--('ANALISE PRODUTO'!$F$3:$F$10000=A6),0) * IFERROR(--'ANALISE PRODUTO'!$AO$3:$AO$10000,0) ) / SUMPRODUCT( IFERROR(--('ANALISE PRODUTO'!$F$3:$F$10000=A6),0) * IFERROR(--'ANALISE PRODUTO'!$AJ$3:$AJ$10000,0) ) ), "" )} | H6: 60 | I6: 90 | J6: =SUMIF('ANALISE PRODUTO'!F:F, A6, 'ANALISE PRODUTO'!AP:AP) | K6: =SUMIF('ANALISE PRODUTO'!F:F, A6, 'ANALISE PRODUTO'!AN:AN) | L6: =SUMIF('ANALISE PRODUTO'!F:F, A6, 'ANALISE PRODUTO'!BB:BB) | M6: =SUMIF('ANALISE PRODUTO'!F:F, A6, 'ANALISE PRODUTO'!BC:BC) | N6: =SUMIF('ANALISE PRODUTO'!F:F, A6, 'ANALISE PRODUTO'!BD:BD) | O6: =SUMIF('ANALISE PRODUTO'!F:F, A6, 'ANALISE PRODUTO'!BA:BA) | P6: =IF(J6=0, 0, IF(O6/J6=0, 0, O6/J6)) | Q6: =IF(J6=0, 0, IF(L6/J6=0, 0, L6/J6)) | R6: =SUMIF('ANALISE PRODUTO'!F:F, A6, 'ANALISE PRODUTO'!BJ:BJ) | S6: =SUMIF('ANALISE PRODUTO'!F:F, A6, 'ANALISE PRODUTO'!BK:BK) | T6: =SUMIF('ANALISE PRODUTO'!F:F, A6, 'ANALISE PRODUTO'!BL:BL) | U6: =SUMIFS('ANALISE PRODUTO'!BI:BI, 'ANALISE PRODUTO'!F:F, A6) | V6: =IF(C6="DESCONTINUADO", 0, IF(J6=0, 0, IF(U6/J6=0, 0, U6/J6))) | W6: =IF(OR(C6="DESCONTINUADO", J6=0), 0, IFERROR((S6+T6)/J6, 0)) | X6: =COUNTIF('ANALISE PRODUTO'!F:F, A6) | Y6: =COUNTIFS('ANALISE PRODUTO'!F:F, A6, 'ANALISE PRODUTO'!S:S, "S") | Z6: =X6-Y6 | AA6: =IFERROR(IF(COUNTIF('contas-pagas-fornecedor-7'!$C:$C,B6)>1, AVERAGEIF('contas-pagas-fornecedor-7'!$C:$C,B6,'contas-pagas-fornecedor-7'!$I:$I), VLOOKUP(B6,'contas-pagas-fornecedor-7'!$C:$Q,7,FALSE)), "") | AB6: {=IFERROR( INDEX('fornecedor-venda-por-filial-ger'!J:J, MATCH(1, ('fornecedor-venda-por-filial-ger'!A:A=A6) * ('fornecedor-venda-por-filial-ger'!B:B=$B$1), 0) ), "")} | AC6: {=IFERROR( INDEX('fornecedor-venda-por-filial-ger'!O:O, MATCH(1, ('fornecedor-venda-por-filial-ger'!A:A=A6) * ('fornecedor-venda-por-filial-ger'!B:B=$B$1), 0) ), "")} | AD6: =IFERROR(VLOOKUP(A6,'venda-fornecedor-12-meses-7'!A:AC,3,0),"") | AE6: {=IFERROR( INDEX('fornecedor-venda-por-filial-ger'!N:N, MATCH(1, ('fornecedor-venda-por-filial-ger'!A:A=A6) * ('fornecedor-venda-por-filial-ger'!B:B=$B$1), 0) ), "")} | AF6: =IF(J6<=0,"100,00%",IFERROR(AD6/AE6,1)) | AG6: {=IFERROR( INDEX('fornecedor-venda-por-filial-ger'!L:L, MATCH(1, ('fornecedor-venda-por-filial-ger'!A:A=A6)* ('fornecedor-venda-por-filial-ger'!B:B=$B$1), 0) )/100, "")} | AH6: {=IFERROR( INDEX('fornecedor-venda-por-filial-ger'!S:S, MATCH(1, ('fornecedor-venda-por-filial-ger'!A:A=A6) * ('fornecedor-venda-por-filial-ger'!B:B=$B$1), 0) )/100, "")} | AI6: =IFERROR(IF(OR(AH6="",AG6=""),"",IF(J6=0,0,AH6-AG6)),"") | AJ6: {=IF(MAX(IF('ANALISE PRODUTO'!F:F=A6,'ANALISE PRODUTO'!AD:AD))=0,"SEM ENTRADA",MAX(IF('ANALISE PRODUTO'!F:F=A6,'ANALISE PRODUTO'!AD:AD)))} | AL6: =IF(IFERROR(VLOOKUP($A6,'VENDA 2023'!$1:$1048576,3 + (COLUMN(A3)-1)*2,FALSE),"")=0,"",IFERROR(VLOOKUP($A6,'VENDA 2023'!$1:$1048576,3 + (COLUMN(A3)-1)*2,FALSE),"")) | AM6: =IF(IFERROR(VLOOKUP($A6,'VENDA 2023'!$1:$1048576,3 + (COLUMN(B3)-1)*2,FALSE),"")=0,"",IFERROR(VLOOKUP($A6,'VENDA 2023'!$1:$1048576,3 + (COLUMN(B3)-1)*2,FALSE),"")) | AN6: =IF(IFERROR(VLOOKUP($A6,'VENDA 2023'!$1:$1048576,3 + (COLUMN(C3)-1)*2,FALSE),"")=0,"",IFERROR(VLOOKUP($A6,'VENDA 2023'!$1:$1048576,3 + (COLUMN(C3)-1)*2,FALSE),"")) | AO6: =IF(IFERROR(VLOOKUP($A6,'VENDA 2023'!$1:$1048576,3 + (COLUMN(D3)-1)*2,FALSE),"")=0,"",IFERROR(VLOOKUP($A6,'VENDA 2023'!$1:$1048576,3 + (COLUMN(D3)-1)*2,FALSE),"")) | AP6: =IF(IFERROR(VLOOKUP($A6,'VENDA 2023'!$1:$1048576,3 + (COLUMN(E3)-1)*2,FALSE),"")=0,"",IFERROR(VLOOKUP($A6,'VENDA 2023'!$1:$1048576,3 + (COLUMN(E3)-1)*2,FALSE),"")) | AQ6: =IF(IFERROR(VLOOKUP($A6,'VENDA 2023'!$1:$1048576,3 + (COLUMN(F3)-1)*2,FALSE),"")=0,"",IFERROR(VLOOKUP($A6,'VENDA 2023'!$1:$1048576,3 + (COLUMN(F3)-1)*2,FALSE),"")) | AR6: =IF(IFERROR(VLOOKUP($A6,'VENDA 2023'!$1:$1048576,3 + (COLUMN(G3)-1)*2,FALSE),"")=0,"",IFERROR(VLOOKUP($A6,'VENDA 2023'!$1:$1048576,3 + (COLUMN(G3)-1)*2,FALSE),"")) | AS6: =IF(IFERROR(VLOOKUP($A6,'VENDA 2023'!$1:$1048576,3 + (COLUMN(H3)-1)*2,FALSE),"")=0,"",IFERROR(VLOOKUP($A6,'VENDA 2023'!$1:$1048576,3 + (COLUMN(H3)-1)*2,FALSE),"")) | ... AW6: =IF(IFERROR(VLOOKUP($A6,'VENDA 2023'!$1:$1048576,3 + (COLUMN(L3)-1)*2,FALSE),"")=0,"",IFERROR(VLOOKUP($A6,'VENDA 2023'!$1:$1048576,3 + (COLUMN(L3)-1)*2,FALSE),"")) | AX6: =IF(COUNT(AL6:AW6)=0,"",SUM(AL6:AW6)) | AY6: =IF(IFERROR(VLOOKUP($A6,'VENDA 2024'!$1:$1048576,3 + (COLUMN(A3)-1)*2,FALSE),"")=0,"",IFERROR(VLOOKUP($A6,'VENDA 2024'!$1:$1048576,3 + (COLUMN(A3)-1)*2,FALSE),"")) | AZ6: =IF(IFERROR(VLOOKUP($A6,'VENDA 2024'!$1:$1048576,3 + (COLUMN(B3)-1)*2,FALSE),"")=0,"",IFERROR(VLOOKUP($A6,'VENDA 2024'!$1:$1048576,3 + (COLUMN(B3)-1)*2,FALSE),"")) | BA6: =IF(IFERROR(VLOOKUP($A6,'VENDA 2024'!$1:$1048576,3 + (COLUMN(C3)-1)*2,FALSE),"")=0,"",IFERROR(VLOOKUP($A6,'VENDA 2024'!$1:$1048576,3 + (COLUMN(C3)-1)*2,FALSE),"")) | BB6: =IF(IFERROR(VLOOKUP($A6,'VENDA 2024'!$1:$1048576,3 + (COLUMN(D3)-1)*2,FALSE),"")=0,"",IFERROR(VLOOKUP($A6,'VENDA 2024'!$1:$1048576,3 + (COLUMN(D3)-1)*2,FALSE),"")) | BC6: =IF(IFERROR(VLOOKUP($A6,'VENDA 2024'!$1:$1048576,3 + (COLUMN(E3)-1)*2,FALSE),"")=0,"",IFERROR(VLOOKUP($A6,'VENDA 2024'!$1:$1048576,3 + (COLUMN(E3)-1)*2,FALSE),"")) | BD6: =IF(IFERROR(VLOOKUP($A6,'VENDA 2024'!$1:$1048576,3 + (COLUMN(F3)-1)*2,FALSE),"")=0,"",IFERROR(VLOOKUP($A6,'VENDA 2024'!$1:$1048576,3 + (COLUMN(F3)-1)*2,FALSE),"")) | BE6: =IF(IFERROR(VLOOKUP($A6,'VENDA 2024'!$1:$1048576,3 + (COLUMN(G3)-1)*2,FALSE),"")=0,"",IFERROR(VLOOKUP($A6,'VENDA 2024'!$1:$1048576,3 + (COLUMN(G3)-1)*2,FALSE),"")) | BF6: =IF(IFERROR(VLOOKUP($A6,'VENDA 2024'!$1:$1048576,3 + (COLUMN(H3)-1)*2,FALSE),"")=0,"",IFERROR(VLOOKUP($A6,'VENDA 2024'!$1:$1048576,3 + (COLUMN(H3)-1)*2,FALSE),"")) | ... BJ6: =IF(IFERROR(VLOOKUP($A6,'VENDA 2024'!$1:$1048576,3 + (COLUMN(L3)-1)*2,FALSE),"")=0,"",IFERROR(VLOOKUP($A6,'VENDA 2024'!$1:$1048576,3 + (COLUMN(L3)-1)*2,FALSE),"")) | BK6: =IF(COUNT(AY6:BJ6)=0,"",SUM(AY6:BJ6)) | BL6: =IF(IFERROR(VLOOKUP($A6,'VENDA 2025'!$1:$1048576,3 + (COLUMN(A3)-1)*2,FALSE),"")=0,"",IFERROR(VLOOKUP($A6,'VENDA 2025'!$1:$1048576,3 + (COLUMN(A3)-1)*2,FALSE),"")) | BM6: =IF(IFERROR(VLOOKUP($A6,'VENDA 2025'!$1:$1048576,3 + (COLUMN(B3)-1)*2,FALSE),"")=0,"",IFERROR(VLOOKUP($A6,'VENDA 2025'!$1:$1048576,3 + (COLUMN(B3)-1)*2,FALSE),"")) | BN6: =IF(IFERROR(VLOOKUP($A6,'VENDA 2025'!$1:$1048576,3 + (COLUMN(C3)-1)*2,FALSE),"")=0,"",IFERROR(VLOOKUP($A6,'VENDA 2025'!$1:$1048576,3 + (COLUMN(C3)-1)*2,FALSE),"")) | BO6: =IF(IFERROR(VLOOKUP($A6,'VENDA 2025'!$1:$1048576,3 + (COLUMN(D3)-1)*2,FALSE),"")=0,"",IFERROR(VLOOKUP($A6,'VENDA 2025'!$1:$1048576,3 + (COLUMN(D3)-1)*2,FALSE),"")) | BP6: =IF(IFERROR(VLOOKUP($A6,'VENDA 2025'!$1:$1048576,3 + (COLUMN(E3)-1)*2,FALSE),"")=0,"",IFERROR(VLOOKUP($A6,'VENDA 2025'!$1:$1048576,3 + (COLUMN(E3)-1)*2,FALSE),"")) | BQ6: =IF(IFERROR(VLOOKUP($A6,'VENDA 2025'!$1:$1048576,3 + (COLUMN(F3)-1)*2,FALSE),"")=0,"",IFERROR(VLOOKUP($A6,'VENDA 2025'!$1:$1048576,3 + (COLUMN(F3)-1)*2,FALSE),"")) | BR6: =IF(IFERROR(VLOOKUP($A6,'VENDA 2025'!$1:$1048576,3 + (COLUMN(G3)-1)*2,FALSE),"")=0,"",IFERROR(VLOOKUP($A6,'VENDA 2025'!$1:$1048576,3 + (COLUMN(G3)-1)*2,FALSE),"")) | BS6: =IF(IFERROR(VLOOKUP($A6,'VENDA 2025'!$1:$1048576,3 + (COLUMN(H3)-1)*2,FALSE),"")=0,"",IFERROR(VLOOKUP($A6,'VENDA 2025'!$1:$1048576,3 + (COLUMN(H3)-1)*2,FALSE),"")) | ... BW6: =IF(IFERROR(VLOOKUP($A6,'VENDA 2025'!$1:$1048576,3 + (COLUMN(L3)-1)*2,FALSE),"")=0,"",IFERROR(VLOOKUP($A6,'VENDA 2025'!$1:$1048576,3 + (COLUMN(L3)-1)*2,FALSE),"")) | BX6: =IF(COUNT(BL6:BW6)=0,"",SUM(BL6:BW6)) | BY6: =IF(IFERROR(VLOOKUP($A6,'venda-fornecedor-12-meses-7'!$1:$1048576,4 + (COLUMN(A3)-1)*2,FALSE),"")=0,"",IFERROR(VLOOKUP($A6,'venda-fornecedor-12-meses-7'!$1:$1048576,4 + (COLUMN(A3)-1)*2,FALSE),"")) | BZ6: =IF(IFERROR(VLOOKUP($A6,'venda-fornecedor-12-meses-7'!$1:$1048576,4 + (COLUMN(B3)-1)*2,FALSE),"")=0,"",IFERROR(VLOOKUP($A6,'venda-fornecedor-12-meses-7'!$1:$1048576,4 + (COLUMN(B3)-1)*2,FALSE),"")) | CA6: =IF(IFERROR(VLOOKUP($A6,'venda-fornecedor-12-meses-7'!$1:$1048576,4 + (COLUMN(C3)-1)*2,FALSE),"")=0,"",IFERROR(VLOOKUP($A6,'venda-fornecedor-12-meses-7'!$1:$1048576,4 + (COLUMN(C3)-1)*2,FALSE),"")) | CB6: =IF(IFERROR(VLOOKUP($A6,'venda-fornecedor-12-meses-7'!$1:$1048576,4 + (COLUMN(D3)-1)*2,FALSE),"")=0,"",IFERROR(VLOOKUP($A6,'venda-fornecedor-12-meses-7'!$1:$1048576,4 + (COLUMN(D3)-1)*2,FALSE),"")) | CC6: =IF(IFERROR(VLOOKUP($A6,'venda-fornecedor-12-meses-7'!$1:$1048576,4 + (COLUMN(E3)-1)*2,FALSE),"")=0,"",IFERROR(VLOOKUP($A6,'venda-fornecedor-12-meses-7'!$1:$1048576,4 + (COLUMN(E3)-1)*2,FALSE),"")) | CD6: =IF(IFERROR(VLOOKUP($A6,'venda-fornecedor-12-meses-7'!$1:$1048576,4 + (COLUMN(F3)-1)*2,FALSE),"")=0,"",IFERROR(VLOOKUP($A6,'venda-fornecedor-12-meses-7'!$1:$1048576,4 + (COLUMN(F3)-1)*2,FALSE),"")) | CE6: =IF(IFERROR(VLOOKUP($A6,'venda-fornecedor-12-meses-7'!$1:$1048576,4 + (COLUMN(G3)-1)*2,FALSE),"")=0,"",IFERROR(VLOOKUP($A6,'venda-fornecedor-12-meses-7'!$1:$1048576,4 + (COLUMN(G3)-1)*2,FALSE),"")) | CF6: =IF(IFERROR(VLOOKUP($A6,'venda-fornecedor-12-meses-7'!$1:$1048576,4 + (COLUMN(H3)-1)*2,FALSE),"")=0,"",IFERROR(VLOOKUP($A6,'venda-fornecedor-12-meses-7'!$1:$1048576,4 + (COLUMN(H3)-1)*2,FALSE),"")) | ... CJ6: =IF(IFERROR(VLOOKUP($A6,'venda-fornecedor-12-meses-7'!$1:$1048576,4 + (COLUMN(L3)-1)*2,FALSE),"")=0,"",IFERROR(VLOOKUP($A6,'venda-fornecedor-12-meses-7'!$1:$1048576,4 + (COLUMN(L3)-1)*2,FALSE),"")) | CK6: =IF(COUNT(BY6:CJ6)=0,"",SUM(BY6:CJ6)) | CL6: =IF(COUNT(BY6:CJ6)=0,"",AVERAGE(BY6:CJ6)) | CN6: =IF(IFERROR(VLOOKUP($A6,'ENTRADA 2023'!$1:$1048576,3 + (COLUMN(A3)-1)*1,FALSE),"")=0,"",IFERROR(VLOOKUP($A6,'ENTRADA 2023'!$1:$1048576,3 + (COLUMN(A3)-1)*1,FALSE),"")) | CO6: =IF(IFERROR(VLOOKUP($A6,'ENTRADA 2023'!$1:$1048576,3 + (COLUMN(B3)-1)*1,FALSE),"")=0,"",IFERROR(VLOOKUP($A6,'ENTRADA 2023'!$1:$1048576,3 + (COLUMN(B3)-1)*1,FALSE),"")) | CP6: =IF(IFERROR(VLOOKUP($A6,'ENTRADA 2023'!$1:$1048576,3 + (COLUMN(C3)-1)*1,FALSE),"")=0,"",IFERROR(VLOOKUP($A6,'ENTRADA 2023'!$1:$1048576,3 + (COLUMN(C3)-1)*1,FALSE),"")) | CQ6: =IF(IFERROR(VLOOKUP($A6,'ENTRADA 2023'!$1:$1048576,3 + (COLUMN(D3)-1)*1,FALSE),"")=0,"",IFERROR(VLOOKUP($A6,'ENTRADA 2023'!$1:$1048576,3 + (COLUMN(D3)-1)*1,FALSE),"")) | CR6: =IF(IFERROR(VLOOKUP($A6,'ENTRADA 2023'!$1:$1048576,3 + (COLUMN(E3)-1)*1,FALSE),"")=0,"",IFERROR(VLOOKUP($A6,'ENTRADA 2023'!$1:$1048576,3 + (COLUMN(E3)-1)*1,FALSE),"")) | CS6: =IF(IFERROR(VLOOKUP($A6,'ENTRADA 2023'!$1:$1048576,3 + (COLUMN(F3)-1)*1,FALSE),"")=0,"",IFERROR(VLOOKUP($A6,'ENTRADA 2023'!$1:$1048576,3 + (COLUMN(F3)-1)*1,FALSE),"")) | CT6: =IF(IFERROR(VLOOKUP($A6,'ENTRADA 2023'!$1:$1048576,3 + (COLUMN(G3)-1)*1,FALSE),"")=0,"",IFERROR(VLOOKUP($A6,'ENTRADA 2023'!$1:$1048576,3 + (COLUMN(G3)-1)*1,FALSE),"")) | CU6: =IF(IFERROR(VLOOKUP($A6,'ENTRADA 2023'!$1:$1048576,3 + (COLUMN(H3)-1)*1,FALSE),"")=0,"",IFERROR(VLOOKUP($A6,'ENTRADA 2023'!$1:$1048576,3 + (COLUMN(H3)-1)*1,FALSE),"")) | ... CY6: =IF(IFERROR(VLOOKUP($A6,'ENTRADA 2023'!$1:$1048576,3 + (COLUMN(L3)-1)*1,FALSE),"")=0,"",IFERROR(VLOOKUP($A6,'ENTRADA 2023'!$1:$1048576,3 + (COLUMN(L3)-1)*1,FALSE),"")) | CZ6: =IF(COUNT(CN6:CY6)=0,"",SUM(CN6:CY6)) | DA6: =IF(IFERROR(VLOOKUP($A6,'ENTRADA 2024'!$1:$1048576,3 + (COLUMN(A3)-1)*1,FALSE),"")=0,"",IFERROR(VLOOKUP($A6,'ENTRADA 2024'!$1:$1048576,3 + (COLUMN(A3)-1)*1,FALSE),"")) | DB6: =IF(IFERROR(VLOOKUP($A6,'ENTRADA 2024'!$1:$1048576,3 + (COLUMN(B3)-1)*1,FALSE),"")=0,"",IFERROR(VLOOKUP($A6,'ENTRADA 2024'!$1:$1048576,3 + (COLUMN(B3)-1)*1,FALSE),"")) | DC6: =IF(IFERROR(VLOOKUP($A6,'ENTRADA 2024'!$1:$1048576,3 + (COLUMN(C3)-1)*1,FALSE),"")=0,"",IFERROR(VLOOKUP($A6,'ENTRADA 2024'!$1:$1048576,3 + (COLUMN(C3)-1)*1,FALSE),"")) | DD6: =IF(IFERROR(VLOOKUP($A6,'ENTRADA 2024'!$1:$1048576,3 + (COLUMN(D3)-1)*1,FALSE),"")=0,"",IFERROR(VLOOKUP($A6,'ENTRADA 2024'!$1:$1048576,3 + (COLUMN(D3)-1)*1,FALSE),"")) | DE6: =IF(IFERROR(VLOOKUP($A6,'ENTRADA 2024'!$1:$1048576,3 + (COLUMN(E3)-1)*1,FALSE),"")=0,"",IFERROR(VLOOKUP($A6,'ENTRADA 2024'!$1:$1048576,3 + (COLUMN(E3)-1)*1,FALSE),"")) | DF6: =IF(IFERROR(VLOOKUP($A6,'ENTRADA 2024'!$1:$1048576,3 + (COLUMN(F3)-1)*1,FALSE),"")=0,"",IFERROR(VLOOKUP($A6,'ENTRADA 2024'!$1:$1048576,3 + (COLUMN(F3)-1)*1,FALSE),"")) | DG6: =IF(IFERROR(VLOOKUP($A6,'ENTRADA 2024'!$1:$1048576,3 + (COLUMN(G3)-1)*1,FALSE),"")=0,"",IFERROR(VLOOKUP($A6,'ENTRADA 2024'!$1:$1048576,3 + (COLUMN(G3)-1)*1,FALSE),"")) | DH6: =IF(IFERROR(VLOOKUP($A6,'ENTRADA 2024'!$1:$1048576,3 + (COLUMN(H3)-1)*1,FALSE),"")=0,"",IFERROR(VLOOKUP($A6,'ENTRADA 2024'!$1:$1048576,3 + (COLUMN(H3)-1)*1,FALSE),"")) | ... DL6: =IF(IFERROR(VLOOKUP($A6,'ENTRADA 2024'!$1:$1048576,3 + (COLUMN(L3)-1)*1,FALSE),"")=0,"",IFERROR(VLOOKUP($A6,'ENTRADA 2024'!$1:$1048576,3 + (COLUMN(L3)-1)*1,FALSE),"")) | DM6: =IF(COUNT(DA6:DL6)=0,"",SUM(DA6:DL6)) | DN6: =IF(IFERROR(VLOOKUP($A6,'ENTRADA 2025'!$1:$1048576,3 + (COLUMN(A3)-1)*1,FALSE),"")=0,"",IFERROR(VLOOKUP($A6,'ENTRADA 2025'!$1:$1048576,3 + (COLUMN(A3)-1)*1,FALSE),"")) | DO6: =IF(IFERROR(VLOOKUP($A6,'ENTRADA 2025'!$1:$1048576,3 + (COLUMN(B3)-1)*1,FALSE),"")=0,"",IFERROR(VLOOKUP($A6,'ENTRADA 2025'!$1:$1048576,3 + (COLUMN(B3)-1)*1,FALSE),"")) | DP6: =IF(IFERROR(VLOOKUP($A6,'ENTRADA 2025'!$1:$1048576,3 + (COLUMN(C3)-1)*1,FALSE),"")=0,"",IFERROR(VLOOKUP($A6,'ENTRADA 2025'!$1:$1048576,3 + (COLUMN(C3)-1)*1,FALSE),"")) | DQ6: =IF(IFERROR(VLOOKUP($A6,'ENTRADA 2025'!$1:$1048576,3 + (COLUMN(D3)-1)*1,FALSE),"")=0,"",IFERROR(VLOOKUP($A6,'ENTRADA 2025'!$1:$1048576,3 + (COLUMN(D3)-1)*1,FALSE),"")) | DR6: =IF(IFERROR(VLOOKUP($A6,'ENTRADA 2025'!$1:$1048576,3 + (COLUMN(E3)-1)*1,FALSE),"")=0,"",IFERROR(VLOOKUP($A6,'ENTRADA 2025'!$1:$1048576,3 + (COLUMN(E3)-1)*1,FALSE),"")) | DS6: =IF(IFERROR(VLOOKUP($A6,'ENTRADA 2025'!$1:$1048576,3 + (COLUMN(F3)-1)*1,FALSE),"")=0,"",IFERROR(VLOOKUP($A6,'ENTRADA 2025'!$1:$1048576,3 + (COLUMN(F3)-1)*1,FALSE),"")) | DT6: =IF(IFERROR(VLOOKUP($A6,'ENTRADA 2025'!$1:$1048576,3 + (COLUMN(G3)-1)*1,FALSE),"")=0,"",IFERROR(VLOOKUP($A6,'ENTRADA 2025'!$1:$1048576,3 + (COLUMN(G3)-1)*1,FALSE),"")) | DU6: =IF(IFERROR(VLOOKUP($A6,'ENTRADA 2025'!$1:$1048576,3 + (COLUMN(H3)-1)*1,FALSE),"")=0,"",IFERROR(VLOOKUP($A6,'ENTRADA 2025'!$1:$1048576,3 + (COLUMN(H3)-1)*1,FALSE),"")) | ... DY6: =IF(IFERROR(VLOOKUP($A6,'ENTRADA 2025'!$1:$1048576,3 + (COLUMN(L3)-1)*1,FALSE),"")=0,"",IFERROR(VLOOKUP($A6,'ENTRADA 2025'!$1:$1048576,3 + (COLUMN(L3)-1)*1,FALSE),"")) | DZ6: =IF(COUNT(DN6:DY6)=0,"",SUM(DN6:DY6)) | EA6: =IF(IFERROR(VLOOKUP($A6,'entrada-fornecedor-12-meses-7'!$1:$1048576,3 + (COLUMN(A3)-1)*1,FALSE),"")=0,"",IFERROR(VLOOKUP($A6,'entrada-fornecedor-12-meses-7'!$1:$1048576,3 + (COLUMN(A3)-1)*1,FALSE),"")) | EB6: =IF(IFERROR(VLOOKUP($A6,'entrada-fornecedor-12-meses-7'!$1:$1048576,3 + (COLUMN(B3)-1)*1,FALSE),"")=0,"",IFERROR(VLOOKUP($A6,'entrada-fornecedor-12-meses-7'!$1:$1048576,3 + (COLUMN(B3)-1)*1,FALSE),"")) | EC6: =IF(IFERROR(VLOOKUP($A6,'entrada-fornecedor-12-meses-7'!$1:$1048576,3 + (COLUMN(C3)-1)*1,FALSE),"")=0,"",IFERROR(VLOOKUP($A6,'entrada-fornecedor-12-meses-7'!$1:$1048576,3 + (COLUMN(C3)-1)*1,FALSE),"")) | ED6: =IF(IFERROR(VLOOKUP($A6,'entrada-fornecedor-12-meses-7'!$1:$1048576,3 + (COLUMN(D3)-1)*1,FALSE),"")=0,"",IFERROR(VLOOKUP($A6,'entrada-fornecedor-12-meses-7'!$1:$1048576,3 + (COLUMN(D3)-1)*1,FALSE),"")) | EE6: =IF(IFERROR(VLOOKUP($A6,'entrada-fornecedor-12-meses-7'!$1:$1048576,3 + (COLUMN(E3)-1)*1,FALSE),"")=0,"",IFERROR(VLOOKUP($A6,'entrada-fornecedor-12-meses-7'!$1:$1048576,3 + (COLUMN(E3)-1)*1,FALSE),"")) | EF6: =IF(IFERROR(VLOOKUP($A6,'entrada-fornecedor-12-meses-7'!$1:$1048576,3 + (COLUMN(F3)-1)*1,FALSE),"")=0,"",IFERROR(VLOOKUP($A6,'entrada-fornecedor-12-meses-7'!$1:$1048576,3 + (COLUMN(F3)-1)*1,FALSE),"")) | EG6: =IF(IFERROR(VLOOKUP($A6,'entrada-fornecedor-12-meses-7'!$1:$1048576,3 + (COLUMN(G3)-1)*1,FALSE),"")=0,"",IFERROR(VLOOKUP($A6,'entrada-fornecedor-12-meses-7'!$1:$1048576,3 + (COLUMN(G3)-1)*1,FALSE),"")) | EH6: =IF(IFERROR(VLOOKUP($A6,'entrada-fornecedor-12-meses-7'!$1:$1048576,3 + (COLUMN(H3)-1)*1,FALSE),"")=0,"",IFERROR(VLOOKUP($A6,'entrada-fornecedor-12-meses-7'!$1:$1048576,3 + (COLUMN(H3)-1)*1,FALSE),"")) | ... EL6: =IF(IFERROR(VLOOKUP($A6,'entrada-fornecedor-12-meses-7'!$1:$1048576,3 + (COLUMN(L3)-1)*1,FALSE),"")=0,"",IFERROR(VLOOKUP($A6,'entrada-fornecedor-12-meses-7'!$1:$1048576,3 + (COLUMN(L3)-1)*1,FALSE),"")) | EM6: =IF(COUNT(EA6:EL6)=0,"",SUM(EA6:EL6)) | EO6: =IFERROR(AVERAGEIF('lead-time-compras-7'!B:B,A6,'lead-time-compras-7'!S:S),"") | EP6: =IFERROR( AVERAGEIFS( 'notas-fiscais-entrada-830-7'!H:H, 'notas-fiscais-entrada-830-7'!O:O, A6, 'notas-fiscais-entrada-830-7'!E:E, $B$1 ), "" ) | EQ6: =IFERROR(AVERAGEIF('lead-time-compras-7'!B:B,A6,'lead-time-compras-7'!Q:Q),"") | ER6: =SUMIF('fornecedor-saldo-receber-7'!A:A, A6, 'fornecedor-saldo-receber-7'!L:L) | ES6: =SUMIF('fornecedor-verba-aplicar-7'!A:A, A6, 'fornecedor-verba-aplicar-7'!D:D) | EU6: =SUMIF('ANALISE PRODUTO'!F:F, A6, 'ANALISE PRODUTO'!BN:BN) | EV6: =SUMIF('ANALISE PRODUTO'!F:F, A6, 'ANALISE PRODUTO'!BO:BO) | EW6: =SUMIF('ANALISE PRODUTO'!F:F, A6, 'ANALISE PRODUTO'!BP:BP) | EX6: =SUMIF('ANALISE PRODUTO'!F:F, A6, 'ANALISE PRODUTO'!BQ:BQ) | EY6: =SUMIF('ANALISE PRODUTO'!F:F, A6, 'ANALISE PRODUTO'!BR:BR) | EZ6: =SUMIF('ANALISE PRODUTO'!F:F, A6, 'ANALISE PRODUTO'!BS:BS) | FA6: =SUMIF('ANALISE PRODUTO'!F:F, A6, 'ANALISE PRODUTO'!BT:BT) | FB6: =SUMIF('ANALISE PRODUTO'!F:F, A6, 'ANALISE PRODUTO'!BU:BU) | FC6: =SUMIF('ANALISE PRODUTO'!F:F, A6, 'ANALISE PRODUTO'!BV:BV) | FD6: =SUMIF('ANALISE PRODUTO'!F:F, A6, 'ANALISE PRODUTO'!BW:BW) | FE6: =SUMIF('ANALISE PRODUTO'!F:F, A6, 'ANALISE PRODUTO'!CB:CB) | FF6: =SUMIF('ANALISE PRODUTO'!F:F, A6, 'ANALISE PRODUTO'!CC:CC) | FH6: =IF(IFERROR(VLOOKUP($A6,'VENDA 2023'!$1:$1048576,4 + (COLUMN(A3)-1)*2,FALSE),"")=0,"",IFERROR(VLOOKUP($A6,'VENDA 2023'!$1:$1048576,4 + (COLUMN(A3)-1)*2,FALSE),"")) | FI6: =IF(IFERROR(VLOOKUP($A6,'VENDA 2023'!$1:$1048576,4 + (COLUMN(B3)-1)*2,FALSE),"")=0,"",IFERROR(VLOOKUP($A6,'VENDA 2023'!$1:$1048576,4 + (COLUMN(B3)-1)*2,FALSE),"")) | FJ6: =IF(IFERROR(VLOOKUP($A6,'VENDA 2023'!$1:$1048576,4 + (COLUMN(C3)-1)*2,FALSE),"")=0,"",IFERROR(VLOOKUP($A6,'VENDA 2023'!$1:$1048576,4 + (COLUMN(C3)-1)*2,FALSE),"")) | FK6: =IF(IFERROR(VLOOKUP($A6,'VENDA 2023'!$1:$1048576,4 + (COLUMN(D3)-1)*2,FALSE),"")=0,"",IFERROR(VLOOKUP($A6,'VENDA 2023'!$1:$1048576,4 + (COLUMN(D3)-1)*2,FALSE),"")) | FL6: =IF(IFERROR(VLOOKUP($A6,'VENDA 2023'!$1:$1048576,4 + (COLUMN(E3)-1)*2,FALSE),"")=0,"",IFERROR(VLOOKUP($A6,'VENDA 2023'!$1:$1048576,4 + (COLUMN(E3)-1)*2,FALSE),"")) | FM6: =IF(IFERROR(VLOOKUP($A6,'VENDA 2023'!$1:$1048576,4 + (COLUMN(F3)-1)*2,FALSE),"")=0,"",IFERROR(VLOOKUP($A6,'VENDA 2023'!$1:$1048576,4 + (COLUMN(F3)-1)*2,FALSE),"")) | FN6: =IF(IFERROR(VLOOKUP($A6,'VENDA 2023'!$1:$1048576,4 + (COLUMN(G3)-1)*2,FALSE),"")=0,"",IFERROR(VLOOKUP($A6,'VENDA 2023'!$1:$1048576,4 + (COLUMN(G3)-1)*2,FALSE),"")) | FO6: =IF(IFERROR(VLOOKUP($A6,'VENDA 2023'!$1:$1048576,4 + (COLUMN(H3)-1)*2,FALSE),"")=0,"",IFERROR(VLOOKUP($A6,'VENDA 2023'!$1:$1048576,4 + (COLUMN(H3)-1)*2,FALSE),"")) | ... FS6: =IF(IFERROR(VLOOKUP($A6,'VENDA 2023'!$1:$1048576,4 + (COLUMN(L3)-1)*2,FALSE),"")=0,"",IFERROR(VLOOKUP($A6,'VENDA 2023'!$1:$1048576,4 + (COLUMN(L3)-1)*2,FALSE),"")) | FT6: =IF(COUNT(FH6:FS6)=0,"",SUM(FH6:FS6)) | FU6: =IF(IFERROR(VLOOKUP($A6,'VENDA 2024'!$1:$1048576,4 + (COLUMN(A3)-1)*2,FALSE),"")=0,"",IFERROR(VLOOKUP($A6,'VENDA 2024'!$1:$1048576,4 + (COLUMN(A3)-1)*2,FALSE),"")) | FV6: =IF(IFERROR(VLOOKUP($A6,'VENDA 2024'!$1:$1048576,4 + (COLUMN(B3)-1)*2,FALSE),"")=0,"",IFERROR(VLOOKUP($A6,'VENDA 2024'!$1:$1048576,4 + (COLUMN(B3)-1)*2,FALSE),"")) | FW6: =IF(IFERROR(VLOOKUP($A6,'VENDA 2024'!$1:$1048576,4 + (COLUMN(C3)-1)*2,FALSE),"")=0,"",IFERROR(VLOOKUP($A6,'VENDA 2024'!$1:$1048576,4 + (COLUMN(C3)-1)*2,FALSE),"")) | FX6: =IF(IFERROR(VLOOKUP($A6,'VENDA 2024'!$1:$1048576,4 + (COLUMN(D3)-1)*2,FALSE),"")=0,"",IFERROR(VLOOKUP($A6,'VENDA 2024'!$1:$1048576,4 + (COLUMN(D3)-1)*2,FALSE),"")) | FY6: =IF(IFERROR(VLOOKUP($A6,'VENDA 2024'!$1:$1048576,4 + (COLUMN(E3)-1)*2,FALSE),"")=0,"",IFERROR(VLOOKUP($A6,'VENDA 2024'!$1:$1048576,4 + (COLUMN(E3)-1)*2,FALSE),"")) | FZ6: =IF(IFERROR(VLOOKUP($A6,'VENDA 2024'!$1:$1048576,4 + (COLUMN(F3)-1)*2,FALSE),"")=0,"",IFERROR(VLOOKUP($A6,'VENDA 2024'!$1:$1048576,4 + (COLUMN(F3)-1)*2,FALSE),"")) | GA6: =IF(IFERROR(VLOOKUP($A6,'VENDA 2024'!$1:$1048576,4 + (COLUMN(G3)-1)*2,FALSE),"")=0,"",IFERROR(VLOOKUP($A6,'VENDA 2024'!$1:$1048576,4 + (COLUMN(G3)-1)*2,FALSE),"")) | GB6: =IF(IFERROR(VLOOKUP($A6,'VENDA 2024'!$1:$1048576,4 + (COLUMN(H3)-1)*2,FALSE),"")=0,"",IFERROR(VLOOKUP($A6,'VENDA 2024'!$1:$1048576,4 + (COLUMN(H3)-1)*2,FALSE),"")) | ... GF6: =IF(IFERROR(VLOOKUP($A6,'VENDA 2024'!$1:$1048576,4 + (COLUMN(L3)-1)*2,FALSE),"")=0,"",IFERROR(VLOOKUP($A6,'VENDA 2024'!$1:$1048576,4 + (COLUMN(L3)-1)*2,FALSE),"")) | GG6: =IF(COUNT(FU6:GF6)=0,"",SUM(FU6:GF6)) | GH6: =IF(IFERROR(VLOOKUP($A6,'venda-fornecedor-12-meses-7'!$1:$1048576,5 + (COLUMN(A3)-1)*2,FALSE),"")=0,"",IFERROR(VLOOKUP($A6,'venda-fornecedor-12-meses-7'!$1:$1048576,5 + (COLUMN(A3)-1)*2,FALSE),"")) | GI6: =IF(IFERROR(VLOOKUP($A6,'venda-fornecedor-12-meses-7'!$1:$1048576,5 + (COLUMN(B3)-1)*2,FALSE),"")=0,"",IFERROR(VLOOKUP($A6,'venda-fornecedor-12-meses-7'!$1:$1048576,5 + (COLUMN(B3)-1)*2,FALSE),"")) | GJ6: =IF(IFERROR(VLOOKUP($A6,'venda-fornecedor-12-meses-7'!$1:$1048576,5 + (COLUMN(C3)-1)*2,FALSE),"")=0,"",IFERROR(VLOOKUP($A6,'venda-fornecedor-12-meses-7'!$1:$1048576,5 + (COLUMN(C3)-1)*2,FALSE),"")) | GK6: =IF(IFERROR(VLOOKUP($A6,'venda-fornecedor-12-meses-7'!$1:$1048576,5 + (COLUMN(D3)-1)*2,FALSE),"")=0,"",IFERROR(VLOOKUP($A6,'venda-fornecedor-12-meses-7'!$1:$1048576,5 + (COLUMN(D3)-1)*2,FALSE),"")) | GL6: =IF(IFERROR(VLOOKUP($A6,'venda-fornecedor-12-meses-7'!$1:$1048576,5 + (COLUMN(E3)-1)*2,FALSE),"")=0,"",IFERROR(VLOOKUP($A6,'venda-fornecedor-12-meses-7'!$1:$1048576,5 + (COLUMN(E3)-1)*2,FALSE),"")) | GM6: =IF(IFERROR(VLOOKUP($A6,'venda-fornecedor-12-meses-7'!$1:$1048576,5 + (COLUMN(F3)-1)*2,FALSE),"")=0,"",IFERROR(VLOOKUP($A6,'venda-fornecedor-12-meses-7'!$1:$1048576,5 + (COLUMN(F3)-1)*2,FALSE),"")) | GN6: =IF(IFERROR(VLOOKUP($A6,'venda-fornecedor-12-meses-7'!$1:$1048576,5 + (COLUMN(G3)-1)*2,FALSE),"")=0,"",IFERROR(VLOOKUP($A6,'venda-fornecedor-12-meses-7'!$1:$1048576,5 + (COLUMN(G3)-1)*2,FALSE),"")) | GO6: =IF(IFERROR(VLOOKUP($A6,'venda-fornecedor-12-meses-7'!$1:$1048576,5 + (COLUMN(H3)-1)*2,FALSE),"")=0,"",IFERROR(VLOOKUP($A6,'venda-fornecedor-12-meses-7'!$1:$1048576,5 + (COLUMN(H3)-1)*2,FALSE),"")) | ... GS6: =IF(IFERROR(VLOOKUP($A6,'venda-fornecedor-12-meses-7'!$1:$1048576,5 + (COLUMN(L3)-1)*2,FALSE),"")=0,"",IFERROR(VLOOKUP($A6,'venda-fornecedor-12-meses-7'!$1:$1048576,5 + (COLUMN(L3)-1)*2,FALSE),"")) | GT6: =IF(COUNT(GH6:GS6)=0,"",SUM(GH6:GS6))
A7: 36138 | B7: =VLOOKUP(A7,'FORNECEDORES X COMPRADOR'!$A:$D,4,0) | C7: =VLOOKUP(A7,'FORNECEDORES X COMPRADOR'!$A:$E,5,0) | D7: =IFERROR(AVERAGEIF('ANALISE PRODUTO'!F:F,A7,'ANALISE PRODUTO'!BE:BE),"") | E7: =IFERROR(AVERAGEIF('ANALISE PRODUTO'!F:F,A7,'ANALISE PRODUTO'!BF:BF),"") | F7: {=IFERROR( IF( SUMPRODUCT( IFERROR(--('ANALISE PRODUTO'!$F$3:$F$10000=A7),0) * IFERROR(--'ANALISE PRODUTO'!$AJ$3:$AJ$10000,0) )=0, "", SUMPRODUCT( IFERROR(--('ANALISE PRODUTO'!$F$3:$F$10000=A7),0) * IFERROR(--'ANALISE PRODUTO'!$AN$3:$AN$10000,0) ) / SUMPRODUCT( IFERROR(--('ANALISE PRODUTO'!$F$3:$F$10000=A7),0) * IFERROR(--'ANALISE PRODUTO'!$AJ$3:$AJ$10000,0) ) ), "" )} | G7: {=IFERROR( IF( SUMPRODUCT( IFERROR(--('ANALISE PRODUTO'!$F$3:$F$10000=A7),0) * IFERROR(--'ANALISE PRODUTO'!$AJ$3:$AJ$10000,0) )=0, "", SUMPRODUCT( IFERROR(--('ANALISE PRODUTO'!$F$3:$F$10000=A7),0) * IFERROR(--'ANALISE PRODUTO'!$AO$3:$AO$10000,0) ) / SUMPRODUCT( IFERROR(--('ANALISE PRODUTO'!$F$3:$F$10000=A7),0) * IFERROR(--'ANALISE PRODUTO'!$AJ$3:$AJ$10000,0) ) ), "" )} | H7: 60 | I7: 90 | J7: =SUMIF('ANALISE PRODUTO'!F:F, A7, 'ANALISE PRODUTO'!AP:AP) | K7: =SUMIF('ANALISE PRODUTO'!F:F, A7, 'ANALISE PRODUTO'!AN:AN) | L7: =SUMIF('ANALISE PRODUTO'!F:F, A7, 'ANALISE PRODUTO'!BB:BB) | M7: =SUMIF('ANALISE PRODUTO'!F:F, A7, 'ANALISE PRODUTO'!BC:BC) | N7: =SUMIF('ANALISE PRODUTO'!F:F, A7, 'ANALISE PRODUTO'!BD:BD) | O7: =SUMIF('ANALISE PRODUTO'!F:F, A7, 'ANALISE PRODUTO'!BA:BA) | P7: =IF(J7=0, 0, IF(O7/J7=0, 0, O7/J7)) | Q7: =IF(J7=0, 0, IF(L7/J7=0, 0, L7/J7)) | R7: =SUMIF('ANALISE PRODUTO'!F:F, A7, 'ANALISE PRODUTO'!BJ:BJ) | S7: =SUMIF('ANALISE PRODUTO'!F:F, A7, 'ANALISE PRODUTO'!BK:BK) | T7: =SUMIF('ANALISE PRODUTO'!F:F, A7, 'ANALISE PRODUTO'!BL:BL) | U7: =SUMIFS('ANALISE PRODUTO'!BI:BI, 'ANALISE PRODUTO'!F:F, A7) | V7: =IF(C7="DESCONTINUADO", 0, IF(J7=0, 0, IF(U7/J7=0, 0, U7/J7))) | W7: =IF(OR(C7="DESCONTINUADO", J7=0), 0, IFERROR((S7+T7)/J7, 0)) | X7: =COUNTIF('ANALISE PRODUTO'!F:F, A7) | Y7: =COUNTIFS('ANALISE PRODUTO'!F:F, A7, 'ANALISE PRODUTO'!S:S, "S") | Z7: =X7-Y7 | AA7: =IFERROR(IF(COUNTIF('contas-pagas-fornecedor-7'!$C:$C,B7)>1, AVERAGEIF('contas-pagas-fornecedor-7'!$C:$C,B7,'contas-pagas-fornecedor-7'!$I:$I), VLOOKUP(B7,'contas-pagas-fornecedor-7'!$C:$Q,7,FALSE)), "") | AB7: {=IFERROR( INDEX('fornecedor-venda-por-filial-ger'!J:J, MATCH(1, ('fornecedor-venda-por-filial-ger'!A:A=A7) * ('fornecedor-venda-por-filial-ger'!B:B=$B$1), 0) ), "")} | AC7: {=IFERROR( INDEX('fornecedor-venda-por-filial-ger'!O:O, MATCH(1, ('fornecedor-venda-por-filial-ger'!A:A=A7) * ('fornecedor-venda-por-filial-ger'!B:B=$B$1), 0) ), "")} | AD7: =IFERROR(VLOOKUP(A7,'venda-fornecedor-12-meses-7'!A:AC,3,0),"") | AE7: {=IFERROR( INDEX('fornecedor-venda-por-filial-ger'!N:N, MATCH(1, ('fornecedor-venda-por-filial-ger'!A:A=A7) * ('fornecedor-venda-por-filial-ger'!B:B=$B$1), 0) ), "")} | AF7: =IF(J7<=0,"100,00%",IFERROR(AD7/AE7,1)) | AG7: {=IFERROR( INDEX('fornecedor-venda-por-filial-ger'!L:L, MATCH(1, ('fornecedor-venda-por-filial-ger'!A:A=A7)* ('fornecedor-venda-por-filial-ger'!B:B=$B$1), 0) )/100, "")} | AH7: {=IFERROR( INDEX('fornecedor-venda-por-filial-ger'!S:S, MATCH(1, ('fornecedor-venda-por-filial-ger'!A:A=A7) * ('fornecedor-venda-por-filial-ger'!B:B=$B$1), 0) )/100, "")} | AI7: =IFERROR(IF(OR(AH7="",AG7=""),"",IF(J7=0,0,AH7-AG7)),"") | AJ7: {=IF(MAX(IF('ANALISE PRODUTO'!F:F=A7,'ANALISE PRODUTO'!AD:AD))=0,"SEM ENTRADA",MAX(IF('ANALISE PRODUTO'!F:F=A7,'ANALISE PRODUTO'!AD:AD)))} | AL7: =IF(IFERROR(VLOOKUP($A7,'VENDA 2023'!$1:$1048576,3 + (COLUMN(A4)-1)*2,FALSE),"")=0,"",IFERROR(VLOOKUP($A7,'VENDA 2023'!$1:$1048576,3 + (COLUMN(A4)-1)*2,FALSE),"")) | AM7: =IF(IFERROR(VLOOKUP($A7,'VENDA 2023'!$1:$1048576,3 + (COLUMN(B4)-1)*2,FALSE),"")=0,"",IFERROR(VLOOKUP($A7,'VENDA 2023'!$1:$1048576,3 + (COLUMN(B4)-1)*2,FALSE),"")) | AN7: =IF(IFERROR(VLOOKUP($A7,'VENDA 2023'!$1:$1048576,3 + (COLUMN(C4)-1)*2,FALSE),"")=0,"",IFERROR(VLOOKUP($A7,'VENDA 2023'!$1:$1048576,3 + (COLUMN(C4)-1)*2,FALSE),"")) | AO7: =IF(IFERROR(VLOOKUP($A7,'VENDA 2023'!$1:$1048576,3 + (COLUMN(D4)-1)*2,FALSE),"")=0,"",IFERROR(VLOOKUP($A7,'VENDA 2023'!$1:$1048576,3 + (COLUMN(D4)-1)*2,FALSE),"")) | AP7: =IF(IFERROR(VLOOKUP($A7,'VENDA 2023'!$1:$1048576,3 + (COLUMN(E4)-1)*2,FALSE),"")=0,"",IFERROR(VLOOKUP($A7,'VENDA 2023'!$1:$1048576,3 + (COLUMN(E4)-1)*2,FALSE),"")) | AQ7: =IF(IFERROR(VLOOKUP($A7,'VENDA 2023'!$1:$1048576,3 + (COLUMN(F4)-1)*2,FALSE),"")=0,"",IFERROR(VLOOKUP($A7,'VENDA 2023'!$1:$1048576,3 + (COLUMN(F4)-1)*2,FALSE),"")) | AR7: =IF(IFERROR(VLOOKUP($A7,'VENDA 2023'!$1:$1048576,3 + (COLUMN(G4)-1)*2,FALSE),"")=0,"",IFERROR(VLOOKUP($A7,'VENDA 2023'!$1:$1048576,3 + (COLUMN(G4)-1)*2,FALSE),"")) | AS7: =IF(IFERROR(VLOOKUP($A7,'VENDA 2023'!$1:$1048576,3 + (COLUMN(H4)-1)*2,FALSE),"")=0,"",IFERROR(VLOOKUP($A7,'VENDA 2023'!$1:$1048576,3 + (COLUMN(H4)-1)*2,FALSE),"")) | ... AW7: =IF(IFERROR(VLOOKUP($A7,'VENDA 2023'!$1:$1048576,3 + (COLUMN(L4)-1)*2,FALSE),"")=0,"",IFERROR(VLOOKUP($A7,'VENDA 2023'!$1:$1048576,3 + (COLUMN(L4)-1)*2,FALSE),"")) | AX7: =IF(COUNT(AL7:AW7)=0,"",SUM(AL7:AW7)) | AY7: =IF(IFERROR(VLOOKUP($A7,'VENDA 2024'!$1:$1048576,3 + (COLUMN(A4)-1)*2,FALSE),"")=0,"",IFERROR(VLOOKUP($A7,'VENDA 2024'!$1:$1048576,3 + (COLUMN(A4)-1)*2,FALSE),"")) | AZ7: =IF(IFERROR(VLOOKUP($A7,'VENDA 2024'!$1:$1048576,3 + (COLUMN(B4)-1)*2,FALSE),"")=0,"",IFERROR(VLOOKUP($A7,'VENDA 2024'!$1:$1048576,3 + (COLUMN(B4)-1)*2,FALSE),"")) | BA7: =IF(IFERROR(VLOOKUP($A7,'VENDA 2024'!$1:$1048576,3 + (COLUMN(C4)-1)*2,FALSE),"")=0,"",IFERROR(VLOOKUP($A7,'VENDA 2024'!$1:$1048576,3 + (COLUMN(C4)-1)*2,FALSE),"")) | BB7: =IF(IFERROR(VLOOKUP($A7,'VENDA 2024'!$1:$1048576,3 + (COLUMN(D4)-1)*2,FALSE),"")=0,"",IFERROR(VLOOKUP($A7,'VENDA 2024'!$1:$1048576,3 + (COLUMN(D4)-1)*2,FALSE),"")) | BC7: =IF(IFERROR(VLOOKUP($A7,'VENDA 2024'!$1:$1048576,3 + (COLUMN(E4)-1)*2,FALSE),"")=0,"",IFERROR(VLOOKUP($A7,'VENDA 2024'!$1:$1048576,3 + (COLUMN(E4)-1)*2,FALSE),"")) | BD7: =IF(IFERROR(VLOOKUP($A7,'VENDA 2024'!$1:$1048576,3 + (COLUMN(F4)-1)*2,FALSE),"")=0,"",IFERROR(VLOOKUP($A7,'VENDA 2024'!$1:$1048576,3 + (COLUMN(F4)-1)*2,FALSE),"")) | BE7: =IF(IFERROR(VLOOKUP($A7,'VENDA 2024'!$1:$1048576,3 + (COLUMN(G4)-1)*2,FALSE),"")=0,"",IFERROR(VLOOKUP($A7,'VENDA 2024'!$1:$1048576,3 + (COLUMN(G4)-1)*2,FALSE),"")) | BF7: =IF(IFERROR(VLOOKUP($A7,'VENDA 2024'!$1:$1048576,3 + (COLUMN(H4)-1)*2,FALSE),"")=0,"",IFERROR(VLOOKUP($A7,'VENDA 2024'!$1:$1048576,3 + (COLUMN(H4)-1)*2,FALSE),"")) | ... BJ7: =IF(IFERROR(VLOOKUP($A7,'VENDA 2024'!$1:$1048576,3 + (COLUMN(L4)-1)*2,FALSE),"")=0,"",IFERROR(VLOOKUP($A7,'VENDA 2024'!$1:$1048576,3 + (COLUMN(L4)-1)*2,FALSE),"")) | BK7: =IF(COUNT(AY7:BJ7)=0,"",SUM(AY7:BJ7)) | BL7: =IF(IFERROR(VLOOKUP($A7,'VENDA 2025'!$1:$1048576,3 + (COLUMN(A4)-1)*2,FALSE),"")=0,"",IFERROR(VLOOKUP($A7,'VENDA 2025'!$1:$1048576,3 + (COLUMN(A4)-1)*2,FALSE),"")) | BM7: =IF(IFERROR(VLOOKUP($A7,'VENDA 2025'!$1:$1048576,3 + (COLUMN(B4)-1)*2,FALSE),"")=0,"",IFERROR(VLOOKUP($A7,'VENDA 2025'!$1:$1048576,3 + (COLUMN(B4)-1)*2,FALSE),"")) | BN7: =IF(IFERROR(VLOOKUP($A7,'VENDA 2025'!$1:$1048576,3 + (COLUMN(C4)-1)*2,FALSE),"")=0,"",IFERROR(VLOOKUP($A7,'VENDA 2025'!$1:$1048576,3 + (COLUMN(C4)-1)*2,FALSE),"")) | BO7: =IF(IFERROR(VLOOKUP($A7,'VENDA 2025'!$1:$1048576,3 + (COLUMN(D4)-1)*2,FALSE),"")=0,"",IFERROR(VLOOKUP($A7,'VENDA 2025'!$1:$1048576,3 + (COLUMN(D4)-1)*2,FALSE),"")) | BP7: =IF(IFERROR(VLOOKUP($A7,'VENDA 2025'!$1:$1048576,3 + (COLUMN(E4)-1)*2,FALSE),"")=0,"",IFERROR(VLOOKUP($A7,'VENDA 2025'!$1:$1048576,3 + (COLUMN(E4)-1)*2,FALSE),"")) | BQ7: =IF(IFERROR(VLOOKUP($A7,'VENDA 2025'!$1:$1048576,3 + (COLUMN(F4)-1)*2,FALSE),"")=0,"",IFERROR(VLOOKUP($A7,'VENDA 2025'!$1:$1048576,3 + (COLUMN(F4)-1)*2,FALSE),"")) | BR7: =IF(IFERROR(VLOOKUP($A7,'VENDA 2025'!$1:$1048576,3 + (COLUMN(G4)-1)*2,FALSE),"")=0,"",IFERROR(VLOOKUP($A7,'VENDA 2025'!$1:$1048576,3 + (COLUMN(G4)-1)*2,FALSE),"")) | BS7: =IF(IFERROR(VLOOKUP($A7,'VENDA 2025'!$1:$1048576,3 + (COLUMN(H4)-1)*2,FALSE),"")=0,"",IFERROR(VLOOKUP($A7,'VENDA 2025'!$1:$1048576,3 + (COLUMN(H4)-1)*2,FALSE),"")) | ... BW7: =IF(IFERROR(VLOOKUP($A7,'VENDA 2025'!$1:$1048576,3 + (COLUMN(L4)-1)*2,FALSE),"")=0,"",IFERROR(VLOOKUP($A7,'VENDA 2025'!$1:$1048576,3 + (COLUMN(L4)-1)*2,FALSE),"")) | BX7: =IF(COUNT(BL7:BW7)=0,"",SUM(BL7:BW7)) | BY7: =IF(IFERROR(VLOOKUP($A7,'venda-fornecedor-12-meses-7'!$1:$1048576,4 + (COLUMN(A4)-1)*2,FALSE),"")=0,"",IFERROR(VLOOKUP($A7,'venda-fornecedor-12-meses-7'!$1:$1048576,4 + (COLUMN(A4)-1)*2,FALSE),"")) | BZ7: =IF(IFERROR(VLOOKUP($A7,'venda-fornecedor-12-meses-7'!$1:$1048576,4 + (COLUMN(B4)-1)*2,FALSE),"")=0,"",IFERROR(VLOOKUP($A7,'venda-fornecedor-12-meses-7'!$1:$1048576,4 + (COLUMN(B4)-1)*2,FALSE),"")) | CA7: =IF(IFERROR(VLOOKUP($A7,'venda-fornecedor-12-meses-7'!$1:$1048576,4 + (COLUMN(C4)-1)*2,FALSE),"")=0,"",IFERROR(VLOOKUP($A7,'venda-fornecedor-12-meses-7'!$1:$1048576,4 + (COLUMN(C4)-1)*2,FALSE),"")) | CB7: =IF(IFERROR(VLOOKUP($A7,'venda-fornecedor-12-meses-7'!$1:$1048576,4 + (COLUMN(D4)-1)*2,FALSE),"")=0,"",IFERROR(VLOOKUP($A7,'venda-fornecedor-12-meses-7'!$1:$1048576,4 + (COLUMN(D4)-1)*2,FALSE),"")) | CC7: =IF(IFERROR(VLOOKUP($A7,'venda-fornecedor-12-meses-7'!$1:$1048576,4 + (COLUMN(E4)-1)*2,FALSE),"")=0,"",IFERROR(VLOOKUP($A7,'venda-fornecedor-12-meses-7'!$1:$1048576,4 + (COLUMN(E4)-1)*2,FALSE),"")) | CD7: =IF(IFERROR(VLOOKUP($A7,'venda-fornecedor-12-meses-7'!$1:$1048576,4 + (COLUMN(F4)-1)*2,FALSE),"")=0,"",IFERROR(VLOOKUP($A7,'venda-fornecedor-12-meses-7'!$1:$1048576,4 + (COLUMN(F4)-1)*2,FALSE),"")) | CE7: =IF(IFERROR(VLOOKUP($A7,'venda-fornecedor-12-meses-7'!$1:$1048576,4 + (COLUMN(G4)-1)*2,FALSE),"")=0,"",IFERROR(VLOOKUP($A7,'venda-fornecedor-12-meses-7'!$1:$1048576,4 + (COLUMN(G4)-1)*2,FALSE),"")) | CF7: =IF(IFERROR(VLOOKUP($A7,'venda-fornecedor-12-meses-7'!$1:$1048576,4 + (COLUMN(H4)-1)*2,FALSE),"")=0,"",IFERROR(VLOOKUP($A7,'venda-fornecedor-12-meses-7'!$1:$1048576,4 + (COLUMN(H4)-1)*2,FALSE),"")) | ... CJ7: =IF(IFERROR(VLOOKUP($A7,'venda-fornecedor-12-meses-7'!$1:$1048576,4 + (COLUMN(L4)-1)*2,FALSE),"")=0,"",IFERROR(VLOOKUP($A7,'venda-fornecedor-12-meses-7'!$1:$1048576,4 + (COLUMN(L4)-1)*2,FALSE),"")) | CK7: =IF(COUNT(BY7:CJ7)=0,"",SUM(BY7:CJ7)) | CL7: =IF(COUNT(BY7:CJ7)=0,"",AVERAGE(BY7:CJ7)) | CN7: =IF(IFERROR(VLOOKUP($A7,'ENTRADA 2023'!$1:$1048576,3 + (COLUMN(A4)-1)*1,FALSE),"")=0,"",IFERROR(VLOOKUP($A7,'ENTRADA 2023'!$1:$1048576,3 + (COLUMN(A4)-1)*1,FALSE),"")) | CO7: =IF(IFERROR(VLOOKUP($A7,'ENTRADA 2023'!$1:$1048576,3 + (COLUMN(B4)-1)*1,FALSE),"")=0,"",IFERROR(VLOOKUP($A7,'ENTRADA 2023'!$1:$1048576,3 + (COLUMN(B4)-1)*1,FALSE),"")) | CP7: =IF(IFERROR(VLOOKUP($A7,'ENTRADA 2023'!$1:$1048576,3 + (COLUMN(C4)-1)*1,FALSE),"")=0,"",IFERROR(VLOOKUP($A7,'ENTRADA 2023'!$1:$1048576,3 + (COLUMN(C4)-1)*1,FALSE),"")) | CQ7: =IF(IFERROR(VLOOKUP($A7,'ENTRADA 2023'!$1:$1048576,3 + (COLUMN(D4)-1)*1,FALSE),"")=0,"",IFERROR(VLOOKUP($A7,'ENTRADA 2023'!$1:$1048576,3 + (COLUMN(D4)-1)*1,FALSE),"")) | CR7: =IF(IFERROR(VLOOKUP($A7,'ENTRADA 2023'!$1:$1048576,3 + (COLUMN(E4)-1)*1,FALSE),"")=0,"",IFERROR(VLOOKUP($A7,'ENTRADA 2023'!$1:$1048576,3 + (COLUMN(E4)-1)*1,FALSE),"")) | CS7: =IF(IFERROR(VLOOKUP($A7,'ENTRADA 2023'!$1:$1048576,3 + (COLUMN(F4)-1)*1,FALSE),"")=0,"",IFERROR(VLOOKUP($A7,'ENTRADA 2023'!$1:$1048576,3 + (COLUMN(F4)-1)*1,FALSE),"")) | CT7: =IF(IFERROR(VLOOKUP($A7,'ENTRADA 2023'!$1:$1048576,3 + (COLUMN(G4)-1)*1,FALSE),"")=0,"",IFERROR(VLOOKUP($A7,'ENTRADA 2023'!$1:$1048576,3 + (COLUMN(G4)-1)*1,FALSE),"")) | CU7: =IF(IFERROR(VLOOKUP($A7,'ENTRADA 2023'!$1:$1048576,3 + (COLUMN(H4)-1)*1,FALSE),"")=0,"",IFERROR(VLOOKUP($A7,'ENTRADA 2023'!$1:$1048576,3 + (COLUMN(H4)-1)*1,FALSE),"")) | ... CY7: =IF(IFERROR(VLOOKUP($A7,'ENTRADA 2023'!$1:$1048576,3 + (COLUMN(L4)-1)*1,FALSE),"")=0,"",IFERROR(VLOOKUP($A7,'ENTRADA 2023'!$1:$1048576,3 + (COLUMN(L4)-1)*1,FALSE),"")) | CZ7: =IF(COUNT(CN7:CY7)=0,"",SUM(CN7:CY7)) | DA7: =IF(IFERROR(VLOOKUP($A7,'ENTRADA 2024'!$1:$1048576,3 + (COLUMN(A4)-1)*1,FALSE),"")=0,"",IFERROR(VLOOKUP($A7,'ENTRADA 2024'!$1:$1048576,3 + (COLUMN(A4)-1)*1,FALSE),"")) | DB7: =IF(IFERROR(VLOOKUP($A7,'ENTRADA 2024'!$1:$1048576,3 + (COLUMN(B4)-1)*1,FALSE),"")=0,"",IFERROR(VLOOKUP($A7,'ENTRADA 2024'!$1:$1048576,3 + (COLUMN(B4)-1)*1,FALSE),"")) | DC7: =IF(IFERROR(VLOOKUP($A7,'ENTRADA 2024'!$1:$1048576,3 + (COLUMN(C4)-1)*1,FALSE),"")=0,"",IFERROR(VLOOKUP($A7,'ENTRADA 2024'!$1:$1048576,3 + (COLUMN(C4)-1)*1,FALSE),"")) | DD7: =IF(IFERROR(VLOOKUP($A7,'ENTRADA 2024'!$1:$1048576,3 + (COLUMN(D4)-1)*1,FALSE),"")=0,"",IFERROR(VLOOKUP($A7,'ENTRADA 2024'!$1:$1048576,3 + (COLUMN(D4)-1)*1,FALSE),"")) | DE7: =IF(IFERROR(VLOOKUP($A7,'ENTRADA 2024'!$1:$1048576,3 + (COLUMN(E4)-1)*1,FALSE),"")=0,"",IFERROR(VLOOKUP($A7,'ENTRADA 2024'!$1:$1048576,3 + (COLUMN(E4)-1)*1,FALSE),"")) | DF7: =IF(IFERROR(VLOOKUP($A7,'ENTRADA 2024'!$1:$1048576,3 + (COLUMN(F4)-1)*1,FALSE),"")=0,"",IFERROR(VLOOKUP($A7,'ENTRADA 2024'!$1:$1048576,3 + (COLUMN(F4)-1)*1,FALSE),"")) | DG7: =IF(IFERROR(VLOOKUP($A7,'ENTRADA 2024'!$1:$1048576,3 + (COLUMN(G4)-1)*1,FALSE),"")=0,"",IFERROR(VLOOKUP($A7,'ENTRADA 2024'!$1:$1048576,3 + (COLUMN(G4)-1)*1,FALSE),"")) | DH7: =IF(IFERROR(VLOOKUP($A7,'ENTRADA 2024'!$1:$1048576,3 + (COLUMN(H4)-1)*1,FALSE),"")=0,"",IFERROR(VLOOKUP($A7,'ENTRADA 2024'!$1:$1048576,3 + (COLUMN(H4)-1)*1,FALSE),"")) | ... DL7: =IF(IFERROR(VLOOKUP($A7,'ENTRADA 2024'!$1:$1048576,3 + (COLUMN(L4)-1)*1,FALSE),"")=0,"",IFERROR(VLOOKUP($A7,'ENTRADA 2024'!$1:$1048576,3 + (COLUMN(L4)-1)*1,FALSE),"")) | DM7: =IF(COUNT(DA7:DL7)=0,"",SUM(DA7:DL7)) | DN7: =IF(IFERROR(VLOOKUP($A7,'ENTRADA 2025'!$1:$1048576,3 + (COLUMN(A4)-1)*1,FALSE),"")=0,"",IFERROR(VLOOKUP($A7,'ENTRADA 2025'!$1:$1048576,3 + (COLUMN(A4)-1)*1,FALSE),"")) | DO7: =IF(IFERROR(VLOOKUP($A7,'ENTRADA 2025'!$1:$1048576,3 + (COLUMN(B4)-1)*1,FALSE),"")=0,"",IFERROR(VLOOKUP($A7,'ENTRADA 2025'!$1:$1048576,3 + (COLUMN(B4)-1)*1,FALSE),"")) | DP7: =IF(IFERROR(VLOOKUP($A7,'ENTRADA 2025'!$1:$1048576,3 + (COLUMN(C4)-1)*1,FALSE),"")=0,"",IFERROR(VLOOKUP($A7,'ENTRADA 2025'!$1:$1048576,3 + (COLUMN(C4)-1)*1,FALSE),"")) | DQ7: =IF(IFERROR(VLOOKUP($A7,'ENTRADA 2025'!$1:$1048576,3 + (COLUMN(D4)-1)*1,FALSE),"")=0,"",IFERROR(VLOOKUP($A7,'ENTRADA 2025'!$1:$1048576,3 + (COLUMN(D4)-1)*1,FALSE),"")) | DR7: =IF(IFERROR(VLOOKUP($A7,'ENTRADA 2025'!$1:$1048576,3 + (COLUMN(E4)-1)*1,FALSE),"")=0,"",IFERROR(VLOOKUP($A7,'ENTRADA 2025'!$1:$1048576,3 + (COLUMN(E4)-1)*1,FALSE),"")) | DS7: =IF(IFERROR(VLOOKUP($A7,'ENTRADA 2025'!$1:$1048576,3 + (COLUMN(F4)-1)*1,FALSE),"")=0,"",IFERROR(VLOOKUP($A7,'ENTRADA 2025'!$1:$1048576,3 + (COLUMN(F4)-1)*1,FALSE),"")) | DT7: =IF(IFERROR(VLOOKUP($A7,'ENTRADA 2025'!$1:$1048576,3 + (COLUMN(G4)-1)*1,FALSE),"")=0,"",IFERROR(VLOOKUP($A7,'ENTRADA 2025'!$1:$1048576,3 + (COLUMN(G4)-1)*1,FALSE),"")) | DU7: =IF(IFERROR(VLOOKUP($A7,'ENTRADA 2025'!$1:$1048576,3 + (COLUMN(H4)-1)*1,FALSE),"")=0,"",IFERROR(VLOOKUP($A7,'ENTRADA 2025'!$1:$1048576,3 + (COLUMN(H4)-1)*1,FALSE),"")) | ... DY7: =IF(IFERROR(VLOOKUP($A7,'ENTRADA 2025'!$1:$1048576,3 + (COLUMN(L4)-1)*1,FALSE),"")=0,"",IFERROR(VLOOKUP($A7,'ENTRADA 2025'!$1:$1048576,3 + (COLUMN(L4)-1)*1,FALSE),"")) | DZ7: =IF(COUNT(DN7:DY7)=0,"",SUM(DN7:DY7)) | EA7: =IF(IFERROR(VLOOKUP($A7,'entrada-fornecedor-12-meses-7'!$1:$1048576,3 + (COLUMN(A4)-1)*1,FALSE),"")=0,"",IFERROR(VLOOKUP($A7,'entrada-fornecedor-12-meses-7'!$1:$1048576,3 + (COLUMN(A4)-1)*1,FALSE),"")) | EB7: =IF(IFERROR(VLOOKUP($A7,'entrada-fornecedor-12-meses-7'!$1:$1048576,3 + (COLUMN(B4)-1)*1,FALSE),"")=0,"",IFERROR(VLOOKUP($A7,'entrada-fornecedor-12-meses-7'!$1:$1048576,3 + (COLUMN(B4)-1)*1,FALSE),"")) | EC7: =IF(IFERROR(VLOOKUP($A7,'entrada-fornecedor-12-meses-7'!$1:$1048576,3 + (COLUMN(C4)-1)*1,FALSE),"")=0,"",IFERROR(VLOOKUP($A7,'entrada-fornecedor-12-meses-7'!$1:$1048576,3 + (COLUMN(C4)-1)*1,FALSE),"")) | ED7: =IF(IFERROR(VLOOKUP($A7,'entrada-fornecedor-12-meses-7'!$1:$1048576,3 + (COLUMN(D4)-1)*1,FALSE),"")=0,"",IFERROR(VLOOKUP($A7,'entrada-fornecedor-12-meses-7'!$1:$1048576,3 + (COLUMN(D4)-1)*1,FALSE),"")) | EE7: =IF(IFERROR(VLOOKUP($A7,'entrada-fornecedor-12-meses-7'!$1:$1048576,3 + (COLUMN(E4)-1)*1,FALSE),"")=0,"",IFERROR(VLOOKUP($A7,'entrada-fornecedor-12-meses-7'!$1:$1048576,3 + (COLUMN(E4)-1)*1,FALSE),"")) | EF7: =IF(IFERROR(VLOOKUP($A7,'entrada-fornecedor-12-meses-7'!$1:$1048576,3 + (COLUMN(F4)-1)*1,FALSE),"")=0,"",IFERROR(VLOOKUP($A7,'entrada-fornecedor-12-meses-7'!$1:$1048576,3 + (COLUMN(F4)-1)*1,FALSE),"")) | EG7: =IF(IFERROR(VLOOKUP($A7,'entrada-fornecedor-12-meses-7'!$1:$1048576,3 + (COLUMN(G4)-1)*1,FALSE),"")=0,"",IFERROR(VLOOKUP($A7,'entrada-fornecedor-12-meses-7'!$1:$1048576,3 + (COLUMN(G4)-1)*1,FALSE),"")) | EH7: =IF(IFERROR(VLOOKUP($A7,'entrada-fornecedor-12-meses-7'!$1:$1048576,3 + (COLUMN(H4)-1)*1,FALSE),"")=0,"",IFERROR(VLOOKUP($A7,'entrada-fornecedor-12-meses-7'!$1:$1048576,3 + (COLUMN(H4)-1)*1,FALSE),"")) | ... EL7: =IF(IFERROR(VLOOKUP($A7,'entrada-fornecedor-12-meses-7'!$1:$1048576,3 + (COLUMN(L4)-1)*1,FALSE),"")=0,"",IFERROR(VLOOKUP($A7,'entrada-fornecedor-12-meses-7'!$1:$1048576,3 + (COLUMN(L4)-1)*1,FALSE),"")) | EM7: =IF(COUNT(EA7:EL7)=0,"",SUM(EA7:EL7)) | EO7: =IFERROR(AVERAGEIF('lead-time-compras-7'!B:B,A7,'lead-time-compras-7'!S:S),"") | EP7: =IFERROR( AVERAGEIFS( 'notas-fiscais-entrada-830-7'!H:H, 'notas-fiscais-entrada-830-7'!O:O, A7, 'notas-fiscais-entrada-830-7'!E:E, $B$1 ), "" ) | EQ7: =IFERROR(AVERAGEIF('lead-time-compras-7'!B:B,A7,'lead-time-compras-7'!Q:Q),"") | ER7: =SUMIF('fornecedor-saldo-receber-7'!A:A, A7, 'fornecedor-saldo-receber-7'!L:L) | ES7: =SUMIF('fornecedor-verba-aplicar-7'!A:A, A7, 'fornecedor-verba-aplicar-7'!D:D) | EU7: =SUMIF('ANALISE PRODUTO'!F:F, A7, 'ANALISE PRODUTO'!BN:BN) | EV7: =SUMIF('ANALISE PRODUTO'!F:F, A7, 'ANALISE PRODUTO'!BO:BO) | EW7: =SUMIF('ANALISE PRODUTO'!F:F, A7, 'ANALISE PRODUTO'!BP:BP) | EX7: =SUMIF('ANALISE PRODUTO'!F:F, A7, 'ANALISE PRODUTO'!BQ:BQ) | EY7: =SUMIF('ANALISE PRODUTO'!F:F, A7, 'ANALISE PRODUTO'!BR:BR) | EZ7: =SUMIF('ANALISE PRODUTO'!F:F, A7, 'ANALISE PRODUTO'!BS:BS) | FA7: =SUMIF('ANALISE PRODUTO'!F:F, A7, 'ANALISE PRODUTO'!BT:BT) | FB7: =SUMIF('ANALISE PRODUTO'!F:F, A7, 'ANALISE PRODUTO'!BU:BU) | FC7: =SUMIF('ANALISE PRODUTO'!F:F, A7, 'ANALISE PRODUTO'!BV:BV) | FD7: =SUMIF('ANALISE PRODUTO'!F:F, A7, 'ANALISE PRODUTO'!BW:BW) | FE7: =SUMIF('ANALISE PRODUTO'!F:F, A7, 'ANALISE PRODUTO'!CB:CB) | FF7: =SUMIF('ANALISE PRODUTO'!F:F, A7, 'ANALISE PRODUTO'!CC:CC) | FH7: =IF(IFERROR(VLOOKUP($A7,'VENDA 2023'!$1:$1048576,4 + (COLUMN(A4)-1)*2,FALSE),"")=0,"",IFERROR(VLOOKUP($A7,'VENDA 2023'!$1:$1048576,4 + (COLUMN(A4)-1)*2,FALSE),"")) | FI7: =IF(IFERROR(VLOOKUP($A7,'VENDA 2023'!$1:$1048576,4 + (COLUMN(B4)-1)*2,FALSE),"")=0,"",IFERROR(VLOOKUP($A7,'VENDA 2023'!$1:$1048576,4 + (COLUMN(B4)-1)*2,FALSE),"")) | FJ7: =IF(IFERROR(VLOOKUP($A7,'VENDA 2023'!$1:$1048576,4 + (COLUMN(C4)-1)*2,FALSE),"")=0,"",IFERROR(VLOOKUP($A7,'VENDA 2023'!$1:$1048576,4 + (COLUMN(C4)-1)*2,FALSE),"")) | FK7: =IF(IFERROR(VLOOKUP($A7,'VENDA 2023'!$1:$1048576,4 + (COLUMN(D4)-1)*2,FALSE),"")=0,"",IFERROR(VLOOKUP($A7,'VENDA 2023'!$1:$1048576,4 + (COLUMN(D4)-1)*2,FALSE),"")) | FL7: =IF(IFERROR(VLOOKUP($A7,'VENDA 2023'!$1:$1048576,4 + (COLUMN(E4)-1)*2,FALSE),"")=0,"",IFERROR(VLOOKUP($A7,'VENDA 2023'!$1:$1048576,4 + (COLUMN(E4)-1)*2,FALSE),"")) | FM7: =IF(IFERROR(VLOOKUP($A7,'VENDA 2023'!$1:$1048576,4 + (COLUMN(F4)-1)*2,FALSE),"")=0,"",IFERROR(VLOOKUP($A7,'VENDA 2023'!$1:$1048576,4 + (COLUMN(F4)-1)*2,FALSE),"")) | FN7: =IF(IFERROR(VLOOKUP($A7,'VENDA 2023'!$1:$1048576,4 + (COLUMN(G4)-1)*2,FALSE),"")=0,"",IFERROR(VLOOKUP($A7,'VENDA 2023'!$1:$1048576,4 + (COLUMN(G4)-1)*2,FALSE),"")) | FO7: =IF(IFERROR(VLOOKUP($A7,'VENDA 2023'!$1:$1048576,4 + (COLUMN(H4)-1)*2,FALSE),"")=0,"",IFERROR(VLOOKUP($A7,'VENDA 2023'!$1:$1048576,4 + (COLUMN(H4)-1)*2,FALSE),"")) | ... FS7: =IF(IFERROR(VLOOKUP($A7,'VENDA 2023'!$1:$1048576,4 + (COLUMN(L4)-1)*2,FALSE),"")=0,"",IFERROR(VLOOKUP($A7,'VENDA 2023'!$1:$1048576,4 + (COLUMN(L4)-1)*2,FALSE),"")) | FT7: =IF(COUNT(FH7:FS7)=0,"",SUM(FH7:FS7)) | FU7: =IF(IFERROR(VLOOKUP($A7,'VENDA 2024'!$1:$1048576,4 + (COLUMN(A4)-1)*2,FALSE),"")=0,"",IFERROR(VLOOKUP($A7,'VENDA 2024'!$1:$1048576,4 + (COLUMN(A4)-1)*2,FALSE),"")) | FV7: =IF(IFERROR(VLOOKUP($A7,'VENDA 2024'!$1:$1048576,4 + (COLUMN(B4)-1)*2,FALSE),"")=0,"",IFERROR(VLOOKUP($A7,'VENDA 2024'!$1:$1048576,4 + (COLUMN(B4)-1)*2,FALSE),"")) | FW7: =IF(IFERROR(VLOOKUP($A7,'VENDA 2024'!$1:$1048576,4 + (COLUMN(C4)-1)*2,FALSE),"")=0,"",IFERROR(VLOOKUP($A7,'VENDA 2024'!$1:$1048576,4 + (COLUMN(C4)-1)*2,FALSE),"")) | FX7: =IF(IFERROR(VLOOKUP($A7,'VENDA 2024'!$1:$1048576,4 + (COLUMN(D4)-1)*2,FALSE),"")=0,"",IFERROR(VLOOKUP($A7,'VENDA 2024'!$1:$1048576,4 + (COLUMN(D4)-1)*2,FALSE),"")) | FY7: =IF(IFERROR(VLOOKUP($A7,'VENDA 2024'!$1:$1048576,4 + (COLUMN(E4)-1)*2,FALSE),"")=0,"",IFERROR(VLOOKUP($A7,'VENDA 2024'!$1:$1048576,4 + (COLUMN(E4)-1)*2,FALSE),"")) | FZ7: =IF(IFERROR(VLOOKUP($A7,'VENDA 2024'!$1:$1048576,4 + (COLUMN(F4)-1)*2,FALSE),"")=0,"",IFERROR(VLOOKUP($A7,'VENDA 2024'!$1:$1048576,4 + (COLUMN(F4)-1)*2,FALSE),"")) | GA7: =IF(IFERROR(VLOOKUP($A7,'VENDA 2024'!$1:$1048576,4 + (COLUMN(G4)-1)*2,FALSE),"")=0,"",IFERROR(VLOOKUP($A7,'VENDA 2024'!$1:$1048576,4 + (COLUMN(G4)-1)*2,FALSE),"")) | GB7: =IF(IFERROR(VLOOKUP($A7,'VENDA 2024'!$1:$1048576,4 + (COLUMN(H4)-1)*2,FALSE),"")=0,"",IFERROR(VLOOKUP($A7,'VENDA 2024'!$1:$1048576,4 + (COLUMN(H4)-1)*2,FALSE),"")) | ... GF7: =IF(IFERROR(VLOOKUP($A7,'VENDA 2024'!$1:$1048576,4 + (COLUMN(L4)-1)*2,FALSE),"")=0,"",IFERROR(VLOOKUP($A7,'VENDA 2024'!$1:$1048576,4 + (COLUMN(L4)-1)*2,FALSE),"")) | GG7: =IF(COUNT(FU7:GF7)=0,"",SUM(FU7:GF7)) | GH7: =IF(IFERROR(VLOOKUP($A7,'venda-fornecedor-12-meses-7'!$1:$1048576,5 + (COLUMN(A4)-1)*2,FALSE),"")=0,"",IFERROR(VLOOKUP($A7,'venda-fornecedor-12-meses-7'!$1:$1048576,5 + (COLUMN(A4)-1)*2,FALSE),"")) | GI7: =IF(IFERROR(VLOOKUP($A7,'venda-fornecedor-12-meses-7'!$1:$1048576,5 + (COLUMN(B4)-1)*2,FALSE),"")=0,"",IFERROR(VLOOKUP($A7,'venda-fornecedor-12-meses-7'!$1:$1048576,5 + (COLUMN(B4)-1)*2,FALSE),"")) | GJ7: =IF(IFERROR(VLOOKUP($A7,'venda-fornecedor-12-meses-7'!$1:$1048576,5 + (COLUMN(C4)-1)*2,FALSE),"")=0,"",IFERROR(VLOOKUP($A7,'venda-fornecedor-12-meses-7'!$1:$1048576,5 + (COLUMN(C4)-1)*2,FALSE),"")) | GK7: =IF(IFERROR(VLOOKUP($A7,'venda-fornecedor-12-meses-7'!$1:$1048576,5 + (COLUMN(D4)-1)*2,FALSE),"")=0,"",IFERROR(VLOOKUP($A7,'venda-fornecedor-12-meses-7'!$1:$1048576,5 + (COLUMN(D4)-1)*2,FALSE),"")) | GL7: =IF(IFERROR(VLOOKUP($A7,'venda-fornecedor-12-meses-7'!$1:$1048576,5 + (COLUMN(E4)-1)*2,FALSE),"")=0,"",IFERROR(VLOOKUP($A7,'venda-fornecedor-12-meses-7'!$1:$1048576,5 + (COLUMN(E4)-1)*2,FALSE),"")) | GM7: =IF(IFERROR(VLOOKUP($A7,'venda-fornecedor-12-meses-7'!$1:$1048576,5 + (COLUMN(F4)-1)*2,FALSE),"")=0,"",IFERROR(VLOOKUP($A7,'venda-fornecedor-12-meses-7'!$1:$1048576,5 + (COLUMN(F4)-1)*2,FALSE),"")) | GN7: =IF(IFERROR(VLOOKUP($A7,'venda-fornecedor-12-meses-7'!$1:$1048576,5 + (COLUMN(G4)-1)*2,FALSE),"")=0,"",IFERROR(VLOOKUP($A7,'venda-fornecedor-12-meses-7'!$1:$1048576,5 + (COLUMN(G4)-1)*2,FALSE),"")) | GO7: =IF(IFERROR(VLOOKUP($A7,'venda-fornecedor-12-meses-7'!$1:$1048576,5 + (COLUMN(H4)-1)*2,FALSE),"")=0,"",IFERROR(VLOOKUP($A7,'venda-fornecedor-12-meses-7'!$1:$1048576,5 + (COLUMN(H4)-1)*2,FALSE),"")) | ... GS7: =IF(IFERROR(VLOOKUP($A7,'venda-fornecedor-12-meses-7'!$1:$1048576,5 + (COLUMN(L4)-1)*2,FALSE),"")=0,"",IFERROR(VLOOKUP($A7,'venda-fornecedor-12-meses-7'!$1:$1048576,5 + (COLUMN(L4)-1)*2,FALSE),"")) | GT7: =IF(COUNT(GH7:GS7)=0,"",SUM(GH7:GS7))
A8: 11743 | B8: =VLOOKUP(A8,'FORNECEDORES X COMPRADOR'!$A:$D,4,0) | C8: =VLOOKUP(A8,'FORNECEDORES X COMPRADOR'!$A:$E,5,0) | D8: =IFERROR(AVERAGEIF('ANALISE PRODUTO'!F:F,A8,'ANALISE PRODUTO'!BE:BE),"") | E8: =IFERROR(AVERAGEIF('ANALISE PRODUTO'!F:F,A8,'ANALISE PRODUTO'!BF:BF),"") | F8: {=IFERROR( IF( SUMPRODUCT( IFERROR(--('ANALISE PRODUTO'!$F$3:$F$10000=A8),0) * IFERROR(--'ANALISE PRODUTO'!$AJ$3:$AJ$10000,0) )=0, "", SUMPRODUCT( IFERROR(--('ANALISE PRODUTO'!$F$3:$F$10000=A8),0) * IFERROR(--'ANALISE PRODUTO'!$AN$3:$AN$10000,0) ) / SUMPRODUCT( IFERROR(--('ANALISE PRODUTO'!$F$3:$F$10000=A8),0) * IFERROR(--'ANALISE PRODUTO'!$AJ$3:$AJ$10000,0) ) ), "" )} | G8: {=IFERROR( IF( SUMPRODUCT( IFERROR(--('ANALISE PRODUTO'!$F$3:$F$10000=A8),0) * IFERROR(--'ANALISE PRODUTO'!$AJ$3:$AJ$10000,0) )=0, "", SUMPRODUCT( IFERROR(--('ANALISE PRODUTO'!$F$3:$F$10000=A8),0) * IFERROR(--'ANALISE PRODUTO'!$AO$3:$AO$10000,0) ) / SUMPRODUCT( IFERROR(--('ANALISE PRODUTO'!$F$3:$F$10000=A8),0) * IFERROR(--'ANALISE PRODUTO'!$AJ$3:$AJ$10000,0) ) ), "" )} | H8: 60 | I8: 90 | J8: =SUMIF('ANALISE PRODUTO'!F:F, A8, 'ANALISE PRODUTO'!AP:AP) | K8: =SUMIF('ANALISE PRODUTO'!F:F, A8, 'ANALISE PRODUTO'!AN:AN) | L8: =SUMIF('ANALISE PRODUTO'!F:F, A8, 'ANALISE PRODUTO'!BB:BB) | M8: =SUMIF('ANALISE PRODUTO'!F:F, A8, 'ANALISE PRODUTO'!BC:BC) | N8: =SUMIF('ANALISE PRODUTO'!F:F, A8, 'ANALISE PRODUTO'!BD:BD) | O8: =SUMIF('ANALISE PRODUTO'!F:F, A8, 'ANALISE PRODUTO'!BA:BA) | P8: =IF(J8=0, 0, IF(O8/J8=0, 0, O8/J8)) | Q8: =IF(J8=0, 0, IF(L8/J8=0, 0, L8/J8)) | R8: =SUMIF('ANALISE PRODUTO'!F:F, A8, 'ANALISE PRODUTO'!BJ:BJ) | S8: =SUMIF('ANALISE PRODUTO'!F:F, A8, 'ANALISE PRODUTO'!BK:BK) | T8: =SUMIF('ANALISE PRODUTO'!F:F, A8, 'ANALISE PRODUTO'!BL:BL) | U8: =SUMIFS('ANALISE PRODUTO'!BI:BI, 'ANALISE PRODUTO'!F:F, A8) | V8: =IF(C8="DESCONTINUADO", 0, IF(J8=0, 0, IF(U8/J8=0, 0, U8/J8))) | W8: =IF(OR(C8="DESCONTINUADO", J8=0), 0, IFERROR((S8+T8)/J8, 0)) | X8: =COUNTIF('ANALISE PRODUTO'!F:F, A8) | Y8: =COUNTIFS('ANALISE PRODUTO'!F:F, A8, 'ANALISE PRODUTO'!S:S, "S") | Z8: =X8-Y8 | AA8: =IFERROR(IF(COUNTIF('contas-pagas-fornecedor-7'!$C:$C,B8)>1, AVERAGEIF('contas-pagas-fornecedor-7'!$C:$C,B8,'contas-pagas-fornecedor-7'!$I:$I), VLOOKUP(B8,'contas-pagas-fornecedor-7'!$C:$Q,7,FALSE)), "") | AB8: {=IFERROR( INDEX('fornecedor-venda-por-filial-ger'!J:J, MATCH(1, ('fornecedor-venda-por-filial-ger'!A:A=A8) * ('fornecedor-venda-por-filial-ger'!B:B=$B$1), 0) ), "")} | AC8: {=IFERROR( INDEX('fornecedor-venda-por-filial-ger'!O:O, MATCH(1, ('fornecedor-venda-por-filial-ger'!A:A=A8) * ('fornecedor-venda-por-filial-ger'!B:B=$B$1), 0) ), "")} | AD8: =IFERROR(VLOOKUP(A8,'venda-fornecedor-12-meses-7'!A:AC,3,0),"") | AE8: {=IFERROR( INDEX('fornecedor-venda-por-filial-ger'!N:N, MATCH(1, ('fornecedor-venda-por-filial-ger'!A:A=A8) * ('fornecedor-venda-por-filial-ger'!B:B=$B$1), 0) ), "")} | AF8: =IF(J8<=0,"100,00%",IFERROR(AD8/AE8,1)) | AG8: {=IFERROR( INDEX('fornecedor-venda-por-filial-ger'!L:L, MATCH(1, ('fornecedor-venda-por-filial-ger'!A:A=A8)* ('fornecedor-venda-por-filial-ger'!B:B=$B$1), 0) )/100, "")} | AH8: {=IFERROR( INDEX('fornecedor-venda-por-filial-ger'!S:S, MATCH(1, ('fornecedor-venda-por-filial-ger'!A:A=A8) * ('fornecedor-venda-por-filial-ger'!B:B=$B$1), 0) )/100, "")} | AI8: =IFERROR(IF(OR(AH8="",AG8=""),"",IF(J8=0,0,AH8-AG8)),"") | AJ8: {=IF(MAX(IF('ANALISE PRODUTO'!F:F=A8,'ANALISE PRODUTO'!AD:AD))=0,"SEM ENTRADA",MAX(IF('ANALISE PRODUTO'!F:F=A8,'ANALISE PRODUTO'!AD:AD)))} | AL8: =IF(IFERROR(VLOOKUP($A8,'VENDA 2023'!$1:$1048576,3 + (COLUMN(A5)-1)*2,FALSE),"")=0,"",IFERROR(VLOOKUP($A8,'VENDA 2023'!$1:$1048576,3 + (COLUMN(A5)-1)*2,FALSE),"")) | AM8: =IF(IFERROR(VLOOKUP($A8,'VENDA 2023'!$1:$1048576,3 + (COLUMN(B5)-1)*2,FALSE),"")=0,"",IFERROR(VLOOKUP($A8,'VENDA 2023'!$1:$1048576,3 + (COLUMN(B5)-1)*2,FALSE),"")) | AN8: =IF(IFERROR(VLOOKUP($A8,'VENDA 2023'!$1:$1048576,3 + (COLUMN(C5)-1)*2,FALSE),"")=0,"",IFERROR(VLOOKUP($A8,'VENDA 2023'!$1:$1048576,3 + (COLUMN(C5)-1)*2,FALSE),"")) | AO8: =IF(IFERROR(VLOOKUP($A8,'VENDA 2023'!$1:$1048576,3 + (COLUMN(D5)-1)*2,FALSE),"")=0,"",IFERROR(VLOOKUP($A8,'VENDA 2023'!$1:$1048576,3 + (COLUMN(D5)-1)*2,FALSE),"")) | AP8: =IF(IFERROR(VLOOKUP($A8,'VENDA 2023'!$1:$1048576,3 + (COLUMN(E5)-1)*2,FALSE),"")=0,"",IFERROR(VLOOKUP($A8,'VENDA 2023'!$1:$1048576,3 + (COLUMN(E5)-1)*2,FALSE),"")) | AQ8: =IF(IFERROR(VLOOKUP($A8,'VENDA 2023'!$1:$1048576,3 + (COLUMN(F5)-1)*2,FALSE),"")=0,"",IFERROR(VLOOKUP($A8,'VENDA 2023'!$1:$1048576,3 + (COLUMN(F5)-1)*2,FALSE),"")) | AR8: =IF(IFERROR(VLOOKUP($A8,'VENDA 2023'!$1:$1048576,3 + (COLUMN(G5)-1)*2,FALSE),"")=0,"",IFERROR(VLOOKUP($A8,'VENDA 2023'!$1:$1048576,3 + (COLUMN(G5)-1)*2,FALSE),"")) | AS8: =IF(IFERROR(VLOOKUP($A8,'VENDA 2023'!$1:$1048576,3 + (COLUMN(H5)-1)*2,FALSE),"")=0,"",IFERROR(VLOOKUP($A8,'VENDA 2023'!$1:$1048576,3 + (COLUMN(H5)-1)*2,FALSE),"")) | ... AW8: =IF(IFERROR(VLOOKUP($A8,'VENDA 2023'!$1:$1048576,3 + (COLUMN(L5)-1)*2,FALSE),"")=0,"",IFERROR(VLOOKUP($A8,'VENDA 2023'!$1:$1048576,3 + (COLUMN(L5)-1)*2,FALSE),"")) | AX8: =IF(COUNT(AL8:AW8)=0,"",SUM(AL8:AW8)) | AY8: =IF(IFERROR(VLOOKUP($A8,'VENDA 2024'!$1:$1048576,3 + (COLUMN(A5)-1)*2,FALSE),"")=0,"",IFERROR(VLOOKUP($A8,'VENDA 2024'!$1:$1048576,3 + (COLUMN(A5)-1)*2,FALSE),"")) | AZ8: =IF(IFERROR(VLOOKUP($A8,'VENDA 2024'!$1:$1048576,3 + (COLUMN(B5)-1)*2,FALSE),"")=0,"",IFERROR(VLOOKUP($A8,'VENDA 2024'!$1:$1048576,3 + (COLUMN(B5)-1)*2,FALSE),"")) | BA8: =IF(IFERROR(VLOOKUP($A8,'VENDA 2024'!$1:$1048576,3 + (COLUMN(C5)-1)*2,FALSE),"")=0,"",IFERROR(VLOOKUP($A8,'VENDA 2024'!$1:$1048576,3 + (COLUMN(C5)-1)*2,FALSE),"")) | BB8: =IF(IFERROR(VLOOKUP($A8,'VENDA 2024'!$1:$1048576,3 + (COLUMN(D5)-1)*2,FALSE),"")=0,"",IFERROR(VLOOKUP($A8,'VENDA 2024'!$1:$1048576,3 + (COLUMN(D5)-1)*2,FALSE),"")) | BC8: =IF(IFERROR(VLOOKUP($A8,'VENDA 2024'!$1:$1048576,3 + (COLUMN(E5)-1)*2,FALSE),"")=0,"",IFERROR(VLOOKUP($A8,'VENDA 2024'!$1:$1048576,3 + (COLUMN(E5)-1)*2,FALSE),"")) | BD8: =IF(IFERROR(VLOOKUP($A8,'VENDA 2024'!$1:$1048576,3 + (COLUMN(F5)-1)*2,FALSE),"")=0,"",IFERROR(VLOOKUP($A8,'VENDA 2024'!$1:$1048576,3 + (COLUMN(F5)-1)*2,FALSE),"")) | BE8: =IF(IFERROR(VLOOKUP($A8,'VENDA 2024'!$1:$1048576,3 + (COLUMN(G5)-1)*2,FALSE),"")=0,"",IFERROR(VLOOKUP($A8,'VENDA 2024'!$1:$1048576,3 + (COLUMN(G5)-1)*2,FALSE),"")) | BF8: =IF(IFERROR(VLOOKUP($A8,'VENDA 2024'!$1:$1048576,3 + (COLUMN(H5)-1)*2,FALSE),"")=0,"",IFERROR(VLOOKUP($A8,'VENDA 2024'!$1:$1048576,3 + (COLUMN(H5)-1)*2,FALSE),"")) | ... BJ8: =IF(IFERROR(VLOOKUP($A8,'VENDA 2024'!$1:$1048576,3 + (COLUMN(L5)-1)*2,FALSE),"")=0,"",IFERROR(VLOOKUP($A8,'VENDA 2024'!$1:$1048576,3 + (COLUMN(L5)-1)*2,FALSE),"")) | BK8: =IF(COUNT(AY8:BJ8)=0,"",SUM(AY8:BJ8)) | BL8: =IF(IFERROR(VLOOKUP($A8,'VENDA 2025'!$1:$1048576,3 + (COLUMN(A5)-1)*2,FALSE),"")=0,"",IFERROR(VLOOKUP($A8,'VENDA 2025'!$1:$1048576,3 + (COLUMN(A5)-1)*2,FALSE),"")) | BM8: =IF(IFERROR(VLOOKUP($A8,'VENDA 2025'!$1:$1048576,3 + (COLUMN(B5)-1)*2,FALSE),"")=0,"",IFERROR(VLOOKUP($A8,'VENDA 2025'!$1:$1048576,3 + (COLUMN(B5)-1)*2,FALSE),"")) | BN8: =IF(IFERROR(VLOOKUP($A8,'VENDA 2025'!$1:$1048576,3 + (COLUMN(C5)-1)*2,FALSE),"")=0,"",IFERROR(VLOOKUP($A8,'VENDA 2025'!$1:$1048576,3 + (COLUMN(C5)-1)*2,FALSE),"")) | BO8: =IF(IFERROR(VLOOKUP($A8,'VENDA 2025'!$1:$1048576,3 + (COLUMN(D5)-1)*2,FALSE),"")=0,"",IFERROR(VLOOKUP($A8,'VENDA 2025'!$1:$1048576,3 + (COLUMN(D5)-1)*2,FALSE),"")) | BP8: =IF(IFERROR(VLOOKUP($A8,'VENDA 2025'!$1:$1048576,3 + (COLUMN(E5)-1)*2,FALSE),"")=0,"",IFERROR(VLOOKUP($A8,'VENDA 2025'!$1:$1048576,3 + (COLUMN(E5)-1)*2,FALSE),"")) | BQ8: =IF(IFERROR(VLOOKUP($A8,'VENDA 2025'!$1:$1048576,3 + (COLUMN(F5)-1)*2,FALSE),"")=0,"",IFERROR(VLOOKUP($A8,'VENDA 2025'!$1:$1048576,3 + (COLUMN(F5)-1)*2,FALSE),"")) | BR8: =IF(IFERROR(VLOOKUP($A8,'VENDA 2025'!$1:$1048576,3 + (COLUMN(G5)-1)*2,FALSE),"")=0,"",IFERROR(VLOOKUP($A8,'VENDA 2025'!$1:$1048576,3 + (COLUMN(G5)-1)*2,FALSE),"")) | BS8: =IF(IFERROR(VLOOKUP($A8,'VENDA 2025'!$1:$1048576,3 + (COLUMN(H5)-1)*2,FALSE),"")=0,"",IFERROR(VLOOKUP($A8,'VENDA 2025'!$1:$1048576,3 + (COLUMN(H5)-1)*2,FALSE),"")) | ... BW8: =IF(IFERROR(VLOOKUP($A8,'VENDA 2025'!$1:$1048576,3 + (COLUMN(L5)-1)*2,FALSE),"")=0,"",IFERROR(VLOOKUP($A8,'VENDA 2025'!$1:$1048576,3 + (COLUMN(L5)-1)*2,FALSE),"")) | BX8: =IF(COUNT(BL8:BW8)=0,"",SUM(BL8:BW8)) | BY8: =IF(IFERROR(VLOOKUP($A8,'venda-fornecedor-12-meses-7'!$1:$1048576,4 + (COLUMN(A5)-1)*2,FALSE),"")=0,"",IFERROR(VLOOKUP($A8,'venda-fornecedor-12-meses-7'!$1:$1048576,4 + (COLUMN(A5)-1)*2,FALSE),"")) | BZ8: =IF(IFERROR(VLOOKUP($A8,'venda-fornecedor-12-meses-7'!$1:$1048576,4 + (COLUMN(B5)-1)*2,FALSE),"")=0,"",IFERROR(VLOOKUP($A8,'venda-fornecedor-12-meses-7'!$1:$1048576,4 + (COLUMN(B5)-1)*2,FALSE),"")) | CA8: =IF(IFERROR(VLOOKUP($A8,'venda-fornecedor-12-meses-7'!$1:$1048576,4 + (COLUMN(C5)-1)*2,FALSE),"")=0,"",IFERROR(VLOOKUP($A8,'venda-fornecedor-12-meses-7'!$1:$1048576,4 + (COLUMN(C5)-1)*2,FALSE),"")) | CB8: =IF(IFERROR(VLOOKUP($A8,'venda-fornecedor-12-meses-7'!$1:$1048576,4 + (COLUMN(D5)-1)*2,FALSE),"")=0,"",IFERROR(VLOOKUP($A8,'venda-fornecedor-12-meses-7'!$1:$1048576,4 + (COLUMN(D5)-1)*2,FALSE),"")) | CC8: =IF(IFERROR(VLOOKUP($A8,'venda-fornecedor-12-meses-7'!$1:$1048576,4 + (COLUMN(E5)-1)*2,FALSE),"")=0,"",IFERROR(VLOOKUP($A8,'venda-fornecedor-12-meses-7'!$1:$1048576,4 + (COLUMN(E5)-1)*2,FALSE),"")) | CD8: =IF(IFERROR(VLOOKUP($A8,'venda-fornecedor-12-meses-7'!$1:$1048576,4 + (COLUMN(F5)-1)*2,FALSE),"")=0,"",IFERROR(VLOOKUP($A8,'venda-fornecedor-12-meses-7'!$1:$1048576,4 + (COLUMN(F5)-1)*2,FALSE),"")) | CE8: =IF(IFERROR(VLOOKUP($A8,'venda-fornecedor-12-meses-7'!$1:$1048576,4 + (COLUMN(G5)-1)*2,FALSE),"")=0,"",IFERROR(VLOOKUP($A8,'venda-fornecedor-12-meses-7'!$1:$1048576,4 + (COLUMN(G5)-1)*2,FALSE),"")) | CF8: =IF(IFERROR(VLOOKUP($A8,'venda-fornecedor-12-meses-7'!$1:$1048576,4 + (COLUMN(H5)-1)*2,FALSE),"")=0,"",IFERROR(VLOOKUP($A8,'venda-fornecedor-12-meses-7'!$1:$1048576,4 + (COLUMN(H5)-1)*2,FALSE),"")) | ... CJ8: =IF(IFERROR(VLOOKUP($A8,'venda-fornecedor-12-meses-7'!$1:$1048576,4 + (COLUMN(L5)-1)*2,FALSE),"")=0,"",IFERROR(VLOOKUP($A8,'venda-fornecedor-12-meses-7'!$1:$1048576,4 + (COLUMN(L5)-1)*2,FALSE),"")) | CK8: =IF(COUNT(BY8:CJ8)=0,"",SUM(BY8:CJ8)) | CL8: =IF(COUNT(BY8:CJ8)=0,"",AVERAGE(BY8:CJ8)) | CN8: =IF(IFERROR(VLOOKUP($A8,'ENTRADA 2023'!$1:$1048576,3 + (COLUMN(A5)-1)*1,FALSE),"")=0,"",IFERROR(VLOOKUP($A8,'ENTRADA 2023'!$1:$1048576,3 + (COLUMN(A5)-1)*1,FALSE),"")) | CO8: =IF(IFERROR(VLOOKUP($A8,'ENTRADA 2023'!$1:$1048576,3 + (COLUMN(B5)-1)*1,FALSE),"")=0,"",IFERROR(VLOOKUP($A8,'ENTRADA 2023'!$1:$1048576,3 + (COLUMN(B5)-1)*1,FALSE),"")) | CP8: =IF(IFERROR(VLOOKUP($A8,'ENTRADA 2023'!$1:$1048576,3 + (COLUMN(C5)-1)*1,FALSE),"")=0,"",IFERROR(VLOOKUP($A8,'ENTRADA 2023'!$1:$1048576,3 + (COLUMN(C5)-1)*1,FALSE),"")) | CQ8: =IF(IFERROR(VLOOKUP($A8,'ENTRADA 2023'!$1:$1048576,3 + (COLUMN(D5)-1)*1,FALSE),"")=0,"",IFERROR(VLOOKUP($A8,'ENTRADA 2023'!$1:$1048576,3 + (COLUMN(D5)-1)*1,FALSE),"")) | CR8: =IF(IFERROR(VLOOKUP($A8,'ENTRADA 2023'!$1:$1048576,3 + (COLUMN(E5)-1)*1,FALSE),"")=0,"",IFERROR(VLOOKUP($A8,'ENTRADA 2023'!$1:$1048576,3 + (COLUMN(E5)-1)*1,FALSE),"")) | CS8: =IF(IFERROR(VLOOKUP($A8,'ENTRADA 2023'!$1:$1048576,3 + (COLUMN(F5)-1)*1,FALSE),"")=0,"",IFERROR(VLOOKUP($A8,'ENTRADA 2023'!$1:$1048576,3 + (COLUMN(F5)-1)*1,FALSE),"")) | CT8: =IF(IFERROR(VLOOKUP($A8,'ENTRADA 2023'!$1:$1048576,3 + (COLUMN(G5)-1)*1,FALSE),"")=0,"",IFERROR(VLOOKUP($A8,'ENTRADA 2023'!$1:$1048576,3 + (COLUMN(G5)-1)*1,FALSE),"")) | CU8: =IF(IFERROR(VLOOKUP($A8,'ENTRADA 2023'!$1:$1048576,3 + (COLUMN(H5)-1)*1,FALSE),"")=0,"",IFERROR(VLOOKUP($A8,'ENTRADA 2023'!$1:$1048576,3 + (COLUMN(H5)-1)*1,FALSE),"")) | ... CY8: =IF(IFERROR(VLOOKUP($A8,'ENTRADA 2023'!$1:$1048576,3 + (COLUMN(L5)-1)*1,FALSE),"")=0,"",IFERROR(VLOOKUP($A8,'ENTRADA 2023'!$1:$1048576,3 + (COLUMN(L5)-1)*1,FALSE),"")) | CZ8: =IF(COUNT(CN8:CY8)=0,"",SUM(CN8:CY8)) | DA8: =IF(IFERROR(VLOOKUP($A8,'ENTRADA 2024'!$1:$1048576,3 + (COLUMN(A5)-1)*1,FALSE),"")=0,"",IFERROR(VLOOKUP($A8,'ENTRADA 2024'!$1:$1048576,3 + (COLUMN(A5)-1)*1,FALSE),"")) | DB8: =IF(IFERROR(VLOOKUP($A8,'ENTRADA 2024'!$1:$1048576,3 + (COLUMN(B5)-1)*1,FALSE),"")=0,"",IFERROR(VLOOKUP($A8,'ENTRADA 2024'!$1:$1048576,3 + (COLUMN(B5)-1)*1,FALSE),"")) | DC8: =IF(IFERROR(VLOOKUP($A8,'ENTRADA 2024'!$1:$1048576,3 + (COLUMN(C5)-1)*1,FALSE),"")=0,"",IFERROR(VLOOKUP($A8,'ENTRADA 2024'!$1:$1048576,3 + (COLUMN(C5)-1)*1,FALSE),"")) | DD8: =IF(IFERROR(VLOOKUP($A8,'ENTRADA 2024'!$1:$1048576,3 + (COLUMN(D5)-1)*1,FALSE),"")=0,"",IFERROR(VLOOKUP($A8,'ENTRADA 2024'!$1:$1048576,3 + (COLUMN(D5)-1)*1,FALSE),"")) | DE8: =IF(IFERROR(VLOOKUP($A8,'ENTRADA 2024'!$1:$1048576,3 + (COLUMN(E5)-1)*1,FALSE),"")=0,"",IFERROR(VLOOKUP($A8,'ENTRADA 2024'!$1:$1048576,3 + (COLUMN(E5)-1)*1,FALSE),"")) | DF8: =IF(IFERROR(VLOOKUP($A8,'ENTRADA 2024'!$1:$1048576,3 + (COLUMN(F5)-1)*1,FALSE),"")=0,"",IFERROR(VLOOKUP($A8,'ENTRADA 2024'!$1:$1048576,3 + (COLUMN(F5)-1)*1,FALSE),"")) | DG8: =IF(IFERROR(VLOOKUP($A8,'ENTRADA 2024'!$1:$1048576,3 + (COLUMN(G5)-1)*1,FALSE),"")=0,"",IFERROR(VLOOKUP($A8,'ENTRADA 2024'!$1:$1048576,3 + (COLUMN(G5)-1)*1,FALSE),"")) | DH8: =IF(IFERROR(VLOOKUP($A8,'ENTRADA 2024'!$1:$1048576,3 + (COLUMN(H5)-1)*1,FALSE),"")=0,"",IFERROR(VLOOKUP($A8,'ENTRADA 2024'!$1:$1048576,3 + (COLUMN(H5)-1)*1,FALSE),"")) | ... DL8: =IF(IFERROR(VLOOKUP($A8,'ENTRADA 2024'!$1:$1048576,3 + (COLUMN(L5)-1)*1,FALSE),"")=0,"",IFERROR(VLOOKUP($A8,'ENTRADA 2024'!$1:$1048576,3 + (COLUMN(L5)-1)*1,FALSE),"")) | DM8: =IF(COUNT(DA8:DL8)=0,"",SUM(DA8:DL8)) | DN8: =IF(IFERROR(VLOOKUP($A8,'ENTRADA 2025'!$1:$1048576,3 + (COLUMN(A5)-1)*1,FALSE),"")=0,"",IFERROR(VLOOKUP($A8,'ENTRADA 2025'!$1:$1048576,3 + (COLUMN(A5)-1)*1,FALSE),"")) | DO8: =IF(IFERROR(VLOOKUP($A8,'ENTRADA 2025'!$1:$1048576,3 + (COLUMN(B5)-1)*1,FALSE),"")=0,"",IFERROR(VLOOKUP($A8,'ENTRADA 2025'!$1:$1048576,3 + (COLUMN(B5)-1)*1,FALSE),"")) | DP8: =IF(IFERROR(VLOOKUP($A8,'ENTRADA 2025'!$1:$1048576,3 + (COLUMN(C5)-1)*1,FALSE),"")=0,"",IFERROR(VLOOKUP($A8,'ENTRADA 2025'!$1:$1048576,3 + (COLUMN(C5)-1)*1,FALSE),"")) | DQ8: =IF(IFERROR(VLOOKUP($A8,'ENTRADA 2025'!$1:$1048576,3 + (COLUMN(D5)-1)*1,FALSE),"")=0,"",IFERROR(VLOOKUP($A8,'ENTRADA 2025'!$1:$1048576,3 + (COLUMN(D5)-1)*1,FALSE),"")) | DR8: =IF(IFERROR(VLOOKUP($A8,'ENTRADA 2025'!$1:$1048576,3 + (COLUMN(E5)-1)*1,FALSE),"")=0,"",IFERROR(VLOOKUP($A8,'ENTRADA 2025'!$1:$1048576,3 + (COLUMN(E5)-1)*1,FALSE),"")) | DS8: =IF(IFERROR(VLOOKUP($A8,'ENTRADA 2025'!$1:$1048576,3 + (COLUMN(F5)-1)*1,FALSE),"")=0,"",IFERROR(VLOOKUP($A8,'ENTRADA 2025'!$1:$1048576,3 + (COLUMN(F5)-1)*1,FALSE),"")) | DT8: =IF(IFERROR(VLOOKUP($A8,'ENTRADA 2025'!$1:$1048576,3 + (COLUMN(G5)-1)*1,FALSE),"")=0,"",IFERROR(VLOOKUP($A8,'ENTRADA 2025'!$1:$1048576,3 + (COLUMN(G5)-1)*1,FALSE),"")) | DU8: =IF(IFERROR(VLOOKUP($A8,'ENTRADA 2025'!$1:$1048576,3 + (COLUMN(H5)-1)*1,FALSE),"")=0,"",IFERROR(VLOOKUP($A8,'ENTRADA 2025'!$1:$1048576,3 + (COLUMN(H5)-1)*1,FALSE),"")) | ... DY8: =IF(IFERROR(VLOOKUP($A8,'ENTRADA 2025'!$1:$1048576,3 + (COLUMN(L5)-1)*1,FALSE),"")=0,"",IFERROR(VLOOKUP($A8,'ENTRADA 2025'!$1:$1048576,3 + (COLUMN(L5)-1)*1,FALSE),"")) | DZ8: =IF(COUNT(DN8:DY8)=0,"",SUM(DN8:DY8)) | EA8: =IF(IFERROR(VLOOKUP($A8,'entrada-fornecedor-12-meses-7'!$1:$1048576,3 + (COLUMN(A5)-1)*1,FALSE),"")=0,"",IFERROR(VLOOKUP($A8,'entrada-fornecedor-12-meses-7'!$1:$1048576,3 + (COLUMN(A5)-1)*1,FALSE),"")) | EB8: =IF(IFERROR(VLOOKUP($A8,'entrada-fornecedor-12-meses-7'!$1:$1048576,3 + (COLUMN(B5)-1)*1,FALSE),"")=0,"",IFERROR(VLOOKUP($A8,'entrada-fornecedor-12-meses-7'!$1:$1048576,3 + (COLUMN(B5)-1)*1,FALSE),"")) | EC8: =IF(IFERROR(VLOOKUP($A8,'entrada-fornecedor-12-meses-7'!$1:$1048576,3 + (COLUMN(C5)-1)*1,FALSE),"")=0,"",IFERROR(VLOOKUP($A8,'entrada-fornecedor-12-meses-7'!$1:$1048576,3 + (COLUMN(C5)-1)*1,FALSE),"")) | ED8: =IF(IFERROR(VLOOKUP($A8,'entrada-fornecedor-12-meses-7'!$1:$1048576,3 + (COLUMN(D5)-1)*1,FALSE),"")=0,"",IFERROR(VLOOKUP($A8,'entrada-fornecedor-12-meses-7'!$1:$1048576,3 + (COLUMN(D5)-1)*1,FALSE),"")) | EE8: =IF(IFERROR(VLOOKUP($A8,'entrada-fornecedor-12-meses-7'!$1:$1048576,3 + (COLUMN(E5)-1)*1,FALSE),"")=0,"",IFERROR(VLOOKUP($A8,'entrada-fornecedor-12-meses-7'!$1:$1048576,3 + (COLUMN(E5)-1)*1,FALSE),"")) | EF8: =IF(IFERROR(VLOOKUP($A8,'entrada-fornecedor-12-meses-7'!$1:$1048576,3 + (COLUMN(F5)-1)*1,FALSE),"")=0,"",IFERROR(VLOOKUP($A8,'entrada-fornecedor-12-meses-7'!$1:$1048576,3 + (COLUMN(F5)-1)*1,FALSE),"")) | EG8: =IF(IFERROR(VLOOKUP($A8,'entrada-fornecedor-12-meses-7'!$1:$1048576,3 + (COLUMN(G5)-1)*1,FALSE),"")=0,"",IFERROR(VLOOKUP($A8,'entrada-fornecedor-12-meses-7'!$1:$1048576,3 + (COLUMN(G5)-1)*1,FALSE),"")) | EH8: =IF(IFERROR(VLOOKUP($A8,'entrada-fornecedor-12-meses-7'!$1:$1048576,3 + (COLUMN(H5)-1)*1,FALSE),"")=0,"",IFERROR(VLOOKUP($A8,'entrada-fornecedor-12-meses-7'!$1:$1048576,3 + (COLUMN(H5)-1)*1,FALSE),"")) | ... EL8: =IF(IFERROR(VLOOKUP($A8,'entrada-fornecedor-12-meses-7'!$1:$1048576,3 + (COLUMN(L5)-1)*1,FALSE),"")=0,"",IFERROR(VLOOKUP($A8,'entrada-fornecedor-12-meses-7'!$1:$1048576,3 + (COLUMN(L5)-1)*1,FALSE),"")) | EM8: =IF(COUNT(EA8:EL8)=0,"",SUM(EA8:EL8)) | EO8: =IFERROR(AVERAGEIF('lead-time-compras-7'!B:B,A8,'lead-time-compras-7'!S:S),"") | EP8: =IFERROR( AVERAGEIFS( 'notas-fiscais-entrada-830-7'!H:H, 'notas-fiscais-entrada-830-7'!O:O, A8, 'notas-fiscais-entrada-830-7'!E:E, $B$1 ), "" ) | EQ8: =IFERROR(AVERAGEIF('lead-time-compras-7'!B:B,A8,'lead-time-compras-7'!Q:Q),"") | ER8: =SUMIF('fornecedor-saldo-receber-7'!A:A, A8, 'fornecedor-saldo-receber-7'!L:L) | ES8: =SUMIF('fornecedor-verba-aplicar-7'!A:A, A8, 'fornecedor-verba-aplicar-7'!D:D) | EU8: =SUMIF('ANALISE PRODUTO'!F:F, A8, 'ANALISE PRODUTO'!BN:BN) | EV8: =SUMIF('ANALISE PRODUTO'!F:F, A8, 'ANALISE PRODUTO'!BO:BO) | EW8: =SUMIF('ANALISE PRODUTO'!F:F, A8, 'ANALISE PRODUTO'!BP:BP) | EX8: =SUMIF('ANALISE PRODUTO'!F:F, A8, 'ANALISE PRODUTO'!BQ:BQ) | EY8: =SUMIF('ANALISE PRODUTO'!F:F, A8, 'ANALISE PRODUTO'!BR:BR) | EZ8: =SUMIF('ANALISE PRODUTO'!F:F, A8, 'ANALISE PRODUTO'!BS:BS) | FA8: =SUMIF('ANALISE PRODUTO'!F:F, A8, 'ANALISE PRODUTO'!BT:BT) | FB8: =SUMIF('ANALISE PRODUTO'!F:F, A8, 'ANALISE PRODUTO'!BU:BU) | FC8: =SUMIF('ANALISE PRODUTO'!F:F, A8, 'ANALISE PRODUTO'!BV:BV) | FD8: =SUMIF('ANALISE PRODUTO'!F:F, A8, 'ANALISE PRODUTO'!BW:BW) | FE8: =SUMIF('ANALISE PRODUTO'!F:F, A8, 'ANALISE PRODUTO'!CB:CB) | FF8: =SUMIF('ANALISE PRODUTO'!F:F, A8, 'ANALISE PRODUTO'!CC:CC) | FH8: =IF(IFERROR(VLOOKUP($A8,'VENDA 2023'!$1:$1048576,4 + (COLUMN(A5)-1)*2,FALSE),"")=0,"",IFERROR(VLOOKUP($A8,'VENDA 2023'!$1:$1048576,4 + (COLUMN(A5)-1)*2,FALSE),"")) | FI8: =IF(IFERROR(VLOOKUP($A8,'VENDA 2023'!$1:$1048576,4 + (COLUMN(B5)-1)*2,FALSE),"")=0,"",IFERROR(VLOOKUP($A8,'VENDA 2023'!$1:$1048576,4 + (COLUMN(B5)-1)*2,FALSE),"")) | FJ8: =IF(IFERROR(VLOOKUP($A8,'VENDA 2023'!$1:$1048576,4 + (COLUMN(C5)-1)*2,FALSE),"")=0,"",IFERROR(VLOOKUP($A8,'VENDA 2023'!$1:$1048576,4 + (COLUMN(C5)-1)*2,FALSE),"")) | FK8: =IF(IFERROR(VLOOKUP($A8,'VENDA 2023'!$1:$1048576,4 + (COLUMN(D5)-1)*2,FALSE),"")=0,"",IFERROR(VLOOKUP($A8,'VENDA 2023'!$1:$1048576,4 + (COLUMN(D5)-1)*2,FALSE),"")) | FL8: =IF(IFERROR(VLOOKUP($A8,'VENDA 2023'!$1:$1048576,4 + (COLUMN(E5)-1)*2,FALSE),"")=0,"",IFERROR(VLOOKUP($A8,'VENDA 2023'!$1:$1048576,4 + (COLUMN(E5)-1)*2,FALSE),"")) | FM8: =IF(IFERROR(VLOOKUP($A8,'VENDA 2023'!$1:$1048576,4 + (COLUMN(F5)-1)*2,FALSE),"")=0,"",IFERROR(VLOOKUP($A8,'VENDA 2023'!$1:$1048576,4 + (COLUMN(F5)-1)*2,FALSE),"")) | FN8: =IF(IFERROR(VLOOKUP($A8,'VENDA 2023'!$1:$1048576,4 + (COLUMN(G5)-1)*2,FALSE),"")=0,"",IFERROR(VLOOKUP($A8,'VENDA 2023'!$1:$1048576,4 + (COLUMN(G5)-1)*2,FALSE),"")) | FO8: =IF(IFERROR(VLOOKUP($A8,'VENDA 2023'!$1:$1048576,4 + (COLUMN(H5)-1)*2,FALSE),"")=0,"",IFERROR(VLOOKUP($A8,'VENDA 2023'!$1:$1048576,4 + (COLUMN(H5)-1)*2,FALSE),"")) | ... FS8: =IF(IFERROR(VLOOKUP($A8,'VENDA 2023'!$1:$1048576,4 + (COLUMN(L5)-1)*2,FALSE),"")=0,"",IFERROR(VLOOKUP($A8,'VENDA 2023'!$1:$1048576,4 + (COLUMN(L5)-1)*2,FALSE),"")) | FT8: =IF(COUNT(FH8:FS8)=0,"",SUM(FH8:FS8)) | FU8: =IF(IFERROR(VLOOKUP($A8,'VENDA 2024'!$1:$1048576,4 + (COLUMN(A5)-1)*2,FALSE),"")=0,"",IFERROR(VLOOKUP($A8,'VENDA 2024'!$1:$1048576,4 + (COLUMN(A5)-1)*2,FALSE),"")) | FV8: =IF(IFERROR(VLOOKUP($A8,'VENDA 2024'!$1:$1048576,4 + (COLUMN(B5)-1)*2,FALSE),"")=0,"",IFERROR(VLOOKUP($A8,'VENDA 2024'!$1:$1048576,4 + (COLUMN(B5)-1)*2,FALSE),"")) | FW8: =IF(IFERROR(VLOOKUP($A8,'VENDA 2024'!$1:$1048576,4 + (COLUMN(C5)-1)*2,FALSE),"")=0,"",IFERROR(VLOOKUP($A8,'VENDA 2024'!$1:$1048576,4 + (COLUMN(C5)-1)*2,FALSE),"")) | FX8: =IF(IFERROR(VLOOKUP($A8,'VENDA 2024'!$1:$1048576,4 + (COLUMN(D5)-1)*2,FALSE),"")=0,"",IFERROR(VLOOKUP($A8,'VENDA 2024'!$1:$1048576,4 + (COLUMN(D5)-1)*2,FALSE),"")) | FY8: =IF(IFERROR(VLOOKUP($A8,'VENDA 2024'!$1:$1048576,4 + (COLUMN(E5)-1)*2,FALSE),"")=0,"",IFERROR(VLOOKUP($A8,'VENDA 2024'!$1:$1048576,4 + (COLUMN(E5)-1)*2,FALSE),"")) | FZ8: =IF(IFERROR(VLOOKUP($A8,'VENDA 2024'!$1:$1048576,4 + (COLUMN(F5)-1)*2,FALSE),"")=0,"",IFERROR(VLOOKUP($A8,'VENDA 2024'!$1:$1048576,4 + (COLUMN(F5)-1)*2,FALSE),"")) | GA8: =IF(IFERROR(VLOOKUP($A8,'VENDA 2024'!$1:$1048576,4 + (COLUMN(G5)-1)*2,FALSE),"")=0,"",IFERROR(VLOOKUP($A8,'VENDA 2024'!$1:$1048576,4 + (COLUMN(G5)-1)*2,FALSE),"")) | GB8: =IF(IFERROR(VLOOKUP($A8,'VENDA 2024'!$1:$1048576,4 + (COLUMN(H5)-1)*2,FALSE),"")=0,"",IFERROR(VLOOKUP($A8,'VENDA 2024'!$1:$1048576,4 + (COLUMN(H5)-1)*2,FALSE),"")) | ... GF8: =IF(IFERROR(VLOOKUP($A8,'VENDA 2024'!$1:$1048576,4 + (COLUMN(L5)-1)*2,FALSE),"")=0,"",IFERROR(VLOOKUP($A8,'VENDA 2024'!$1:$1048576,4 + (COLUMN(L5)-1)*2,FALSE),"")) | GG8: =IF(COUNT(FU8:GF8)=0,"",SUM(FU8:GF8)) | GH8: =IF(IFERROR(VLOOKUP($A8,'venda-fornecedor-12-meses-7'!$1:$1048576,5 + (COLUMN(A5)-1)*2,FALSE),"")=0,"",IFERROR(VLOOKUP($A8,'venda-fornecedor-12-meses-7'!$1:$1048576,5 + (COLUMN(A5)-1)*2,FALSE),"")) | GI8: =IF(IFERROR(VLOOKUP($A8,'venda-fornecedor-12-meses-7'!$1:$1048576,5 + (COLUMN(B5)-1)*2,FALSE),"")=0,"",IFERROR(VLOOKUP($A8,'venda-fornecedor-12-meses-7'!$1:$1048576,5 + (COLUMN(B5)-1)*2,FALSE),"")) | GJ8: =IF(IFERROR(VLOOKUP($A8,'venda-fornecedor-12-meses-7'!$1:$1048576,5 + (COLUMN(C5)-1)*2,FALSE),"")=0,"",IFERROR(VLOOKUP($A8,'venda-fornecedor-12-meses-7'!$1:$1048576,5 + (COLUMN(C5)-1)*2,FALSE),"")) | GK8: =IF(IFERROR(VLOOKUP($A8,'venda-fornecedor-12-meses-7'!$1:$1048576,5 + (COLUMN(D5)-1)*2,FALSE),"")=0,"",IFERROR(VLOOKUP($A8,'venda-fornecedor-12-meses-7'!$1:$1048576,5 + (COLUMN(D5)-1)*2,FALSE),"")) | GL8: =IF(IFERROR(VLOOKUP($A8,'venda-fornecedor-12-meses-7'!$1:$1048576,5 + (COLUMN(E5)-1)*2,FALSE),"")=0,"",IFERROR(VLOOKUP($A8,'venda-fornecedor-12-meses-7'!$1:$1048576,5 + (COLUMN(E5)-1)*2,FALSE),"")) | GM8: =IF(IFERROR(VLOOKUP($A8,'venda-fornecedor-12-meses-7'!$1:$1048576,5 + (COLUMN(F5)-1)*2,FALSE),"")=0,"",IFERROR(VLOOKUP($A8,'venda-fornecedor-12-meses-7'!$1:$1048576,5 + (COLUMN(F5)-1)*2,FALSE),"")) | GN8: =IF(IFERROR(VLOOKUP($A8,'venda-fornecedor-12-meses-7'!$1:$1048576,5 + (COLUMN(G5)-1)*2,FALSE),"")=0,"",IFERROR(VLOOKUP($A8,'venda-fornecedor-12-meses-7'!$1:$1048576,5 + (COLUMN(G5)-1)*2,FALSE),"")) | GO8: =IF(IFERROR(VLOOKUP($A8,'venda-fornecedor-12-meses-7'!$1:$1048576,5 + (COLUMN(H5)-1)*2,FALSE),"")=0,"",IFERROR(VLOOKUP($A8,'venda-fornecedor-12-meses-7'!$1:$1048576,5 + (COLUMN(H5)-1)*2,FALSE),"")) | ... GS8: =IF(IFERROR(VLOOKUP($A8,'venda-fornecedor-12-meses-7'!$1:$1048576,5 + (COLUMN(L5)-1)*2,FALSE),"")=0,"",IFERROR(VLOOKUP($A8,'venda-fornecedor-12-meses-7'!$1:$1048576,5 + (COLUMN(L5)-1)*2,FALSE),"")) | GT8: =IF(COUNT(GH8:GS8)=0,"",SUM(GH8:GS8))
